Workbook

Sheet 0分
A1: 周 | B1: 5^0 | C1: 地 | D1: Σ | E1: 0₦t | F1: ∀₦t | G1: فجر | I1: شروق | K1: صباح | M1: ظهر | O1: عصر | Q1: آصيل | S1: غروب | U1: غسق | W1: صدفة | Y1: -1₦ | Z1: 0₲ | AA1: i9 | AB1: m7 | AC1: 个 | AD1: 媒 | AE1: 思 | AF1: hcb | AG1: 家 | AH1: 社 | AI1: n156 | AL1: 1₲
A2: 1.1 | B2: 45662 | C2: sf21 | D2: =SUM(Y2:AH2) | E2: ='0₦'!AF5 | F2: ='0₦'!AG5 | K2: 1 | L2: 303 | M2: 1 | N2: 273 | O2: 1 | P2: 281 | Q2: 1 | R2: 211 | S2: 1 | T2: 183 | U2: 1 | V2: 386 | W2: 1 | X2: =D2-SUM(H2,J2,L2,N2,P2,R2,T2,V2) | Y2: =12*COUNT(G2,I2,K2,M2,O2,Q2,U2,W2,S2) | Z2: =9+40+100 | AA2: ='0₦'!BI5 + 30 | AB2: ='0₦'!BE5 + 30 + 50 + 30 + 30 + 16 + 30 + 20 + 10 + 30 + 20 + 10 | AC2: ='0₦'!BC5 + 5+10 + 10 + 30 + 20 + 20 + 20 + 20 + 20 + 20 + 20 + 20 + 15+20 + 20 + 40 | AD2: ='0₦'!BD5 | AE2: ='0₦'!AX5 | AF2: =hcbi!AA6+hcbi!Y6 | AG2: ='0₦'!AW5 + 5 + 60 + 120 + 60 + 15 + 60 + 40 | AH2: =0 | AI2: #VALUE! | AJ2: #VALUE! | AK2: 577 | AL2: 184
B3: =B2+1 | C3: sf21 | D3: =SUM(Y3:AH3) | E3: ='0₦'!AF6 | F3: ='0₦'!AG6 | I3: 1 | J3: 251 | K3: 1 | L3: 373 | M3: 1 | N3: 154 | O3: 1 | P3: 139 | Q3: 1 | R3: 145 | S3: 1 | T3: 153 | U3: 1 | V3: 225 | W3: 1 | X3: =D3-SUM(H3,J3,L3,N3,P3,R3,T3,V3) | Y3: =12*COUNT(G3,I3,K3,M3,O3,Q3,U3,W3,S3) | Z3: =9+40 + 80 + 50 | AA3: ='0₦'!BI6 + 30 + 40 + 51 + '1₦+'!AA4 + 60 + 10+'1₦+'!K4 + 45 + 10 + 30 + 30 | AB3: ='0₦'!BE6 + 30 | AC3: ='0₦'!BC6 + 40 + 20 + 10 + 5 + '0₦'!K4+'0₦'!M4+'0₦'!E61 + 10 + 160 | AD3: ='0₦'!BD6 | AE3: =19+20 | AF3: =hcbi!AA7+hcbi!Y7 | AG3: ='0₦'!AW6 + 15 | AH3: =0 | AK3: 699 | AL3: 137
B4: =B3+1 | C4: SEA | D4: =SUM(Y4:AH4) | E4: ='0₦'!AF7 | F4: ='0₦'!AG7 | G4: 1 | H4: 12 | I4: 1 | J4: 321 | K4: 1 | L4: 208 | M4: 1 | N4: 223 | O4: 1 | P4: 205 | Q4: 1 | R4: 200 | S4: 1 | T4: 200 | U4: 1 | V4: 80 | W4: 1 | X4: =D4-SUM(H4,J4,L4,N4,P4,R4,T4,V4) | Y4: =12*COUNT(G4,I4,K4,M4,O4,Q4,U4,W4,S4) | Z4: =9+50+30+50 | AA4: ='0₦'!BI7 + 10 + 15 + 30 + 15 + 7 + 10 + 150 - 20+45+30+30 +50 | AB4: ='0₦'!BE7 + 6 + 10 + 15 + 10 + 10 | AC4: ='0₦'!BC7 + 15 + 7 + 20 + 10 + 43 | AD4: ='0₦'!BD7 | AE4: ='0₦'!AX7+15+'1₦+'!W4+'1₦+'!U4 | AF4: =hcbi!AA8+hcbi!Y8 | AG4: ='0₦'!AW7 + 15 + 20 + 30 | AH4: 240 | AI4: #VALUE! | AJ4: #VALUE! | AK4: 770 | AL4: 103
B5: =B4+1 | C5: SEA | D5: =SUM(Y5:AH5) | E5: ='0₦'!AF8 | F5: ='0₦'!AG8 | I5: 1 | J5: 140 | K5: 1 | L5: 187 | M5: 1 | N5: 250 | O5: 1 | P5: 130 | Q5: 1 | R5: 318 | S5: 1 | T5: 134 | U5: 1 | V5: 120 | W5: 1 | X5: =D5-SUM(H5,J5,L5,N5,P5,R5,T5,V5) | Y5: =12*COUNT(G5,I5,K5,M5,O5,Q5,U5,W5,S5) | Z5: =9+40+60+40 | AA5: ='0₦'!BI8 + 340 + 40 + 30 + 30 + 60 + 200 - 20 | AB5: ='0₦'!BE8 + 30 + 20 | AC5: ='0₦'!BC8 + 0 | AD5: ='0₦'!BD8 | AE5: ='0₦'!AX8 | AF5: =hcbi!AA9+hcbi!Y9 | AG5: ='0₦'!AW8 | AH5: =90+20 + 30 | AK5: 867 | AL5: 136
B6: =B5+1 | C6: SEA | D6: =SUM(Y6:AH6) | E6: ='0₦'!AF9 | F6: ='0₦'!AG9 | G6: 1 | H6: 12 | I6: 1 | J6: 335 | K6: 1 | L6: 307 | M6: 1 | N6: 170 | O6: 1 | P6: 207 | Q6: 1 | R6: 200 | S6: 1 | T6: 205 | U6: 1 | V6: 100 | W6: 1 | X6: =D6-SUM(H6,J6,L6,N6,P6,R6,T6,V6) | Y6: =12*COUNT(G6,I6,K6,M6,O6,Q6,U6,W6,S6) | Z6: =9 + 30 | AA6: ='0₦'!BI9+100*1.5+120+10+64+3+20 + 20 + 10 + 10 + 20 + 30 + 45 + 30 | AB6: ='0₦'!BE9 | AC6: ='0₦'!BC9 + 200 | AD6: ='0₦'!BD9 | AE6: ='0₦'!AX9 | AF6: =hcbi!AA10+hcbi!Y10 | AG6: ='0₦'!AW9 | AH6: =90 + 67 | AI6: #VALUE! | AJ6: #VALUE! | AK6: 839 | AL6: 74
B7: =B6+1 | C7: sf21 | D7: =SUM(Y7:AH7) | E7: ='0₦'!AF10 | F7: ='0₦'!AG10 | G7: 1 | H7: 12 | I7: 1 | J7: 12 | K7: 1 | L7: 277 | M7: 1 | N7: 212 | O7: 1 | P7: 302 | Q7: 1 | R7: 309 | S7: 1 | T7: 304 | U7: 1 | V7: 100 | W7: 1 | X7: =D7-SUM(H7,J7,L7,N7,P7,R7,T7,V7) | Y7: =12*COUNT(G7,I7,K7,M7,O7,Q7,U7,W7,S7) | Z7: =9+50 + 50 + 40 + 20 | AA7: ='0₦'!BI10 + 300 + 30 + 60 + 14*8 + 15 + 100 + 10 + 30 | AB7: ='0₦'!BE10 + 10 + 10 | AC7: ='0₦'!BC10 + 20 + 20 + 20 + 15 + 26 | AD7: ='0₦'!BD10 | AE7: ='0₦'!AX10 + 30 | AF7: =hcbi!AA11+hcbi!Y11 + 25 | AG7: ='0₦'!AW10 | AH7: =24 + 60 + 20 + 20 | AK7: 890 | AL7: 69
B8: =B7+1 | C8: sf21 | D8: =SUM(Y8:AH8) | E8: ='0₦'!AF11 | F8: ='0₦'!AG11 | G8: 1 | H8: 12 | I8: 1 | J8: 205 | K8: 1 | L8: 315 | M8: 1 | N8: =450-53 | O8: 1 | P8: 209 | Q8: 1 | R8: 142 | S8: 1 | T8: 125 | U8: 1 | V8: 298 | W8: 1 | X8: =D8-SUM(H8,J8,L8,N8,P8,R8,T8,V8) | Y8: =12*COUNT(G8,I8,K8,M8,O8,Q8,U8,W8,S8) | Z8: =9+50 + 30 + 10 + 30 + 30 + 40 | AA8: ='0₦'!BI11 + 10 + 30 | AB8: ='0₦'!BE11 + 25 + 10 + 10 + 30 | AC8: ='0₦'!BC11 + 0 - 26 + 70 + 10 + 20 + 25 | AD8: ='0₦'!BD11 | AE8: ='0₦'!AX11 + 30 | AF8: =hcbi!AA12+hcbi!Y12 | AG8: ='0₦'!AW11 + 60 + 30 + 30 + 60 + 17 + 35 + 30 + 15 + 20 + 30 | AH8: =120+15 + 180 | AI8: #VALUE! | AJ8: #VALUE! | AK8: 723 | AL8: 74
A9: =A2+0.1 | B9: =B8+1 | C9: sf21 | D9: =SUM(Y9:AH9) | E9: ='0₦'!AF12 | F9: ='0₦'!AG12 | G9: 1 | H9: 12 | I9: 1 | J9: 270 | K9: 1 | L9: 180 | M9: 1 | N9: 277 | O9: 1 | P9: 326 | Q9: 1 | R9: 300 | S9: 1 | T9: 292 | U9: 1 | V9: 145 | W9: 1 | X9: =D9-SUM(H9,J9,L9,N9,P9,R9,T9,V9) | Y9: =12*COUNT(G9,I9,K9,M9,O9,Q9,U9,W9,S9) | Z9: =9+60 + 30 + 40 + 100 + 30 + 30 | AA9: ='0₦'!BI12 + 45 + 90 - 10 | AB9: ='0₦'!BE12 + 30 + 30 + 10 + 30 + 90 + 30 | AC9: ='0₦'!BC12 + 10+'1₦+'!C5+'1₦+'!D5 + '1₦+'!T104 + 40 + 26 | AD9: ='0₦'!BD12 | AE9: ='0₦'!AX12 | AF9: =hcbi!AA13+hcbi!Y13 | AG9: ='0₦'!AW12 | AH9: =15+120 + 180 | AK9: 697 | AL9: 23
B10: =B9+1 | C10: sf21 | D10: =SUM(Y10:AH10) | E10: ='0₦'!AF13 | F10: ='0₦'!AG13 | I10: 1 | J10: 194 | K10: 1 | L10: 130 | M10: 1 | N10: 115 | O10: 1 | P10: 78 | S10: 1 | T10: 165 | U10: 1 | V10: 125 | W10: 1 | X10: =D10-SUM(H10,J10,L10,N10,P10,R10,T10,V10) | Y10: =12*COUNT(G10,I10,K10,M10,O10,Q10,U10,W10,S10) | Z10: =9+30+50 | AA10: ='0₦'!BI13 + 25 + 30 + 10 + 30 + 60 - 10 - 20 | AB10: ='0₦'!BE13 + 30 | AC10: ='0₦'!BC13 + -26 + 20 + 15 | AD10: ='0₦'!BD13 | AE10: ='0₦'!AX13 | AF10: =hcbi!AA14+hcbi!Y14 | AG10: ='0₦'!AW13 + 10 | AH10: 26 | AI10: #VALUE! | AJ10: #VALUE! | AK10: 755 | AL10: 266
B11: =B10+1 | C11: sf21 | D11: =SUM(Y11:AH11) | E11: ='0₦'!AF14 | F11: ='0₦'!AG14 | K11: 1 | L11: 224 | M11: 1 | N11: 220 | O11: 1 | P11: 103 | Q11: 1 | R11: 153 | S11: 1 | T11: 163 | U11: 1 | V11: 176 | W11: 1 | X11: =D11-SUM(H11,J11,L11,N11,P11,R11,T11,V11) | Y11: =12*COUNT(G11,I11,K11,M11,O11,Q11,U11,W11,S11) | Z11: =IF(AND('0₦'!T14<>0,'0₦'!T14<>""),9,0) + 40 + 30 | AA11: ='0₦'!BI14 + 30+30 + 60 + 30 + 10 + 30 + 10 + 30 + 30 + 30 | AB11: ='0₦'!BE14 + 30 + 10 + 10 | AC11: ='0₦'!BC14 + '1₦+'!X5 | AD11: ='0₦'!BD14 | AE11: ='0₦'!AX14 | AF11: =hcbi!AA15+hcbi!Y15 | AG11: ='0₦'!AW14 + 23 + '1₦+'!P5 + SUM('1₦+'!N5:O5) | AH11: =0 | AK11: =760 | AL11: 507
B12: =B11+1 | C12: sf21 | D12: =SUM(Y12:AH12) | E12: ='0₦'!AF15 | F12: ='0₦'!AG15 | I12: 1 | J12: 168 | K12: 1 | L12: 229 | M12: 1 | N12: 266 | O12: 1 | P12: 229 | Q12: 1 | R12: 193 | S12: 1 | T12: 144 | U12: 1 | V12: 177 | W12: 1 | X12: =D12-SUM(H12,J12,L12,N12,P12,R12,T12,V12) | Y12: =12*COUNT(G12,I12,K12,M12,O12,Q12,U12,W12,S12) | Z12: =IF(AND('0₦'!T15<>0,'0₦'!T15<>""),9,0) + 15 + 20 + 30 + 15 + 100 | AA12: ='0₦'!BI15 + 30 + 40 + 30 + 20 + 30 + 5 + 10 + 10 + 25 + 30 + 30 + 10 + 60 | AB12: ='0₦'!BE15 + 35 + 100 + 20 + 10 + 21 | AC12: ='0₦'!BC15 + 30 | AD12: ='0₦'!BD15 | AE12: ='0₦'!AX15+'1₦+'!U5 | AF12: =hcbi!AA16+hcbi!Y16 + 25 | AG12: ='0₦'!AW15 | AH12: =0+15+'1₦+'!R5+10+'1₦+'!R4 + 20 + 7 | AI12: #VALUE! | AJ12: #VALUE! | AK12: 777 | AL12: 569
B13: =B12+1 | C13: SEA | D13: =SUM(Y13:AH13) | E13: ='0₦'!AF16 | F13: ='0₦'!AG16 | G13: 1 | H13: 12 | I13: 1 | J13: 12 | K13: 1 | L13: 298 | M13: 1 | N13: 145 | O13: 1 | P13: 271 | Q13: 1 | R13: 127 | S13: 1 | T13: 118 | U13: 1 | V13: 245 | X13: =D13-SUM(H13,J13,L13,N13,P13,R13,T13,V13) | Y13: =12*COUNT(G13,I13,K13,M13,O13,Q13,U13,W13,S13) | Z13: =IF(AND('0₦'!T16<>0,'0₦'!T16<>""),9,0) + 20 | AA13: ='0₦'!BI16 + 10+35 + 40 + 30 + 90 + 60 + 30 + 45 + 30 + 30 + 30 - 20 + 20 | AB13: ='0₦'!BE16 + 100 + 15 + 10 | AC13: ='0₦'!BC16 + 12 | AD13: ='0₦'!BD16 | AE13: ='0₦'!AX16 + 14 | AF13: =hcbi!AA17+hcbi!Y17 + 20 | AG13: ='0₦'!AW16 | AH13: =150 | AK13: 690 | AL13: 89
B14: =B13+1 | C14: SEA | D14: =SUM(Y14:AH14) | E14: ='0₦'!AF17 | F14: ='0₦'!AG17 | G14: 1 | H14: 12 | I14: 1 | J14: 75 | K14: 1 | L14: 499 | M14: 1 | N14: 148 | O14: 1 | P14: 168 | Q14: 1 | R14: 171 | S14: 1 | T14: 187 | U14: 1 | V14: 227 | W14: 1 | X14: =D14-SUM(H14,J14,L14,N14,P14,R14,T14,V14) | Y14: =12*COUNT(G14,I14,K14,M14,O14,Q14,U14,W14,S14) | Z14: =IF(AND('0₦'!T17<>0,'0₦'!T17<>""),9,0) + 60 + 30 + 80 + 40 + 30 | AA14: ='0₦'!BI17 + 10 + 300 - 15 + 10 + 20 + 40 + 60 + 30 | AB14: ='0₦'!BE17+30 + 10 + 250 + 15 + 10 + 45 | AC14: ='0₦'!BC17 + 5 + 15 + 20 + 10 | AD14: ='0₦'!BD17+'1₦+'!S5 | AE14: ='0₦'!AX17+'1₦+'!W5 + 18 | AF14: =hcbi!AA18+hcbi!Y18 + 15 | AG14: ='0₦'!AW17 | AH14: =7 + 30 + 10 + 35 + 10 | AI14: #VALUE! | AJ14: #VALUE! | AK14: 583 | AL14: 57
B15: =B14+1 | C15: sf21 | D15: =SUM(Y15:AH15) | E15: ='0₦'!AF18 | F15: ='0₦'!AG18 | G15: 1 | H15: 14 | I15: 1 | J15: 232 | K15: 1 | L15: 229 | M15: 1 | N15: 200 | O15: 1 | P15: 200 | Q15: 1 | R15: 200 | S15: 1 | T15: 200 | U15: 1 | V15: 205 | W15: 1 | X15: =D15-SUM(H15,J15,L15,N15,P15,R15,T15,V15) | Y15: =12*COUNT(G15,I15,K15,M15,O15,Q15,U15,W15,S15) | Z15: =IF(AND('0₦'!T18<>0,'0₦'!T18<>""),9,0) + 70 + 150+ 30 + 40 | AA15: ='0₦'!BI18+10 | AB15: ='0₦'!BE18+25 | AC15: ='0₦'!BC18 + 60 + 3 | AD15: ='0₦'!BD18 | AE15: ='0₦'!AX18 | AF15: =hcbi!AA19+hcbi!Y19 | AG15: ='0₦'!AW18 + 30 + 30 + 120 + 30 | AH15: =120 | AK15: 379 | AL15: 164
A16: =A9+0.1 | B16: =B15+1 | C16: sf21 | D16: =SUM(Y16:AH16) | E16: ='0₦'!AF19 | F16: ='0₦'!AG19 | G16: 1 | H16: 12 | I16: 1 | J16: 249 | K16: 1 | L16: 187 | M16: 1 | N16: 125 | O16: 1 | P16: 213 | Q16: 1 | R16: 215 | S16: 1 | T16: 200 | U16: 1 | V16: 150 | W16: 1 | X16: =D16-SUM(H16,J16,L16,N16,P16,R16,T16,V16) | Y16: =12*COUNT(G16,I16,K16,M16,O16,Q16,U16,W16,S16) | Z16: =IF(AND('0₦'!T19<>0,'0₦'!T19<>""),9,0) + 50 + 90 + 60 | AA16: ='0₦'!BI19 + 0 | AB16: ='0₦'!BE19 + 30 + 10 + 15 + 30 + 30 + 30 + 15 +15 + 20 + 30 + 20 + 36 + 10 + 100 | AC16: ='0₦'!BC19 + 60 + 20 | AD16: ='0₦'!BD19 | AE16: ='0₦'!AX19 | AF16: =hcbi!AA20+hcbi!Y20 | AG16: ='0₦'!AW19 + 60 + 90 + 60 | AH16: =0 | AI16: #VALUE! | AJ16: #VALUE! | AK16: 463 | AL16: 196
B17: =B16+1 | C17: sf21 | D17: =SUM(Y17:AH17) | E17: ='0₦'!AF20 | F17: ='0₦'!AG20 | K17: 1 | L17: 200 | M17: 1 | N17: 200 | O17: 1 | P17: 200 | Q17: 1 | R17: 200 | S17: 1 | T17: 195 | U17: 1 | V17: =D17-SUM(H17,J17,L17,N17,P17,R17,T17) | Y17: =12*COUNT(G17,I17,K17,M17,O17,Q17,U17,W17,S17) | Z17: =9+60 + 30 + 45 | AA17: ='0₦'!BI20 + -5 - 20 | AB17: ='0₦'!BE20 - 15 | AC17: ='0₦'!BC20 + 60 - 10 - 20 | AD17: ='0₦'!BD20 | AE17: ='0₦'!AX20 | AF17: =hcbi!AA21+hcbi!Y21 | AG17: ='0₦'!AW20 + 30 + 120 + 120 + 120 + 180 | AH17: =20+20+20+20 + 10 | AK17: 774 | AL17: 904
B18: =B17+1 | C18: sf21 | D18: =SUM(Y18:AH18) | E18: ='0₦'!AF21 | F18: ='0₦'!AG21 | I18: 1 | J18: 132 | K18: 1 | L18: 302 | M18: 1 | N18: 132 | O18: 1 | P18: 242 | Q18: 1 | R18: 305 | S18: 1 | T18: 208 | U18: 1 | V18: =D18-SUM(H18,J18,L18,N18,P18,R18,T18) | W18: 1 | X18: =D18-SUM(H18,J18,L18,N18,P18,R18,T18,V18) | Y18: =12*COUNT(G18,I18,K18,M18,O18,Q18,U18,W18,S18) | Z18: =IF(AND('0₦'!T21<>0,'0₦'!T21<>""),9,0) + 60 + 40 + 40 + 40 | AA18: ='0₦'!BI21 + 35 + 10 + 5 + 20 + 30 + 30 + 30 + 50 + 30 + 30 + 10 | AB18: ='0₦'!BE21 + 15 + 20 + 100 + 30 + 10 + 7 | AC18: ='0₦'!BC21 + 10 + 20 + 5 - 26 | AD18: ='0₦'!BD21 | AE18: ='0₦'!AX21 + 21 | AF18: =hcbi!AA22+hcbi!Y22 + 20 | AG18: ='0₦'!AW21+10 + 15 + 30 + 20 | AH18: =20+20 | AI18: #VALUE! | AJ18: #VALUE! | AK18: 845 | AL18: 343
B19: =B18+1 | C19: SEA | D19: =SUM(Y19:AH19) | E19: ='0₦'!AF22 | F19: ='0₦'!AG22 | G19: 1 | H19: 12 | I19: 1 | J19: 233 | K19: 1 | L19: 135 | M19: 1 | N19: 234 | O19: 1 | P19: 120 | Q19: 1 | R19: 151 | S19: 1 | T19: 239 | U19: 1 | V19: 200 | W19: 1 | X19: =D19-SUM(H19,J19,L19,N19,P19,R19,T19,V19) | Y19: =12*COUNT(G19,I19,K19,M19,O19,Q19,U19,W19,S19) | Z19: =IF(AND('0₦'!T22<>0,'0₦'!T22<>""),9,0) + 80 + 60 + 40 + 40 | AA19: ='0₦'!BI22 + 60 + 20 + 20 + 40 + 45 + 40 + 30*6 + 30 - 20 | AB19: ='0₦'!BE22 + 50 + 15 + 100 | AC19: ='0₦'!BC22 + 26 + 15 | AD19: ='0₦'!BD22 | AE19: ='0₦'!AX22 + 15 | AF19: =hcbi!AA23+hcbi!Y23 | AG19: ='0₦'!AW22 | AH19: =10 + 20 + 120 + 21 | AK19: 757 | AL19: 533
B20: =B19+1 | C20: SEA | D20: =SUM(Y20:AH20) | E20: ='0₦'!AF23 | F20: ='0₦'!AG23 | G20: 1 | H20: 12 | I20: 1 | J20: 343 | K20: 1 | L20: 303 | M20: 1 | N20: 212 | O20: 1 | P20: 114 | Q20: 1 | R20: 193 | S20: 1 | T20: 231 | U20: 1 | V20: 221 | W20: 1 | X20: =D20-SUM(H20,J20,L20,N20,P20,R20,T20,V20) | Y20: =12*COUNT(G20,I20,K20,M20,O20,Q20,U20,W20,S20) | Z20: =IF(AND('0₦'!T23<>0,'0₦'!T23<>""),9,0) + 50 + 30 + 40 + 46 | AA20: ='0₦'!BI23 + 60 + 30 + 30 + 40 + 10 + 30 + 30 + 20 + 10 + 30 + 30 + 25 - 20 | AB20: ='0₦'!BE23 + 10 + 45 + 15 + 100 + 30+'1₦+'!G6 | AC20: ='0₦'!BC23 + 20+'1₦+'!L6+'1₦+'!D6+'1₦+'!C6 | AD20: ='0₦'!BD23 + 10 | AE20: ='0₦'!AX23 + '1₦+'!Z7 + 30 + 30 + 30 + 25 + 30 + 11 | AF20: =hcbi!AA24+hcbi!Y24 + 15 | AG20: ='0₦'!AW23 | AH20: =25 + 10 | AI20: #VALUE! | AK20: 764 | AL20: 258
B21: =B20+1 | C21: SEA | D21: =SUM(Y21:AH21) | E21: ='0₦'!AF24 | F21: ='0₦'!AG24 | G21: 1 | H21: 12 | I21: 1 | J21: 90 | K21: 1 | L21: 379 | M21: 1 | N21: 212 | O21: 1 | P21: 200 | Q21: 1 | R21: 107 | S21: 1 | T21: 283 | U21: 1 | V21: 115 | W21: 1 | X21: =D21-SUM(H21,J21,L21,N21,P21,R21,T21,V21) | Y21: =12*COUNT(G21,I21,K21,M21,O21,Q21,U21,W21,S21) | Z21: =IF(AND('0₦'!T24<>0,'0₦'!T24<>""),9,0) + 50 + 20 + 20 | AA21: ='0₦'!BI24 + 40 + 300 + 45 + 30 + 30 + 30 | AB21: ='0₦'!BE24 + 30 + 15 +30 | AC21: ='0₦'!BC24 + '1₦+'!Y6 + 20 | AD21: ='0₦'!BD24 | AE21: ='0₦'!AX24 | AF21: =hcbi!AA25+hcbi!Y25 | AG21: ='0₦'!AW24 + 30 | AH21: =30 + 100 | AK21: 750 | AL21: 402
B22: =B21+1 | C22: sf21 | D22: =SUM(Y22:AH22) | E22: ='0₦'!AF25 | F22: ='0₦'!AG25 | G22: 1 | H22: 12 | I22: 1 | J22: =D22-H22 | L22: =D22-SUM(H22,J22) | N22: =D22-SUM(H22,J22,L22,) | P22: =D22-SUM(H22,J22,L22,N22) | R22: =D22-SUM(H22,J22,L22,N22,P22) | T22: =D22-SUM(H22,J22,L22,N22,P22,R22) | V22: =D22-SUM(H22,J22,L22,N22,P22,R22,T22) | X22: =D22-SUM(H22,J22,L22,N22,P22,R22,T22,V22) | Y22: =12*COUNT(G22,I22,K22,M22,O22,Q22,U22,W22,S22) | Z22: =IF(AND('0₦'!T25<>0,'0₦'!T25<>""),9,0) + 0 | AA22: ='0₦'!BI25 + 0 | AB22: ='0₦'!BE25 | AC22: ='0₦'!BC25 + 0 | AD22: ='0₦'!BD25 | AE22: ='0₦'!AX25 | AF22: =hcbi!AA26+hcbi!Y26 | AG22: ='0₦'!AW25 | AH22: =0 | AK22: 768 | AL22: 116
A23: =A16+0.1 | B23: =B22+1 | C23: sf21 | D23: =SUM(Y23:AH23) | E23: ='0₦'!AF26 | F23: ='0₦'!AG26 | H23: =D23 | J23: =D23-H23 | L23: =D23-SUM(H23,J23) | N23: =D23-SUM(H23,J23,L23,) | P23: =D23-SUM(H23,J23,L23,N23) | R23: =D23-SUM(H23,J23,L23,N23,P23) | T23: =D23-SUM(H23,J23,L23,N23,P23,R23) | V23: =D23-SUM(H23,J23,L23,N23,P23,R23,T23) | X23: =D23-SUM(H23,J23,L23,N23,P23,R23,T23,V23) | Y23: =12*COUNT(G23,I23,K23,M23,O23,Q23,U23,W23,S23) | Z23: =IF(AND('0₦'!T26<>0,'0₦'!T26<>""),9,0) + 0 | AA23: ='0₦'!BI26 + 0 | AB23: ='0₦'!BE26 | AC23: ='0₦'!BC26 + 0 | AD23: ='0₦'!BD26 | AE23: ='0₦'!AX26 | AF23: =hcbi!AA27+hcbi!Y27 | AG23: ='0₦'!AW26 | AH23: =0 | AK23: 523 | AL23: 14
B24: =B23+1 | C24: sf21 | D24: =SUM(Y24:AH24) | E24: ='0₦'!AF27 | F24: ='0₦'!AG27 | H24: =D24 | J24: =D24-H24 | L24: =D24-SUM(H24,J24) | N24: =D24-SUM(H24,J24,L24,) | P24: =D24-SUM(H24,J24,L24,N24) | R24: =D24-SUM(H24,J24,L24,N24,P24) | T24: =D24-SUM(H24,J24,L24,N24,P24,R24) | V24: =D24-SUM(H24,J24,L24,N24,P24,R24,T24) | X24: =D24-SUM(H24,J24,L24,N24,P24,R24,T24,V24) | Y24: =12*COUNT(G24,I24,K24,M24,O24,Q24,U24,W24,S24) | Z24: =IF(AND('0₦'!T27<>0,'0₦'!T27<>""),9,0) + 0 | AA24: ='0₦'!BI27 + 0 | AB24: ='0₦'!BE27 | AC24: ='0₦'!BC27 + 0 | AD24: ='0₦'!BD27 | AE24: ='0₦'!AX27 | AF24: =hcbi!AA28+hcbi!Y28 | AG24: ='0₦'!AW27 | AH24: =0 | AK24: 523 | AL24: 100
B25: =B24+1 | C25: sf21 | D25: =SUM(Y25:AH25) | E25: ='0₦'!AF28 | F25: ='0₦'!AG28 | H25: =D25 | J25: =D25-H25 | L25: =D25-SUM(H25,J25) | N25: =D25-SUM(H25,J25,L25,) | P25: =D25-SUM(H25,J25,L25,N25) | R25: =D25-SUM(H25,J25,L25,N25,P25) | T25: =D25-SUM(H25,J25,L25,N25,P25,R25) | V25: =D25-SUM(H25,J25,L25,N25,P25,R25,T25) | X25: =D25-SUM(H25,J25,L25,N25,P25,R25,T25,V25) | Y25: =12*COUNT(G25,I25,K25,M25,O25,Q25,U25,W25,S25) | Z25: =IF(AND('0₦'!T28<>0,'0₦'!T28<>""),9,0) + 0 | AA25: ='0₦'!BI28 + 0 | AB25: ='0₦'!BE28 | AC25: ='0₦'!BC28 + 0 | AD25: ='0₦'!BD28 | AE25: ='0₦'!AX28 | AF25: =hcbi!AA29+hcbi!Y29 | AG25: ='0₦'!AW28 | AH25: =0 | AK25: 656 | AL25: 1000
B26: =B25+1 | C26: sf21 | D26: =SUM(Y26:AH26) | E26: ='0₦'!AF29 | F26: ='0₦'!AG29 | H26: =D26 | J26: =D26-H26 | L26: =D26-SUM(H26,J26) | N26: =D26-SUM(H26,J26,L26,) | P26: =D26-SUM(H26,J26,L26,N26) | R26: =D26-SUM(H26,J26,L26,N26,P26) | T26: =D26-SUM(H26,J26,L26,N26,P26,R26) | V26: =D26-SUM(H26,J26,L26,N26,P26,R26,T26) | X26: =D26-SUM(H26,J26,L26,N26,P26,R26,T26,V26) | Y26: =12*COUNT(G26,I26,K26,M26,O26,Q26,U26,W26,S26) | Z26: =IF(AND('0₦'!T29<>0,'0₦'!T29<>""),9,0) + 0 | AA26: ='0₦'!BI29 + 0 | AB26: ='0₦'!BE29 | AC26: ='0₦'!BC29 + 0 | AD26: ='0₦'!BD29 | AE26: ='0₦'!AX29 | AF26: =hcbi!AA30+hcbi!Y30 | AG26: ='0₦'!AW29 | AH26: =0 | AK26: 623 | AL26: 45
B27: =B26+1 | C27: sf21 | D27: =SUM(Y27:AH27) | E27: ='0₦'!AF30 | F27: ='0₦'!AG30 | H27: =D27 | J27: =D27-H27 | L27: =D27-SUM(H27,J27) | N27: =D27-SUM(H27,J27,L27,) | P27: =D27-SUM(H27,J27,L27,N27) | R27: =D27-SUM(H27,J27,L27,N27,P27) | T27: =D27-SUM(H27,J27,L27,N27,P27,R27) | V27: =D27-SUM(H27,J27,L27,N27,P27,R27,T27) | X27: =D27-SUM(H27,J27,L27,N27,P27,R27,T27,V27) | Y27: =12*COUNT(G27,I27,K27,M27,O27,Q27,U27,W27,S27) | Z27: =IF(AND('0₦'!T30<>0,'0₦'!T30<>""),9,0) + 0 | AA27: ='0₦'!BI30 + 0 | AB27: ='0₦'!BE30 | AC27: ='0₦'!BC30 + 0 | AD27: ='0₦'!BD30 | AE27: ='0₦'!AX30 | AF27: =hcbi!AA31+hcbi!Y31 | AG27: ='0₦'!AW30 | AH27: =0 | AK27: 658 | AL27: 129
B28: =B27+1 | C28: sf21 | D28: =SUM(Y28:AH28) | E28: ='0₦'!AF31 | F28: ='0₦'!AG31 | H28: =D28 | J28: =D28-H28 | L28: =D28-SUM(H28,J28) | N28: =D28-SUM(H28,J28,L28,) | P28: =D28-SUM(H28,J28,L28,N28) | R28: =D28-SUM(H28,J28,L28,N28,P28) | T28: =D28-SUM(H28,J28,L28,N28,P28,R28) | V28: =D28-SUM(H28,J28,L28,N28,P28,R28,T28) | X28: =D28-SUM(H28,J28,L28,N28,P28,R28,T28,V28) | Y28: =12*COUNT(G28,I28,K28,M28,O28,Q28,U28,W28,S28) | Z28: =IF(AND('0₦'!T31<>0,'0₦'!T31<>""),9,0) + 0 | AA28: ='0₦'!BI31 + 0 | AB28: ='0₦'!BE31 | AC28: ='0₦'!BC31 + 0 | AD28: ='0₦'!BD31 | AE28: ='0₦'!AX31 | AF28: =hcbi!AA32+hcbi!Y32 | AG28: ='0₦'!AW31 | AH28: =0 | AK28: 620 | AL28: 100
B29: =B28+1 | C29: sf21 | D29: =SUM(Y29:AH29) | E29: ='0₦'!AF32 | F29: ='0₦'!AG32 | H29: =D29 | J29: =D29-H29 | L29: =D29-SUM(H29,J29) | N29: =D29-SUM(H29,J29,L29,) | P29: =D29-SUM(H29,J29,L29,N29) | R29: =D29-SUM(H29,J29,L29,N29,P29) | T29: =D29-SUM(H29,J29,L29,N29,P29,R29) | V29: =D29-SUM(H29,J29,L29,N29,P29,R29,T29) | X29: =D29-SUM(H29,J29,L29,N29,P29,R29,T29,V29) | Y29: =12*COUNT(G29,I29,K29,M29,O29,Q29,U29,W29,S29) | Z29: =IF(AND('0₦'!T32<>0,'0₦'!T32<>""),9,0) + 0 | AA29: ='0₦'!BI32 + 0 | AB29: ='0₦'!BE32 | AC29: ='0₦'!BC32 + 0 | AD29: ='0₦'!BD32 | AE29: ='0₦'!AX32 | AF29: =hcbi!AA33+hcbi!Y33 | AG29: ='0₦'!AW32 | AH29: =0 | AK29: 652 | AL29: 10
A30: =A2+1 | B30: =B29+1 | C30: sf21 | D30: =SUM(Y30:AH30) | E30: ='0₦'!AF33 | F30: ='0₦'!AG33 | H30: =D30 | J30: =D30-H30 | L30: =D30-SUM(H30,J30) | N30: =D30-SUM(H30,J30,L30,) | P30: =D30-SUM(H30,J30,L30,N30) | R30: =D30-SUM(H30,J30,L30,N30,P30) | T30: =D30-SUM(H30,J30,L30,N30,P30,R30) | V30: =D30-SUM(H30,J30,L30,N30,P30,R30,T30) | X30: =D30-SUM(H30,J30,L30,N30,P30,R30,T30,V30) | Y30: =12*COUNT(G30,I30,K30,M30,O30,Q30,U30,W30,S30) | Z30: =IF(AND('0₦'!T33<>0,'0₦'!T33<>""),9,0) + 0 | AA30: ='0₦'!BI33 + 0 | AB30: ='0₦'!BE33 | AC30: ='0₦'!BC33 + 0 | AD30: ='0₦'!BD33 | AE30: ='0₦'!AX33 | AF30: =hcbi!AA34+hcbi!Y34 | AG30: ='0₦'!AW33 | AH30: =0 | AK30: 798 | AL30: 125
B31: =B30+1 | C31: sf21 | D31: =SUM(Y31:AH31) | E31: ='0₦'!AF34 | F31: ='0₦'!AG34 | H31: =D31 | J31: =D31-H31 | L31: =D31-SUM(H31,J31) | N31: =D31-SUM(H31,J31,L31,) | P31: =D31-SUM(H31,J31,L31,N31) | R31: =D31-SUM(H31,J31,L31,N31,P31) | T31: =D31-SUM(H31,J31,L31,N31,P31,R31) | V31: =D31-SUM(H31,J31,L31,N31,P31,R31,T31) | X31: =D31-SUM(H31,J31,L31,N31,P31,R31,T31,V31) | Y31: =12*COUNT(G31,I31,K31,M31,O31,Q31,U31,W31,S31) | Z31: =IF(AND('0₦'!T34<>0,'0₦'!T34<>""),9,0) + 0 | AA31: ='0₦'!BI34 + 0 | AB31: ='0₦'!BE34 | AC31: ='0₦'!BC34 + 0 | AD31: ='0₦'!BD34 | AE31: ='0₦'!AX34 | AF31: =hcbi!AA35+hcbi!Y35 | AG31: ='0₦'!AW34 | AH31: =0 | AK31: 702 | AL31: 329
B32: =B31+1 | C32: sf21 | D32: =SUM(Y32:AH32) | E32: ='0₦'!AF35 | F32: ='0₦'!AG35 | H32: =D32 | J32: =D32-H32 | L32: =D32-SUM(H32,J32) | N32: =D32-SUM(H32,J32,L32,) | P32: =D32-SUM(H32,J32,L32,N32) | R32: =D32-SUM(H32,J32,L32,N32,P32) | T32: =D32-SUM(H32,J32,L32,N32,P32,R32) | V32: =D32-SUM(H32,J32,L32,N32,P32,R32,T32) | X32: =D32-SUM(H32,J32,L32,N32,P32,R32,T32,V32) | Y32: =12*COUNT(G32,I32,K32,M32,O32,Q32,U32,W32,S32) | Z32: =IF(AND('0₦'!T35<>0,'0₦'!T35<>""),9,0) + 0 | AA32: ='0₦'!BI35 + 0 | AB32: ='0₦'!BE35 | AC32: ='0₦'!BC35 + 0 | AD32: ='0₦'!BD35 | AE32: ='0₦'!AX35 | AF32: =hcbi!AA36+hcbi!Y36 | AG32: ='0₦'!AW35 | AH32: =0 | AK32: 727 | AL32: 523
B33: =B32+1 | C33: sf21 | D33: =SUM(Y33:AH33) | E33: ='0₦'!AF36 | F33: ='0₦'!AG36 | H33: =D33 | J33: =D33-H33 | L33: =D33-SUM(H33,J33) | N33: =D33-SUM(H33,J33,L33,) | P33: =D33-SUM(H33,J33,L33,N33) | R33: =D33-SUM(H33,J33,L33,N33,P33) | T33: =D33-SUM(H33,J33,L33,N33,P33,R33) | V33: =D33-SUM(H33,J33,L33,N33,P33,R33,T33) | X33: =D33-SUM(H33,J33,L33,N33,P33,R33,T33,V33) | Y33: =12*COUNT(G33,I33,K33,M33,O33,Q33,U33,W33,S33) | Z33: =IF(AND('0₦'!T36<>0,'0₦'!T36<>""),9,0) + 0 | AA33: ='0₦'!BI36 + 0 | AB33: ='0₦'!BE36 | AC33: ='0₦'!BC36 + 0 | AD33: ='0₦'!BD36 | AE33: ='0₦'!AX36 | AF33: =hcbi!AA37+hcbi!Y37 | AG33: ='0₦'!AW36 | AH33: =0 | AK33: 864 | AL33: 328
B34: =B33+1 | C34: sf21 | D34: =SUM(Y34:AH34) | E34: ='0₦'!AF37 | F34: ='0₦'!AG37 | H34: =D34 | J34: =D34-H34 | L34: =D34-SUM(H34,J34) | N34: =D34-SUM(H34,J34,L34,) | P34: =D34-SUM(H34,J34,L34,N34) | R34: =D34-SUM(H34,J34,L34,N34,P34) | T34: =D34-SUM(H34,J34,L34,N34,P34,R34) | V34: =D34-SUM(H34,J34,L34,N34,P34,R34,T34) | X34: =D34-SUM(H34,J34,L34,N34,P34,R34,T34,V34) | Y34: =12*COUNT(G34,I34,K34,M34,O34,Q34,U34,W34,S34) | Z34: =IF(AND('0₦'!T37<>0,'0₦'!T37<>""),9,0) + 0 | AA34: ='0₦'!BI37 + 0 | AB34: ='0₦'!BE37 | AC34: ='0₦'!BC37 + 0 | AD34: ='0₦'!BD37 | AE34: ='0₦'!AX37 | AF34: =hcbi!AA38+hcbi!Y38 | AG34: ='0₦'!AW37 | AH34: =0 | AK34: 757 | AL34: 574
B35: =B34+1 | C35: sf21 | D35: =SUM(Y35:AH35) | E35: ='0₦'!AF38 | F35: ='0₦'!AG38 | H35: =D35 | J35: =D35-H35 | L35: =D35-SUM(H35,J35) | N35: =D35-SUM(H35,J35,L35,) | P35: =D35-SUM(H35,J35,L35,N35) | R35: =D35-SUM(H35,J35,L35,N35,P35) | T35: =D35-SUM(H35,J35,L35,N35,P35,R35) | V35: =D35-SUM(H35,J35,L35,N35,P35,R35,T35) | X35: =D35-SUM(H35,J35,L35,N35,P35,R35,T35,V35) | Y35: =12*COUNT(G35,I35,K35,M35,O35,Q35,U35,W35,S35) | Z35: =IF(AND('0₦'!T38<>0,'0₦'!T38<>""),9,0) + 0 | AA35: ='0₦'!BI38 + 0 | AB35: ='0₦'!BE38 | AC35: ='0₦'!BC38 + 0 | AD35: ='0₦'!BD38 | AE35: ='0₦'!AX38 | AF35: =hcbi!AA39+hcbi!Y39 | AG35: ='0₦'!AW38 | AH35: =0 | AK35: 930 | AL35: 517
B36: =B35+1 | C36: sf21 | D36: =SUM(Y36:AH36) | E36: ='0₦'!AF39 | F36: ='0₦'!AG39 | H36: =D36 | J36: =D36-H36 | L36: =D36-SUM(H36,J36) | N36: =D36-SUM(H36,J36,L36,) | P36: =D36-SUM(H36,J36,L36,N36) | R36: =D36-SUM(H36,J36,L36,N36,P36) | T36: =D36-SUM(H36,J36,L36,N36,P36,R36) | V36: =D36-SUM(H36,J36,L36,N36,P36,R36,T36) | X36: =D36-SUM(H36,J36,L36,N36,P36,R36,T36,V36) | Y36: =12*COUNT(G36,I36,K36,M36,O36,Q36,U36,W36,S36) | Z36: =IF(AND('0₦'!T39<>0,'0₦'!T39<>""),9,0) + 0 | AA36: ='0₦'!BI39 + 0 | AB36: ='0₦'!BE39 | AC36: ='0₦'!BC39 + 0 | AD36: ='0₦'!BD39 | AE36: ='0₦'!AX39 | AF36: =hcbi!AA40+hcbi!Y40 | AG36: ='0₦'!AW39 | AH36: =0 | AK36: 923 | AL36: 117
A37: =A30+0.1 | B37: =B36+1 | C37: sf21 | D37: =SUM(Y37:AH37) | E37: ='0₦'!AF40 | F37: ='0₦'!AG40 | H37: =D37 | J37: =D37-H37 | L37: =D37-SUM(H37,J37) | N37: =D37-SUM(H37,J37,L37,) | P37: =D37-SUM(H37,J37,L37,N37) | R37: =D37-SUM(H37,J37,L37,N37,P37) | T37: =D37-SUM(H37,J37,L37,N37,P37,R37) | V37: =D37-SUM(H37,J37,L37,N37,P37,R37,T37) | X37: =D37-SUM(H37,J37,L37,N37,P37,R37,T37,V37) | Y37: =12*COUNT(G37,I37,K37,M37,O37,Q37,U37,W37,S37) | Z37: =IF(AND('0₦'!T40<>0,'0₦'!T40<>""),9,0) + 0 | AA37: ='0₦'!BI40 + 0 | AB37: ='0₦'!BE40 | AC37: ='0₦'!BC40 + 0 | AD37: ='0₦'!BD40 | AE37: ='0₦'!AX40 | AF37: =hcbi!AA41+hcbi!Y41 | AG37: ='0₦'!AW40 | AH37: =0 | AK37: 757 | AL37: 88
B38: =B37+1 | C38: sf21 | D38: =SUM(Y38:AH38) | E38: ='0₦'!AF41 | F38: ='0₦'!AG41 | H38: =D38 | J38: =D38-H38 | L38: =D38-SUM(H38,J38) | N38: =D38-SUM(H38,J38,L38,) | P38: =D38-SUM(H38,J38,L38,N38) | R38: =D38-SUM(H38,J38,L38,N38,P38) | T38: =D38-SUM(H38,J38,L38,N38,P38,R38) | V38: =D38-SUM(H38,J38,L38,N38,P38,R38,T38) | X38: =D38-SUM(H38,J38,L38,N38,P38,R38,T38,V38) | Y38: =12*COUNT(G38,I38,K38,M38,O38,Q38,U38,W38,S38) | Z38: =IF(AND('0₦'!T41<>0,'0₦'!T41<>""),9,0) + 0 | AA38: ='0₦'!BI41 + 0 | AB38: ='0₦'!BE41 | AC38: ='0₦'!BC41 + 0 | AD38: ='0₦'!BD41 | AE38: ='0₦'!AX41 | AF38: =hcbi!AA42+hcbi!Y42 | AG38: ='0₦'!AW41 | AH38: =0 | AK38: 917 | AL38: 515
B39: =B38+1 | C39: sf21 | D39: =SUM(Y39:AH39) | E39: ='0₦'!AF42 | F39: ='0₦'!AG42 | H39: =D39 | J39: =D39-H39 | L39: =D39-SUM(H39,J39) | N39: =D39-SUM(H39,J39,L39,) | P39: =D39-SUM(H39,J39,L39,N39) | R39: =D39-SUM(H39,J39,L39,N39,P39) | T39: =D39-SUM(H39,J39,L39,N39,P39,R39) | V39: =D39-SUM(H39,J39,L39,N39,P39,R39,T39) | X39: =D39-SUM(H39,J39,L39,N39,P39,R39,T39,V39) | Y39: =12*COUNT(G39,I39,K39,M39,O39,Q39,U39,W39,S39) | Z39: =IF(AND('0₦'!T42<>0,'0₦'!T42<>""),9,0) + 0 | AA39: ='0₦'!BI42 + 0 | AB39: ='0₦'!BE42 | AC39: ='0₦'!BC42 + 0 | AD39: ='0₦'!BD42 | AE39: ='0₦'!AX42 | AF39: =hcbi!AA43+hcbi!Y43 | AG39: ='0₦'!AW42 | AH39: =0 | AK39: 895 | AL39: 195
B40: =B39+1 | C40: sf21 | D40: =SUM(Y40:AH40) | E40: ='0₦'!AF43 | F40: ='0₦'!AG43 | H40: =D40 | J40: =D40-H40 | L40: =D40-SUM(H40,J40) | N40: =D40-SUM(H40,J40,L40,) | P40: =D40-SUM(H40,J40,L40,N40) | R40: =D40-SUM(H40,J40,L40,N40,P40) | T40: =D40-SUM(H40,J40,L40,N40,P40,R40) | V40: =D40-SUM(H40,J40,L40,N40,P40,R40,T40) | X40: =D40-SUM(H40,J40,L40,N40,P40,R40,T40,V40) | Y40: =12*COUNT(G40,I40,K40,M40,O40,Q40,U40,W40,S40) | Z40: =IF(AND('0₦'!T43<>0,'0₦'!T43<>""),9,0) + 0 | AA40: ='0₦'!BI43 + 0 | AB40: ='0₦'!BE43 | AC40: ='0₦'!BC43 + 0 | AD40: ='0₦'!BD43 | AE40: ='0₦'!AX43 | AF40: =hcbi!AA44+hcbi!Y44 | AG40: ='0₦'!AW43 | AH40: =0 | AK40: 762 | AL40: 413
B41: =B40+1 | C41: sf21 | D41: =SUM(Y41:AH41) | E41: ='0₦'!AF44 | F41: ='0₦'!AG44 | H41: =D41 | J41: =D41-H41 | L41: =D41-SUM(H41,J41) | N41: =D41-SUM(H41,J41,L41,) | P41: =D41-SUM(H41,J41,L41,N41) | R41: =D41-SUM(H41,J41,L41,N41,P41) | T41: =D41-SUM(H41,J41,L41,N41,P41,R41) | V41: =D41-SUM(H41,J41,L41,N41,P41,R41,T41) | X41: =D41-SUM(H41,J41,L41,N41,P41,R41,T41,V41) | Y41: =12*COUNT(G41,I41,K41,M41,O41,Q41,U41,W41,S41) | Z41: =IF(AND('0₦'!T44<>0,'0₦'!T44<>""),9,0) + 0 | AA41: ='0₦'!BI44 + 0 | AB41: ='0₦'!BE44 | AC41: ='0₦'!BC44 + 0 | AD41: ='0₦'!BD44 | AE41: ='0₦'!AX44 | AF41: =hcbi!AA45+hcbi!Y45 | AG41: ='0₦'!AW44 | AH41: =0 | AK41: 706 | AL41: 285
B42: =B41+1 | C42: sf21 | D42: =SUM(Y42:AH42) | E42: ='0₦'!AF45 | F42: ='0₦'!AG45 | H42: =D42 | J42: =D42-H42 | L42: =D42-SUM(H42,J42) | N42: =D42-SUM(H42,J42,L42,) | P42: =D42-SUM(H42,J42,L42,N42) | R42: =D42-SUM(H42,J42,L42,N42,P42) | T42: =D42-SUM(H42,J42,L42,N42,P42,R42) | V42: =D42-SUM(H42,J42,L42,N42,P42,R42,T42) | X42: =D42-SUM(H42,J42,L42,N42,P42,R42,T42,V42) | Y42: =12*COUNT(G42,I42,K42,M42,O42,Q42,U42,W42,S42) | Z42: =IF(AND('0₦'!T45<>0,'0₦'!T45<>""),9,0) + 0 | AA42: ='0₦'!BI45 + 0 | AB42: ='0₦'!BE45 | AC42: ='0₦'!BC45 + 0 | AD42: ='0₦'!BD45 | AE42: ='0₦'!AX45 | AF42: =hcbi!AA46+hcbi!Y46 | AG42: ='0₦'!AW45 | AH42: =0 | AK42: 858 | AL42: 714
B43: =B42+1 | C43: sf21 | D43: =SUM(Y43:AH43) | E43: ='0₦'!AF46 | F43: ='0₦'!AG46 | H43: =D43 | J43: =D43-H43 | L43: =D43-SUM(H43,J43) | N43: =D43-SUM(H43,J43,L43,) | P43: =D43-SUM(H43,J43,L43,N43) | R43: =D43-SUM(H43,J43,L43,N43,P43) | T43: =D43-SUM(H43,J43,L43,N43,P43,R43) | V43: =D43-SUM(H43,J43,L43,N43,P43,R43,T43) | X43: =D43-SUM(H43,J43,L43,N43,P43,R43,T43,V43) | Y43: =12*COUNT(G43,I43,K43,M43,O43,Q43,U43,W43,S43) | Z43: =IF(AND('0₦'!T46<>0,'0₦'!T46<>""),9,0) + 0 | AA43: ='0₦'!BI46 + 0 | AB43: ='0₦'!BE46 | AC43: ='0₦'!BC46 + 0 | AD43: ='0₦'!BD46 | AE43: ='0₦'!AX46 | AF43: =hcbi!AA47+hcbi!Y47 | AG43: ='0₦'!AW46 | AH43: =0 | AK43: 769 | AL43: 159
A44: =A37+0.1 | B44: =B43+1 | C44: sf21 | D44: =SUM(Y44:AH44) | E44: ='0₦'!AF47 | F44: ='0₦'!AG47 | H44: =D44 | J44: =D44-H44 | L44: =D44-SUM(H44,J44) | N44: =D44-SUM(H44,J44,L44,) | P44: =D44-SUM(H44,J44,L44,N44) | R44: =D44-SUM(H44,J44,L44,N44,P44) | T44: =D44-SUM(H44,J44,L44,N44,P44,R44) | V44: =D44-SUM(H44,J44,L44,N44,P44,R44,T44) | X44: =D44-SUM(H44,J44,L44,N44,P44,R44,T44,V44) | Y44: =12*COUNT(G44,I44,K44,M44,O44,Q44,U44,W44,S44) | Z44: =IF(AND('0₦'!T47<>0,'0₦'!T47<>""),9,0) + 0 | AA44: ='0₦'!BI47 + 0 | AB44: ='0₦'!BE47 | AC44: ='0₦'!BC47 + 0 | AD44: ='0₦'!BD47 | AE44: ='0₦'!AX47 | AF44: =hcbi!AA48+hcbi!Y48 | AG44: ='0₦'!AW47 | AH44: =0 | AK44: 662 | AL44: 181
B45: =B44+1 | C45: sf21 | D45: =SUM(Y45:AH45) | E45: ='0₦'!AF48 | F45: ='0₦'!AG48 | H45: =D45 | J45: =D45-H45 | L45: =D45-SUM(H45,J45) | N45: =D45-SUM(H45,J45,L45,) | P45: =D45-SUM(H45,J45,L45,N45) | R45: =D45-SUM(H45,J45,L45,N45,P45) | T45: =D45-SUM(H45,J45,L45,N45,P45,R45) | V45: =D45-SUM(H45,J45,L45,N45,P45,R45,T45) | X45: =D45-SUM(H45,J45,L45,N45,P45,R45,T45,V45) | Y45: =12*COUNT(G45,I45,K45,M45,O45,Q45,U45,W45,S45) | Z45: =IF(AND('0₦'!T48<>0,'0₦'!T48<>""),9,0) + 0 | AA45: ='0₦'!BI48 + 0 | AB45: ='0₦'!BE48 | AC45: ='0₦'!BC48 + 0 | AD45: ='0₦'!BD48 | AE45: ='0₦'!AX48 | AF45: =hcbi!AA49+hcbi!Y49 | AG45: ='0₦'!AW48 | AH45: =0 | AK45: 810 | AL45: 219
B46: =B45+1 | C46: sf21 | D46: =SUM(Y46:AH46) | E46: ='0₦'!AF49 | F46: ='0₦'!AG49 | H46: =D46 | J46: =D46-H46 | L46: =D46-SUM(H46,J46) | N46: =D46-SUM(H46,J46,L46,) | P46: =D46-SUM(H46,J46,L46,N46) | R46: =D46-SUM(H46,J46,L46,N46,P46) | T46: =D46-SUM(H46,J46,L46,N46,P46,R46) | V46: =D46-SUM(H46,J46,L46,N46,P46,R46,T46) | X46: =D46-SUM(H46,J46,L46,N46,P46,R46,T46,V46) | Y46: =12*COUNT(G46,I46,K46,M46,O46,Q46,U46,W46,S46) | Z46: =IF(AND('0₦'!T49<>0,'0₦'!T49<>""),9,0) + 0 | AA46: ='0₦'!BI49 + 0 | AB46: ='0₦'!BE49 | AC46: ='0₦'!BC49 + 0 | AD46: ='0₦'!BD49 | AE46: ='0₦'!AX49 | AF46: =hcbi!AA50+hcbi!Y50 | AG46: ='0₦'!AW49 | AH46: =0 | AK46: 657 | AL46: 111
B47: =B46+1 | C47: sf21 | D47: =SUM(Y47:AH47) | E47: ='0₦'!AF50 | F47: ='0₦'!AG50 | H47: =D47 | J47: =D47-H47 | L47: =D47-SUM(H47,J47) | N47: =D47-SUM(H47,J47,L47,) | P47: =D47-SUM(H47,J47,L47,N47) | R47: =D47-SUM(H47,J47,L47,N47,P47) | T47: =D47-SUM(H47,J47,L47,N47,P47,R47) | V47: =D47-SUM(H47,J47,L47,N47,P47,R47,T47) | X47: =D47-SUM(H47,J47,L47,N47,P47,R47,T47,V47) | Y47: =12*COUNT(G47,I47,K47,M47,O47,Q47,U47,W47,S47) | Z47: =IF(AND('0₦'!T50<>0,'0₦'!T50<>""),9,0) + 0 | AA47: ='0₦'!BI50 + 0 | AB47: ='0₦'!BE50 | AC47: ='0₦'!BC50 + 0 | AD47: ='0₦'!BD50 | AE47: ='0₦'!AX50 | AF47: =hcbi!AA51+hcbi!Y51 | AG47: ='0₦'!AW50 | AH47: =0 | AK47: 347 | AL47: 111
B48: =B47+1 | C48: sf21 | D48: =SUM(Y48:AH48) | E48: ='0₦'!AF51 | F48: ='0₦'!AG51 | H48: =D48 | J48: =D48-H48 | L48: =D48-SUM(H48,J48) | N48: =D48-SUM(H48,J48,L48,) | P48: =D48-SUM(H48,J48,L48,N48) | R48: =D48-SUM(H48,J48,L48,N48,P48) | T48: =D48-SUM(H48,J48,L48,N48,P48,R48) | V48: =D48-SUM(H48,J48,L48,N48,P48,R48,T48) | X48: =D48-SUM(H48,J48,L48,N48,P48,R48,T48,V48) | Y48: =12*COUNT(G48,I48,K48,M48,O48,Q48,U48,W48,S48) | Z48: =IF(AND('0₦'!T51<>0,'0₦'!T51<>""),9,0) + 0 | AA48: ='0₦'!BI51 + 0 | AB48: ='0₦'!BE51 | AC48: ='0₦'!BC51 + 0 | AD48: ='0₦'!BD51 | AE48: ='0₦'!AX51 | AF48: =hcbi!AA52+hcbi!Y52 | AG48: ='0₦'!AW51 | AH48: =0 | AK48: 542 | AL48: 111
B49: =B48+1 | C49: sf21 | D49: =SUM(Y49:AH49) | E49: ='0₦'!AF52 | F49: ='0₦'!AG52 | H49: =D49 | J49: =D49-H49 | L49: =D49-SUM(H49,J49) | N49: =D49-SUM(H49,J49,L49,) | P49: =D49-SUM(H49,J49,L49,N49) | R49: =D49-SUM(H49,J49,L49,N49,P49) | T49: =D49-SUM(H49,J49,L49,N49,P49,R49) | V49: =D49-SUM(H49,J49,L49,N49,P49,R49,T49) | X49: =D49-SUM(H49,J49,L49,N49,P49,R49,T49,V49) | Y49: =12*COUNT(G49,I49,K49,M49,O49,Q49,U49,W49,S49) | Z49: =IF(AND('0₦'!T52<>0,'0₦'!T52<>""),9,0) + 0 | AA49: ='0₦'!BI52 + 0 | AB49: ='0₦'!BE52 | AC49: ='0₦'!BC52 + 0 | AD49: ='0₦'!BD52 | AE49: ='0₦'!AX52 | AF49: =hcbi!AA53+hcbi!Y53 | AG49: ='0₦'!AW52 | AH49: =0 | AK49: 560 | AL49: 111
B50: =B49+1 | C50: sf21 | D50: =SUM(Y50:AH50) | E50: ='0₦'!AF53 | F50: ='0₦'!AG53 | H50: =D50 | J50: =D50-H50 | L50: =D50-SUM(H50,J50) | N50: =D50-SUM(H50,J50,L50,) | P50: =D50-SUM(H50,J50,L50,N50) | R50: =D50-SUM(H50,J50,L50,N50,P50) | T50: =D50-SUM(H50,J50,L50,N50,P50,R50) | V50: =D50-SUM(H50,J50,L50,N50,P50,R50,T50) | X50: =D50-SUM(H50,J50,L50,N50,P50,R50,T50,V50) | Y50: =12*COUNT(G50,I50,K50,M50,O50,Q50,U50,W50,S50) | Z50: =IF(AND('0₦'!T53<>0,'0₦'!T53<>""),9,0) + 0 | AA50: ='0₦'!BI53 + 0 | AB50: ='0₦'!BE53 | AC50: ='0₦'!BC53 + 0 | AD50: ='0₦'!BD53 | AE50: ='0₦'!AX53 | AF50: =hcbi!AA54+hcbi!Y54 | AG50: ='0₦'!AW53 | AH50: =0 | AK50: 648 | AL50: 111
A51: =A44+0.1 | B51: =B50+1 | C51: sf21 | D51: =SUM(Y51:AH51) | E51: ='0₦'!AF54 | F51: ='0₦'!AG54 | H51: =D51 | J51: =D51-H51 | L51: =D51-SUM(H51,J51) | N51: =D51-SUM(H51,J51,L51,) | P51: =D51-SUM(H51,J51,L51,N51) | R51: =D51-SUM(H51,J51,L51,N51,P51) | T51: =D51-SUM(H51,J51,L51,N51,P51,R51) | V51: =D51-SUM(H51,J51,L51,N51,P51,R51,T51) | X51: =D51-SUM(H51,J51,L51,N51,P51,R51,T51,V51) | Y51: =12*COUNT(G51,I51,K51,M51,O51,Q51,U51,W51,S51) | Z51: =IF(AND('0₦'!T54<>0,'0₦'!T54<>""),9,0) + 0 | AA51: ='0₦'!BI54 + 0 | AB51: ='0₦'!BE54 | AC51: ='0₦'!BC54 + 0 | AD51: ='0₦'!BD54 | AE51: ='0₦'!AX54 | AF51: =hcbi!AA55+hcbi!Y55+15 | AG51: ='0₦'!AW54 | AH51: =0 | AK51: 487 | AL51: 169
B52: =B51+1 | C52: sf21 | D52: =SUM(Y52:AH52) | E52: ='0₦'!AF55 | F52: ='0₦'!AG55 | H52: =D52 | J52: =D52-H52 | L52: =D52-SUM(H52,J52) | N52: =D52-SUM(H52,J52,L52,) | P52: =D52-SUM(H52,J52,L52,N52) | R52: =D52-SUM(H52,J52,L52,N52,P52) | T52: =D52-SUM(H52,J52,L52,N52,P52,R52) | V52: =D52-SUM(H52,J52,L52,N52,P52,R52,T52) | X52: =D52-SUM(H52,J52,L52,N52,P52,R52,T52,V52) | Y52: =12*COUNT(G52,I52,K52,M52,O52,Q52,U52,W52,S52) | Z52: =IF(AND('0₦'!T55<>0,'0₦'!T55<>""),9,0) + 0 | AA52: ='0₦'!BI55 + 0 | AB52: ='0₦'!BE55 | AC52: ='0₦'!BC55 + 0 | AD52: ='0₦'!BD55 | AE52: ='0₦'!AX55 | AF52: =hcbi!AA56+hcbi!Y56+10 | AG52: ='0₦'!AW55 | AH52: =0 | AK52: 659 | AL52: 166
B53: =B52+1 | C53: sf21 | D53: =SUM(Y53:AH53) | E53: ='0₦'!AF56 | F53: ='0₦'!AG56 | H53: =D53 | J53: =D53-H53 | L53: =D53-SUM(H53,J53) | N53: =D53-SUM(H53,J53,L53,) | P53: =D53-SUM(H53,J53,L53,N53) | R53: =D53-SUM(H53,J53,L53,N53,P53) | T53: =D53-SUM(H53,J53,L53,N53,P53,R53) | V53: =D53-SUM(H53,J53,L53,N53,P53,R53,T53) | X53: =D53-SUM(H53,J53,L53,N53,P53,R53,T53,V53) | Y53: =12*COUNT(G53,I53,K53,M53,O53,Q53,U53,W53,S53) | Z53: =IF(AND('0₦'!T56<>0,'0₦'!T56<>""),9,0) + 0 | AA53: ='0₦'!BI56 + 0 | AB53: ='0₦'!BE56 | AC53: ='0₦'!BC56 + 0 | AD53: ='0₦'!BD56 | AE53: ='0₦'!AX56 | AF53: =hcbi!AA57+hcbi!Y57 | AG53: ='0₦'!AW56 | AH53: =0 | AK53: 728 | AL53: 159
B54: =B53+1 | C54: sf21 | D54: =SUM(Y54:AH54) | E54: ='0₦'!AF57 | F54: ='0₦'!AG57 | H54: =D54 | J54: =D54-H54 | L54: =D54-SUM(H54,J54) | N54: =D54-SUM(H54,J54,L54,) | P54: =D54-SUM(H54,J54,L54,N54) | R54: =D54-SUM(H54,J54,L54,N54,P54) | T54: =D54-SUM(H54,J54,L54,N54,P54,R54) | V54: =D54-SUM(H54,J54,L54,N54,P54,R54,T54) | X54: =D54-SUM(H54,J54,L54,N54,P54,R54,T54,V54) | Y54: =12*COUNT(G54,I54,K54,M54,O54,Q54,U54,W54,S54) | Z54: =IF(AND('0₦'!T57<>0,'0₦'!T57<>""),9,0) + 0 | AA54: ='0₦'!BI57 + 0 | AB54: ='0₦'!BE57 | AC54: ='0₦'!BC57 + 0 | AD54: ='0₦'!BD57 | AE54: ='0₦'!AX57 | AF54: =hcbi!AA58+hcbi!Y58 | AG54: ='0₦'!AW57 | AH54: =0 | AK54: 827 | AL54: 348
B55: =B54+1 | C55: sf21 | D55: =SUM(Y55:AH55) | E55: ='0₦'!AF58 | F55: ='0₦'!AG58 | H55: =D55 | J55: =D55-H55 | L55: =D55-SUM(H55,J55) | N55: =D55-SUM(H55,J55,L55,) | P55: =D55-SUM(H55,J55,L55,N55) | R55: =D55-SUM(H55,J55,L55,N55,P55) | T55: =D55-SUM(H55,J55,L55,N55,P55,R55) | V55: =D55-SUM(H55,J55,L55,N55,P55,R55,T55) | X55: =D55-SUM(H55,J55,L55,N55,P55,R55,T55,V55) | Y55: =12*COUNT(G55,I55,K55,M55,O55,Q55,U55,W55,S55) | Z55: =IF(AND('0₦'!T58<>0,'0₦'!T58<>""),9,0) + 0 | AA55: ='0₦'!BI58 + 0 | AB55: ='0₦'!BE58 | AC55: ='0₦'!BC58 + 0 | AD55: ='0₦'!BD58 | AE55: ='0₦'!AX58 | AF55: =hcbi!AA59+hcbi!Y59+10+20 | AG55: ='0₦'!AW58 | AH55: =0 | AK55: 945 | AL55: 141
B56: =B55+1 | C56: sf21 | D56: =SUM(Y56:AH56) | E56: ='0₦'!AF59 | F56: ='0₦'!AG59 | H56: =D56 | J56: =D56-H56 | L56: =D56-SUM(H56,J56) | N56: =D56-SUM(H56,J56,L56,) | P56: =D56-SUM(H56,J56,L56,N56) | R56: =D56-SUM(H56,J56,L56,N56,P56) | T56: =D56-SUM(H56,J56,L56,N56,P56,R56) | V56: =D56-SUM(H56,J56,L56,N56,P56,R56,T56) | X56: =D56-SUM(H56,J56,L56,N56,P56,R56,T56,V56) | Y56: =12*COUNT(G56,I56,K56,M56,O56,Q56,U56,W56,S56) | Z56: =IF(AND('0₦'!T59<>0,'0₦'!T59<>""),9,0) + 0 | AA56: ='0₦'!BI59 + 0 | AB56: ='0₦'!BE59 | AC56: ='0₦'!BC59 + 0 | AD56: ='0₦'!BD59 | AE56: ='0₦'!AX59 | AF56: =hcbi!AA60+hcbi!Y60 | AG56: ='0₦'!AW59 | AH56: =0 | AK56: 578 | AL56: 130
B57: =B56+1 | C57: sf21 | D57: =SUM(Y57:AH57) | E57: ='0₦'!AF60 | F57: ='0₦'!AG60 | H57: =D57 | J57: =D57-H57 | L57: =D57-SUM(H57,J57) | N57: =D57-SUM(H57,J57,L57,) | P57: =D57-SUM(H57,J57,L57,N57) | R57: =D57-SUM(H57,J57,L57,N57,P57) | T57: =D57-SUM(H57,J57,L57,N57,P57,R57) | V57: =D57-SUM(H57,J57,L57,N57,P57,R57,T57) | X57: =D57-SUM(H57,J57,L57,N57,P57,R57,T57,V57) | Y57: =12*COUNT(G57,I57,K57,M57,O57,Q57,U57,W57,S57) | Z57: =IF(AND('0₦'!T60<>0,'0₦'!T60<>""),9,0) + 0 | AA57: ='0₦'!BI60 + 0 | AB57: ='0₦'!BE60 | AC57: ='0₦'!BC60 + 0 | AD57: ='0₦'!BD60 | AE57: ='0₦'!AX60 | AF57: =hcbi!AA61+hcbi!Y61 | AG57: ='0₦'!AW60 | AH57: =0 | AK57: 658 | AL57: 164
A58: =A30+1 | B58: =B57+1 | C58: sf21 | D58: =SUM(Y58:AH58) | E58: ='0₦'!AF61 | F58: ='0₦'!AG61 | H58: =D58 | J58: =D58-H58 | L58: =D58-SUM(H58,J58) | N58: =D58-SUM(H58,J58,L58,) | P58: =D58-SUM(H58,J58,L58,N58) | R58: =D58-SUM(H58,J58,L58,N58,P58) | T58: =D58-SUM(H58,J58,L58,N58,P58,R58) | V58: =D58-SUM(H58,J58,L58,N58,P58,R58,T58) | X58: =D58-SUM(H58,J58,L58,N58,P58,R58,T58,V58) | Y58: =12*COUNT(G58,I58,K58,M58,O58,Q58,U58,W58,S58) | Z58: =IF(AND('0₦'!T61<>0,'0₦'!T61<>""),9,0) + 0 | AA58: ='0₦'!BI61 + 0 | AB58: ='0₦'!BE61 | AC58: ='0₦'!BC61 + 0 | AD58: ='0₦'!BD61 | AE58: ='0₦'!AX61 | AF58: =hcbi!AA62+hcbi!Y62 | AG58: ='0₦'!AW61 | AH58: =0 | AK58: 850 | AL58: 134
B59: =B58+1 | C59: sf21 | D59: =SUM(Y59:AH59) | E59: ='0₦'!AF62 | F59: ='0₦'!AG62 | H59: =D59 | J59: =D59-H59 | L59: =D59-SUM(H59,J59) | N59: =D59-SUM(H59,J59,L59,) | P59: =D59-SUM(H59,J59,L59,N59) | R59: =D59-SUM(H59,J59,L59,N59,P59) | T59: =D59-SUM(H59,J59,L59,N59,P59,R59) | V59: =D59-SUM(H59,J59,L59,N59,P59,R59,T59) | X59: =D59-SUM(H59,J59,L59,N59,P59,R59,T59,V59) | Y59: =12*COUNT(G59,I59,K59,M59,O59,Q59,U59,W59,S59) | Z59: =IF(AND('0₦'!T62<>0,'0₦'!T62<>""),9,0) + 0 | AA59: ='0₦'!BI62 + 0 | AB59: ='0₦'!BE62 | AC59: ='0₦'!BC62 + 0 | AD59: ='0₦'!BD62 | AE59: ='0₦'!AX62 | AF59: =hcbi!AA63+hcbi!Y63 | AG59: ='0₦'!AW62 | AH59: =0 | AK59: 777 | AL59: 182
B60: =B59+1 | C60: sf21 | D60: =SUM(Y60:AH60) | E60: ='0₦'!AF63 | F60: ='0₦'!AG63 | H60: =D60 | J60: =D60-H60 | L60: =D60-SUM(H60,J60) | N60: =D60-SUM(H60,J60,L60,) | P60: =D60-SUM(H60,J60,L60,N60) | R60: =D60-SUM(H60,J60,L60,N60,P60) | T60: =D60-SUM(H60,J60,L60,N60,P60,R60) | V60: =D60-SUM(H60,J60,L60,N60,P60,R60,T60) | X60: =D60-SUM(H60,J60,L60,N60,P60,R60,T60,V60) | Y60: =12*COUNT(G60,I60,K60,M60,O60,Q60,U60,W60,S60) | Z60: =IF(AND('0₦'!T63<>0,'0₦'!T63<>""),9,0) + 0 | AA60: ='0₦'!BI63 + 0 | AB60: ='0₦'!BE63 | AC60: ='0₦'!BC63 + 0 | AD60: ='0₦'!BD63 | AE60: ='0₦'!AX63 | AF60: =hcbi!AA64+hcbi!Y64 | AG60: ='0₦'!AW63 | AH60: =0 | AK60: 738 | AL60: 58
B61: =B60+1 | C61: sf21 | D61: =SUM(Y61:AH61) | E61: ='0₦'!AF64 | F61: ='0₦'!AG64 | H61: =D61 | J61: =D61-H61 | L61: =D61-SUM(H61,J61) | N61: =D61-SUM(H61,J61,L61,) | P61: =D61-SUM(H61,J61,L61,N61) | R61: =D61-SUM(H61,J61,L61,N61,P61) | T61: =D61-SUM(H61,J61,L61,N61,P61,R61) | V61: =D61-SUM(H61,J61,L61,N61,P61,R61,T61) | X61: =D61-SUM(H61,J61,L61,N61,P61,R61,T61,V61) | Y61: =12*COUNT(G61,I61,K61,M61,O61,Q61,U61,W61,S61) | Z61: =IF(AND('0₦'!T64<>0,'0₦'!T64<>""),9,0) + 0 | AA61: ='0₦'!BI64 + 0 | AB61: ='0₦'!BE64 | AC61: ='0₦'!BC64 + 0 | AD61: ='0₦'!BD64 | AE61: ='0₦'!AX64 | AF61: =hcbi!AA65+hcbi!Y65 | AG61: ='0₦'!AW64 | AH61: =0 | AK61: 751 | AL61: 245
B62: =B61+1 | C62: sf21 | D62: =SUM(Y62:AH62) | E62: ='0₦'!AF65 | F62: ='0₦'!AG65 | H62: =D62 | J62: =D62-H62 | L62: =D62-SUM(H62,J62) | N62: =D62-SUM(H62,J62,L62,) | P62: =D62-SUM(H62,J62,L62,N62) | R62: =D62-SUM(H62,J62,L62,N62,P62) | T62: =D62-SUM(H62,J62,L62,N62,P62,R62) | V62: =D62-SUM(H62,J62,L62,N62,P62,R62,T62) | X62: =D62-SUM(H62,J62,L62,N62,P62,R62,T62,V62) | Y62: =12*COUNT(G62,I62,K62,M62,O62,Q62,U62,W62,S62) | Z62: =IF(AND('0₦'!T65<>0,'0₦'!T65<>""),9,0) + 0 | AA62: ='0₦'!BI65 + 0 | AB62: ='0₦'!BE65 | AC62: ='0₦'!BC65 + 0 | AD62: ='0₦'!BD65 | AE62: ='0₦'!AX65 | AF62: =hcbi!AA66+hcbi!Y66+30 | AG62: ='0₦'!AW65 | AH62: =0 | AK62: 428 | AL62: 103
B63: =B62+1 | C63: sf21 | D63: =SUM(Y63:AH63) | E63: ='0₦'!AF66 | F63: ='0₦'!AG66 | H63: =D63 | J63: =D63-H63 | L63: =D63-SUM(H63,J63) | N63: =D63-SUM(H63,J63,L63,) | P63: =D63-SUM(H63,J63,L63,N63) | R63: =D63-SUM(H63,J63,L63,N63,P63) | T63: =D63-SUM(H63,J63,L63,N63,P63,R63) | V63: =D63-SUM(H63,J63,L63,N63,P63,R63,T63) | X63: =D63-SUM(H63,J63,L63,N63,P63,R63,T63,V63) | Y63: =12*COUNT(G63,I63,K63,M63,O63,Q63,U63,W63,S63) | Z63: =IF(AND('0₦'!T66<>0,'0₦'!T66<>""),9,0) + 0 | AA63: ='0₦'!BI66 + 0 | AB63: ='0₦'!BE66 | AC63: ='0₦'!BC66 + 0 | AD63: ='0₦'!BD66 | AE63: ='0₦'!AX66 | AF63: =hcbi!AA67+hcbi!Y67 | AG63: ='0₦'!AW66 | AH63: =0 | AK63: 716 | AL63: 130
B64: =B63+1 | C64: sf21 | D64: =SUM(Y64:AH64) | E64: ='0₦'!AF67 | F64: ='0₦'!AG67 | H64: =D64 | J64: =D64-H64 | L64: =D64-SUM(H64,J64) | N64: =D64-SUM(H64,J64,L64,) | P64: =D64-SUM(H64,J64,L64,N64) | R64: =D64-SUM(H64,J64,L64,N64,P64) | T64: =D64-SUM(H64,J64,L64,N64,P64,R64) | V64: =D64-SUM(H64,J64,L64,N64,P64,R64,T64) | X64: =D64-SUM(H64,J64,L64,N64,P64,R64,T64,V64) | Y64: =12*COUNT(G64,I64,K64,M64,O64,Q64,U64,W64,S64) | Z64: =IF(AND('0₦'!T67<>0,'0₦'!T67<>""),9,0) + 0 | AA64: ='0₦'!BI67 + 0 | AB64: ='0₦'!BE67 | AC64: ='0₦'!BC67 + 0 | AD64: ='0₦'!BD67 | AE64: ='0₦'!AX67 | AF64: =hcbi!AA68+hcbi!Y68 | AG64: ='0₦'!AW67 | AH64: =0 | AK64: 648 | AL64: 205
A65: =A58+0.1 | B65: =B64+1 | C65: sf21 | D65: =SUM(Y65:AH65) | E65: ='0₦'!AF68 | F65: ='0₦'!AG68 | H65: =D65 | J65: =D65-H65 | L65: =D65-SUM(H65,J65) | N65: =D65-SUM(H65,J65,L65,) | P65: =D65-SUM(H65,J65,L65,N65) | R65: =D65-SUM(H65,J65,L65,N65,P65) | T65: =D65-SUM(H65,J65,L65,N65,P65,R65) | V65: =D65-SUM(H65,J65,L65,N65,P65,R65,T65) | X65: =D65-SUM(H65,J65,L65,N65,P65,R65,T65,V65) | Y65: =12*COUNT(G65,I65,K65,M65,O65,Q65,U65,W65,S65) | Z65: =IF(AND('0₦'!T68<>0,'0₦'!T68<>""),9,0) + 0 | AA65: ='0₦'!BI68 + 0 | AB65: ='0₦'!BE68 | AC65: ='0₦'!BC68 + 0 | AD65: ='0₦'!BD68 | AE65: ='0₦'!AX68 | AF65: =hcbi!AA69+hcbi!Y69 | AG65: ='0₦'!AW68 | AH65: =0 | AK65: 732 | AL65: 114
B66: =B65+1 | C66: sf21 | D66: =SUM(Y66:AH66) | E66: ='0₦'!AF69 | F66: ='0₦'!AG69 | H66: =D66 | J66: =D66-H66 | L66: =D66-SUM(H66,J66) | N66: =D66-SUM(H66,J66,L66,) | P66: =D66-SUM(H66,J66,L66,N66) | R66: =D66-SUM(H66,J66,L66,N66,P66) | T66: =D66-SUM(H66,J66,L66,N66,P66,R66) | V66: =D66-SUM(H66,J66,L66,N66,P66,R66,T66) | X66: =D66-SUM(H66,J66,L66,N66,P66,R66,T66,V66) | Y66: =12*COUNT(G66,I66,K66,M66,O66,Q66,U66,W66,S66) | Z66: =IF(AND('0₦'!T69<>0,'0₦'!T69<>""),9,0) + 0 | AA66: ='0₦'!BI69 + 0 | AB66: ='0₦'!BE69 | AC66: ='0₦'!BC69 + 0 | AD66: ='0₦'!BD69 | AE66: ='0₦'!AX69 | AF66: =hcbi!AA70+hcbi!Y70 | AG66: ='0₦'!AW69 | AH66: =0 | AK66: 829 | AL66: 400
B67: =B66+1 | C67: sf21 | D67: =SUM(Y67:AH67) | E67: ='0₦'!AF70 | F67: ='0₦'!AG70 | H67: =D67 | J67: =D67-H67 | L67: =D67-SUM(H67,J67) | N67: =D67-SUM(H67,J67,L67,) | P67: =D67-SUM(H67,J67,L67,N67) | R67: =D67-SUM(H67,J67,L67,N67,P67) | T67: =D67-SUM(H67,J67,L67,N67,P67,R67) | V67: =D67-SUM(H67,J67,L67,N67,P67,R67,T67) | X67: =D67-SUM(H67,J67,L67,N67,P67,R67,T67,V67) | Y67: =12*COUNT(G67,I67,K67,M67,O67,Q67,U67,W67,S67) | Z67: =IF(AND('0₦'!T70<>0,'0₦'!T70<>""),9,0) + 0 | AA67: ='0₦'!BI70 + 0 | AB67: ='0₦'!BE70 | AC67: ='0₦'!BC70 + 0 | AD67: ='0₦'!BD70 | AE67: ='0₦'!AX70 | AF67: =hcbi!AA71+hcbi!Y71 | AG67: ='0₦'!AW70 | AH67: =0 | AK67: 701 | AL67: 312
B68: =B67+1 | C68: sf21 | D68: =SUM(Y68:AH68) | E68: ='0₦'!AF71 | F68: ='0₦'!AG71 | H68: =D68 | J68: =D68-H68 | L68: =D68-SUM(H68,J68) | N68: =D68-SUM(H68,J68,L68,) | P68: =D68-SUM(H68,J68,L68,N68) | R68: =D68-SUM(H68,J68,L68,N68,P68) | T68: =D68-SUM(H68,J68,L68,N68,P68,R68) | V68: =D68-SUM(H68,J68,L68,N68,P68,R68,T68) | X68: =D68-SUM(H68,J68,L68,N68,P68,R68,T68,V68) | Y68: =12*COUNT(G68,I68,K68,M68,O68,Q68,U68,W68,S68) | Z68: =IF(AND('0₦'!T71<>0,'0₦'!T71<>""),9,0) + 0 | AA68: ='0₦'!BI71 + 0 | AB68: ='0₦'!BE71 | AC68: ='0₦'!BC71 + 0 | AD68: ='0₦'!BD71 | AE68: ='0₦'!AX71 | AF68: =hcbi!AA72+hcbi!Y72 | AG68: ='0₦'!AW71 | AH68: =0 | AK68: 870 | AL68: 300
B69: =B68+1 | C69: sf21 | D69: =SUM(Y69:AH69) | E69: ='0₦'!AF72 | F69: ='0₦'!AG72 | H69: =D69 | J69: =D69-H69 | L69: =D69-SUM(H69,J69) | N69: =D69-SUM(H69,J69,L69,) | P69: =D69-SUM(H69,J69,L69,N69) | R69: =D69-SUM(H69,J69,L69,N69,P69) | T69: =D69-SUM(H69,J69,L69,N69,P69,R69) | V69: =D69-SUM(H69,J69,L69,N69,P69,R69,T69) | X69: =D69-SUM(H69,J69,L69,N69,P69,R69,T69,V69) | Y69: =12*COUNT(G69,I69,K69,M69,O69,Q69,U69,W69,S69) | Z69: =IF(AND('0₦'!T72<>0,'0₦'!T72<>""),9,0) + 0 | AA69: ='0₦'!BI72 + 0 | AB69: ='0₦'!BE72 | AC69: ='0₦'!BC72 + 0 | AD69: ='0₦'!BD72 | AE69: ='0₦'!AX72 | AF69: =hcbi!AA73+hcbi!Y73+20+10 | AG69: ='0₦'!AW72 | AH69: =0 | AK69: 655 | AL69: 400
B70: =B69+1 | C70: sf21 | D70: =SUM(Y70:AH70) | E70: ='0₦'!AF73 | F70: ='0₦'!AG73 | H70: =D70 | J70: =D70-H70 | L70: =D70-SUM(H70,J70) | N70: =D70-SUM(H70,J70,L70,) | P70: =D70-SUM(H70,J70,L70,N70) | R70: =D70-SUM(H70,J70,L70,N70,P70) | T70: =D70-SUM(H70,J70,L70,N70,P70,R70) | V70: =D70-SUM(H70,J70,L70,N70,P70,R70,T70) | X70: =D70-SUM(H70,J70,L70,N70,P70,R70,T70,V70) | Y70: =12*COUNT(G70,I70,K70,M70,O70,Q70,U70,W70,S70) | Z70: =IF(AND('0₦'!T73<>0,'0₦'!T73<>""),9,0) + 0 | AA70: ='0₦'!BI73 + 0 | AB70: ='0₦'!BE73 | AC70: ='0₦'!BC73 + 0 | AD70: ='0₦'!BD73 | AE70: ='0₦'!AX73 | AF70: =hcbi!AA74+hcbi!Y74 | AG70: ='0₦'!AW73 | AH70: =0 | AK70: 695 | AL70: 179
B71: =B70+1 | C71: sf21 | D71: =SUM(Y71:AH71) | E71: ='0₦'!AF74 | F71: ='0₦'!AG74 | H71: =D71 | J71: =D71-H71 | L71: =D71-SUM(H71,J71) | N71: =D71-SUM(H71,J71,L71,) | P71: =D71-SUM(H71,J71,L71,N71) | R71: =D71-SUM(H71,J71,L71,N71,P71) | T71: =D71-SUM(H71,J71,L71,N71,P71,R71) | V71: =D71-SUM(H71,J71,L71,N71,P71,R71,T71) | X71: =D71-SUM(H71,J71,L71,N71,P71,R71,T71,V71) | Y71: =12*COUNT(G71,I71,K71,M71,O71,Q71,U71,W71,S71) | Z71: =IF(AND('0₦'!T74<>0,'0₦'!T74<>""),9,0) + 0 | AA71: ='0₦'!BI74 + 0 | AB71: ='0₦'!BE74 | AC71: ='0₦'!BC74 + 0 | AD71: ='0₦'!BD74 | AE71: ='0₦'!AX74 | AF71: =hcbi!AA75+hcbi!Y75 | AG71: ='0₦'!AW74 | AH71: =0 | AK71: 843 | AL71: 156
A72: =A65+0.1 | B72: =B71+1 | C72: sf21 | D72: =SUM(Y72:AH72) | E72: ='0₦'!AF75 | F72: ='0₦'!AG75 | H72: =D72 | J72: =D72-H72 | L72: =D72-SUM(H72,J72) | N72: =D72-SUM(H72,J72,L72,) | P72: =D72-SUM(H72,J72,L72,N72) | R72: =D72-SUM(H72,J72,L72,N72,P72) | T72: =D72-SUM(H72,J72,L72,N72,P72,R72) | V72: =D72-SUM(H72,J72,L72,N72,P72,R72,T72) | X72: =D72-SUM(H72,J72,L72,N72,P72,R72,T72,V72) | Y72: =12*COUNT(G72,I72,K72,M72,O72,Q72,U72,W72,S72) | Z72: =IF(AND('0₦'!T75<>0,'0₦'!T75<>""),9,0) + 0 | AA72: ='0₦'!BI75 + 0 | AB72: ='0₦'!BE75 | AC72: ='0₦'!BC75 + 0 | AD72: ='0₦'!BD75 | AE72: ='0₦'!AX75 | AF72: =hcbi!AA76+hcbi!Y76 | AG72: ='0₦'!AW75 | AH72: =0 | AK72: 713 | AL72: 429
B73: =B72+1 | C73: sf21 | D73: =SUM(Y73:AH73) | E73: ='0₦'!AF76 | F73: ='0₦'!AG76 | H73: =D73 | J73: =D73-H73 | L73: =D73-SUM(H73,J73) | N73: =D73-SUM(H73,J73,L73,) | P73: =D73-SUM(H73,J73,L73,N73) | R73: =D73-SUM(H73,J73,L73,N73,P73) | T73: =D73-SUM(H73,J73,L73,N73,P73,R73) | V73: =D73-SUM(H73,J73,L73,N73,P73,R73,T73) | X73: =D73-SUM(H73,J73,L73,N73,P73,R73,T73,V73) | Y73: =12*COUNT(G73,I73,K73,M73,O73,Q73,U73,W73,S73) | Z73: =IF(AND('0₦'!T76<>0,'0₦'!T76<>""),9,0) + 0 | AA73: ='0₦'!BI76 + 0 | AB73: ='0₦'!BE76 | AC73: ='0₦'!BC76 + 0 | AD73: ='0₦'!BD76 | AE73: ='0₦'!AX76 | AF73: =hcbi!AA77+hcbi!Y77 | AG73: ='0₦'!AW76 | AH73: =0 | AK73: 674 | AL73: 429
B74: =B73+1 | C74: sf21 | D74: =SUM(Y74:AH74) | E74: ='0₦'!AF77 | F74: ='0₦'!AG77 | H74: =D74 | J74: =D74-H74 | L74: =D74-SUM(H74,J74) | N74: =D74-SUM(H74,J74,L74,) | P74: =D74-SUM(H74,J74,L74,N74) | R74: =D74-SUM(H74,J74,L74,N74,P74) | T74: =D74-SUM(H74,J74,L74,N74,P74,R74) | V74: =D74-SUM(H74,J74,L74,N74,P74,R74,T74) | X74: =D74-SUM(H74,J74,L74,N74,P74,R74,T74,V74) | Y74: =12*COUNT(G74,I74,K74,M74,O74,Q74,U74,W74,S74) | Z74: =IF(AND('0₦'!T77<>0,'0₦'!T77<>""),9,0) + 0 | AA74: ='0₦'!BI77 + 0 | AB74: ='0₦'!BE77 | AC74: ='0₦'!BC77 + 0 | AD74: ='0₦'!BD77 | AE74: ='0₦'!AX77 | AF74: =hcbi!AA78+hcbi!Y78 | AG74: ='0₦'!AW77 | AH74: =0 | AK74: 837 | AL74: 429
B75: =B74+1 | C75: sf21 | D75: =SUM(Y75:AH75) | E75: ='0₦'!AF78 | F75: ='0₦'!AG78 | H75: =D75 | J75: =D75-H75 | L75: =D75-SUM(H75,J75) | N75: =D75-SUM(H75,J75,L75,) | P75: =D75-SUM(H75,J75,L75,N75) | R75: =D75-SUM(H75,J75,L75,N75,P75) | T75: =D75-SUM(H75,J75,L75,N75,P75,R75) | V75: =D75-SUM(H75,J75,L75,N75,P75,R75,T75) | X75: =D75-SUM(H75,J75,L75,N75,P75,R75,T75,V75) | Y75: =12*COUNT(G75,I75,K75,M75,O75,Q75,U75,W75,S75) | Z75: =IF(AND('0₦'!T78<>0,'0₦'!T78<>""),9,0) + 0 | AA75: ='0₦'!BI78 + 0 | AB75: ='0₦'!BE78 | AC75: ='0₦'!BC78 + 0 | AD75: ='0₦'!BD78 | AE75: ='0₦'!AX78 | AF75: =hcbi!AA79+hcbi!Y79 | AG75: ='0₦'!AW78 | AH75: =0 | AK75: 920 | AL75: 429
B76: =B75+1 | C76: sf21 | D76: =SUM(Y76:AH76) | E76: ='0₦'!AF79 | F76: ='0₦'!AG79 | H76: =D76 | J76: =D76-H76 | L76: =D76-SUM(H76,J76) | N76: =D76-SUM(H76,J76,L76,) | P76: =D76-SUM(H76,J76,L76,N76) | R76: =D76-SUM(H76,J76,L76,N76,P76) | T76: =D76-SUM(H76,J76,L76,N76,P76,R76) | V76: =D76-SUM(H76,J76,L76,N76,P76,R76,T76) | X76: =D76-SUM(H76,J76,L76,N76,P76,R76,T76,V76) | Y76: =12*COUNT(G76,I76,K76,M76,O76,Q76,U76,W76,S76) | Z76: =IF(AND('0₦'!T79<>0,'0₦'!T79<>""),9,0) + 0 | AA76: ='0₦'!BI79 + 0 | AB76: ='0₦'!BE79 | AC76: ='0₦'!BC79 + 0 | AD76: ='0₦'!BD79 | AE76: ='0₦'!AX79 | AF76: =hcbi!AA80+hcbi!Y80+20 | AG76: ='0₦'!AW79 | AH76: =0 | AK76: 619 | AL76: 429
B77: =B76+1 | C77: sf21 | D77: =SUM(Y77:AH77) | E77: ='0₦'!AF80 | F77: ='0₦'!AG80 | H77: =D77 | J77: =D77-H77 | L77: =D77-SUM(H77,J77) | N77: =D77-SUM(H77,J77,L77,) | P77: =D77-SUM(H77,J77,L77,N77) | R77: =D77-SUM(H77,J77,L77,N77,P77) | T77: =D77-SUM(H77,J77,L77,N77,P77,R77) | V77: =D77-SUM(H77,J77,L77,N77,P77,R77,T77) | X77: =D77-SUM(H77,J77,L77,N77,P77,R77,T77,V77) | Y77: =12*COUNT(G77,I77,K77,M77,O77,Q77,U77,W77,S77) | Z77: =IF(AND('0₦'!T80<>0,'0₦'!T80<>""),9,0) + 0 | AA77: ='0₦'!BI80 + 0 | AB77: ='0₦'!BE80 | AC77: ='0₦'!BC80 + 0 | AD77: ='0₦'!BD80 | AE77: ='0₦'!AX80 | AF77: =hcbi!AA81+hcbi!Y81 | AG77: ='0₦'!AW80 | AH77: =0 | AK77: 697 | AL77: 429
B78: =B77+1 | C78: sf21 | D78: =SUM(Y78:AH78) | E78: ='0₦'!AF81 | F78: ='0₦'!AG81 | H78: =D78 | J78: =D78-H78 | L78: =D78-SUM(H78,J78) | N78: =D78-SUM(H78,J78,L78,) | P78: =D78-SUM(H78,J78,L78,N78) | R78: =D78-SUM(H78,J78,L78,N78,P78) | T78: =D78-SUM(H78,J78,L78,N78,P78,R78) | V78: =D78-SUM(H78,J78,L78,N78,P78,R78,T78) | X78: =D78-SUM(H78,J78,L78,N78,P78,R78,T78,V78) | Y78: =12*COUNT(G78,I78,K78,M78,O78,Q78,U78,W78,S78) | Z78: =IF(AND('0₦'!T81<>0,'0₦'!T81<>""),9,0) + 0 | AA78: ='0₦'!BI81 + 0 | AB78: ='0₦'!BE81 | AC78: ='0₦'!BC81 + 0 | AD78: ='0₦'!BD81 | AE78: ='0₦'!AX81 | AF78: =hcbi!AA82+hcbi!Y82 | AG78: ='0₦'!AW81 | AH78: =0 | AK78: 755 | AL78: 263
A79: =A72+0.1 | B79: =B78+1 | C79: sf21 | D79: =SUM(Y79:AH79) | E79: ='0₦'!AF82 | F79: ='0₦'!AG82 | H79: =D79 | J79: =D79-H79 | L79: =D79-SUM(H79,J79) | N79: =D79-SUM(H79,J79,L79,) | P79: =D79-SUM(H79,J79,L79,N79) | R79: =D79-SUM(H79,J79,L79,N79,P79) | T79: =D79-SUM(H79,J79,L79,N79,P79,R79) | V79: =D79-SUM(H79,J79,L79,N79,P79,R79,T79) | X79: =D79-SUM(H79,J79,L79,N79,P79,R79,T79,V79) | Y79: =12*COUNT(G79,I79,K79,M79,O79,Q79,U79,W79,S79) | Z79: =IF(AND('0₦'!T82<>0,'0₦'!T82<>""),9,0) + 0 | AA79: ='0₦'!BI82 + 0 | AB79: ='0₦'!BE82 | AC79: ='0₦'!BC82 + 0 | AD79: ='0₦'!BD82 | AE79: ='0₦'!AX82 | AF79: =hcbi!AA83+hcbi!Y83 | AG79: ='0₦'!AW82 | AH79: =0 | AK79: 569 | AL79: 98
B80: =B79+1 | C80: sf21 | D80: =SUM(Y80:AH80) | E80: ='0₦'!AF83 | F80: ='0₦'!AG83 | H80: =D80 | J80: =D80-H80 | L80: =D80-SUM(H80,J80) | N80: =D80-SUM(H80,J80,L80,) | P80: =D80-SUM(H80,J80,L80,N80) | R80: =D80-SUM(H80,J80,L80,N80,P80) | T80: =D80-SUM(H80,J80,L80,N80,P80,R80) | V80: =D80-SUM(H80,J80,L80,N80,P80,R80,T80) | X80: =D80-SUM(H80,J80,L80,N80,P80,R80,T80,V80) | Y80: =12*COUNT(G80,I80,K80,M80,O80,Q80,U80,W80,S80) | Z80: =IF(AND('0₦'!T83<>0,'0₦'!T83<>""),9,0) + 0 | AA80: ='0₦'!BI83 + 0 | AB80: ='0₦'!BE83 | AC80: ='0₦'!BC83 + 0 | AD80: ='0₦'!BD83 | AE80: ='0₦'!AX83 | AF80: =hcbi!AA84+hcbi!Y84 | AG80: ='0₦'!AW83 | AH80: =0 | AK80: 678 | AL80: 195
B81: =B80+1 | C81: sf21 | D81: =SUM(Y81:AH81) | E81: ='0₦'!AF84 | F81: ='0₦'!AG84 | H81: =D81 | J81: =D81-H81 | L81: =D81-SUM(H81,J81) | N81: =D81-SUM(H81,J81,L81,) | P81: =D81-SUM(H81,J81,L81,N81) | R81: =D81-SUM(H81,J81,L81,N81,P81) | T81: =D81-SUM(H81,J81,L81,N81,P81,R81) | V81: =D81-SUM(H81,J81,L81,N81,P81,R81,T81) | X81: =D81-SUM(H81,J81,L81,N81,P81,R81,T81,V81) | Y81: =12*COUNT(G81,I81,K81,M81,O81,Q81,U81,W81,S81) | Z81: =IF(AND('0₦'!T84<>0,'0₦'!T84<>""),9,0) + 0 | AA81: ='0₦'!BI84 + 0 | AB81: ='0₦'!BE84 | AC81: ='0₦'!BC84 + 0 | AD81: ='0₦'!BD84 | AE81: ='0₦'!AX84 | AF81: =hcbi!AA85+hcbi!Y85+10 | AG81: ='0₦'!AW84 | AH81: =0 | AK81: 770 | AL81: 166
B82: =B81+1 | C82: sf21 | D82: =SUM(Y82:AH82) | E82: ='0₦'!AF85 | F82: ='0₦'!AG85 | H82: =D82 | J82: =D82-H82 | L82: =D82-SUM(H82,J82) | N82: =D82-SUM(H82,J82,L82,) | P82: =D82-SUM(H82,J82,L82,N82) | R82: =D82-SUM(H82,J82,L82,N82,P82) | T82: =D82-SUM(H82,J82,L82,N82,P82,R82) | V82: =D82-SUM(H82,J82,L82,N82,P82,R82,T82) | X82: =D82-SUM(H82,J82,L82,N82,P82,R82,T82,V82) | Y82: =12*COUNT(G82,I82,K82,M82,O82,Q82,U82,W82,S82) | Z82: =IF(AND('0₦'!T85<>0,'0₦'!T85<>""),9,0) + 0 | AA82: ='0₦'!BI85 + 0 | AB82: ='0₦'!BE85 | AC82: ='0₦'!BC85 + 0 | AD82: ='0₦'!BD85 | AE82: ='0₦'!AX85 | AF82: =hcbi!AA86+hcbi!Y86 | AG82: ='0₦'!AW85 | AH82: =0 | AK82: 751 | AL82: 215
B83: =B82+1 | C83: sf21 | D83: =SUM(Y83:AH83) | E83: ='0₦'!AF86 | F83: ='0₦'!AG86 | H83: =D83 | J83: =D83-H83 | L83: =D83-SUM(H83,J83) | N83: =D83-SUM(H83,J83,L83,) | P83: =D83-SUM(H83,J83,L83,N83) | R83: =D83-SUM(H83,J83,L83,N83,P83) | T83: =D83-SUM(H83,J83,L83,N83,P83,R83) | V83: =D83-SUM(H83,J83,L83,N83,P83,R83,T83) | X83: =D83-SUM(H83,J83,L83,N83,P83,R83,T83,V83) | Y83: =12*COUNT(G83,I83,K83,M83,O83,Q83,U83,W83,S83) | Z83: =IF(AND('0₦'!T86<>0,'0₦'!T86<>""),9,0) + 0 | AA83: ='0₦'!BI86 + 0 | AB83: ='0₦'!BE86 | AC83: ='0₦'!BC86 + 0 | AD83: ='0₦'!BD86 | AE83: ='0₦'!AX86 | AF83: =hcbi!AA87+hcbi!Y87 | AG83: ='0₦'!AW86 | AH83: =0 | AK83: 746 | AL83: 462
B84: =B83+1 | C84: sf21 | D84: =SUM(Y84:AH84) | E84: ='0₦'!AF87 | F84: ='0₦'!AG87 | H84: =D84 | J84: =D84-H84 | L84: =D84-SUM(H84,J84) | N84: =D84-SUM(H84,J84,L84,) | P84: =D84-SUM(H84,J84,L84,N84) | R84: =D84-SUM(H84,J84,L84,N84,P84) | T84: =D84-SUM(H84,J84,L84,N84,P84,R84) | V84: =D84-SUM(H84,J84,L84,N84,P84,R84,T84) | X84: =D84-SUM(H84,J84,L84,N84,P84,R84,T84,V84) | Y84: =12*COUNT(G84,I84,K84,M84,O84,Q84,U84,W84,S84) | Z84: =IF(AND('0₦'!T87<>0,'0₦'!T87<>""),9,0) + 0 | AA84: ='0₦'!BI87 + 0 | AB84: ='0₦'!BE87 | AC84: ='0₦'!BC87 + 0 | AD84: ='0₦'!BD87 | AE84: ='0₦'!AX87 | AF84: =hcbi!AA88+hcbi!Y88 | AG84: ='0₦'!AW87 | AH84: =0 | AK84: 745 | AL84: 162
B85: =B84+1 | C85: sf21 | D85: =SUM(Y85:AH85) | E85: ='0₦'!AF88 | F85: ='0₦'!AG88 | H85: =D85 | J85: =D85-H85 | L85: =D85-SUM(H85,J85) | N85: =D85-SUM(H85,J85,L85,) | P85: =D85-SUM(H85,J85,L85,N85) | R85: =D85-SUM(H85,J85,L85,N85,P85) | T85: =D85-SUM(H85,J85,L85,N85,P85,R85) | V85: =D85-SUM(H85,J85,L85,N85,P85,R85,T85) | X85: =D85-SUM(H85,J85,L85,N85,P85,R85,T85,V85) | Y85: =12*COUNT(G85,I85,K85,M85,O85,Q85,U85,W85,S85) | Z85: =IF(AND('0₦'!T88<>0,'0₦'!T88<>""),9,0) + 0 | AA85: ='0₦'!BI88 + 0 | AB85: ='0₦'!BE88 | AC85: ='0₦'!BC88 + 0 | AD85: ='0₦'!BD88 | AE85: ='0₦'!AX88 | AF85: =hcbi!AA89+hcbi!Y89+10+20 | AG85: ='0₦'!AW88 | AH85: =0 | AK85: 664 | AL85: 11
A86: =A79+0.1 | B86: =B85+1 | C86: sf21 | D86: =SUM(Y86:AH86) | E86: ='0₦'!AF89 | F86: ='0₦'!AG89 | H86: =D86 | J86: =D86-H86 | L86: =D86-SUM(H86,J86) | N86: =D86-SUM(H86,J86,L86,) | P86: =D86-SUM(H86,J86,L86,N86) | R86: =D86-SUM(H86,J86,L86,N86,P86) | T86: =D86-SUM(H86,J86,L86,N86,P86,R86) | V86: =D86-SUM(H86,J86,L86,N86,P86,R86,T86) | X86: =D86-SUM(H86,J86,L86,N86,P86,R86,T86,V86) | Y86: =12*COUNT(G86,I86,K86,M86,O86,Q86,U86,W86,S86) | Z86: =IF(AND('0₦'!T89<>0,'0₦'!T89<>""),9,0) + 0 | AA86: ='0₦'!BI89 + 0 | AB86: ='0₦'!BE89 | AC86: ='0₦'!BC89 + 0 | AD86: ='0₦'!BD89 | AE86: ='0₦'!AX89 | AF86: =hcbi!AA90+hcbi!Y90 | AG86: ='0₦'!AW89 | AH86: =0 | AK86: 629 | AL86: 192
B87: =B86+1 | C87: sf21 | D87: =SUM(Y87:AH87) | E87: ='0₦'!AF90 | F87: ='0₦'!AG90 | H87: =D87 | J87: =D87-H87 | L87: =D87-SUM(H87,J87) | N87: =D87-SUM(H87,J87,L87,) | P87: =D87-SUM(H87,J87,L87,N87) | R87: =D87-SUM(H87,J87,L87,N87,P87) | T87: =D87-SUM(H87,J87,L87,N87,P87,R87) | V87: =D87-SUM(H87,J87,L87,N87,P87,R87,T87) | X87: =D87-SUM(H87,J87,L87,N87,P87,R87,T87,V87) | Y87: =12*COUNT(G87,I87,K87,M87,O87,Q87,U87,W87,S87) | Z87: =IF(AND('0₦'!T90<>0,'0₦'!T90<>""),9,0) + 0 | AA87: ='0₦'!BI90 + 0 | AB87: ='0₦'!BE90 | AC87: ='0₦'!BC90 + 0 | AD87: ='0₦'!BD90 | AE87: ='0₦'!AX90 | AF87: =hcbi!AA91+hcbi!Y91 | AG87: ='0₦'!AW90 | AH87: =0 | AK87: 855 | AL87: 153
B88: =B87+1 | C88: sf21 | D88: =SUM(Y88:AH88) | E88: ='0₦'!AF91 | F88: ='0₦'!AG91 | H88: =D88 | J88: =D88-H88 | L88: =D88-SUM(H88,J88) | N88: =D88-SUM(H88,J88,L88,) | P88: =D88-SUM(H88,J88,L88,N88) | R88: =D88-SUM(H88,J88,L88,N88,P88) | T88: =D88-SUM(H88,J88,L88,N88,P88,R88) | V88: =D88-SUM(H88,J88,L88,N88,P88,R88,T88) | X88: =D88-SUM(H88,J88,L88,N88,P88,R88,T88,V88) | Y88: =12*COUNT(G88,I88,K88,M88,O88,Q88,U88,W88,S88) | Z88: =IF(AND('0₦'!T91<>0,'0₦'!T91<>""),9,0) + 0 | AA88: ='0₦'!BI91 + 0 | AB88: ='0₦'!BE91 | AC88: ='0₦'!BC91 + 0 | AD88: ='0₦'!BD91 | AE88: ='0₦'!AX91 | AF88: =hcbi!AA92+hcbi!Y92 | AG88: ='0₦'!AW91 | AH88: =0 | AK88: 529 | AL88: 143
B89: =B88+1 | C89: sf21 | D89: =SUM(Y89:AH89) | E89: ='0₦'!AF92 | F89: ='0₦'!AG92 | H89: =D89 | J89: =D89-H89 | L89: =D89-SUM(H89,J89) | N89: =D89-SUM(H89,J89,L89,) | P89: =D89-SUM(H89,J89,L89,N89) | R89: =D89-SUM(H89,J89,L89,N89,P89) | T89: =D89-SUM(H89,J89,L89,N89,P89,R89) | V89: =D89-SUM(H89,J89,L89,N89,P89,R89,T89) | X89: =D89-SUM(H89,J89,L89,N89,P89,R89,T89,V89) | Y89: =12*COUNT(G89,I89,K89,M89,O89,Q89,U89,W89,S89) | Z89: =IF(AND('0₦'!T92<>0,'0₦'!T92<>""),9,0) + 0 | AA89: ='0₦'!BI92 + 0 | AB89: ='0₦'!BE92 | AC89: ='0₦'!BC92 + 0 | AD89: ='0₦'!BD92 | AE89: ='0₦'!AX92 | AF89: =hcbi!AA93+hcbi!Y93 | AG89: ='0₦'!AW92 | AH89: =0 | AK89: 728 | AL89: 133
B90: =B89+1 | C90: sf21 | D90: =SUM(Y90:AH90) | E90: ='0₦'!AF93 | F90: ='0₦'!AG93 | H90: =D90 | J90: =D90-H90 | L90: =D90-SUM(H90,J90) | N90: =D90-SUM(H90,J90,L90,) | P90: =D90-SUM(H90,J90,L90,N90) | R90: =D90-SUM(H90,J90,L90,N90,P90) | T90: =D90-SUM(H90,J90,L90,N90,P90,R90) | V90: =D90-SUM(H90,J90,L90,N90,P90,R90,T90) | X90: =D90-SUM(H90,J90,L90,N90,P90,R90,T90,V90) | Y90: =12*COUNT(G90,I90,K90,M90,O90,Q90,U90,W90,S90) | Z90: =IF(AND('0₦'!T93<>0,'0₦'!T93<>""),9,0) + 0 | AA90: ='0₦'!BI93 + 0 | AB90: ='0₦'!BE93 | AC90: ='0₦'!BC93 + 0 | AD90: ='0₦'!BD93 | AE90: ='0₦'!AX93 | AF90: =hcbi!AA94+hcbi!Y94 | AG90: ='0₦'!AW93 | AH90: =0 | AK90: 724 | AL90: 123
B91: =B90+1 | C91: sf21 | D91: =SUM(Y91:AH91) | E91: ='0₦'!AF94 | F91: ='0₦'!AG94 | H91: =D91 | J91: =D91-H91 | L91: =D91-SUM(H91,J91) | N91: =D91-SUM(H91,J91,L91,) | P91: =D91-SUM(H91,J91,L91,N91) | R91: =D91-SUM(H91,J91,L91,N91,P91) | T91: =D91-SUM(H91,J91,L91,N91,P91,R91) | V91: =D91-SUM(H91,J91,L91,N91,P91,R91,T91) | X91: =D91-SUM(H91,J91,L91,N91,P91,R91,T91,V91) | Y91: =12*COUNT(G91,I91,K91,M91,O91,Q91,U91,W91,S91) | Z91: =IF(AND('0₦'!T94<>0,'0₦'!T94<>""),9,0) + 0 | AA91: ='0₦'!BI94 + 0 | AB91: ='0₦'!BE94 | AC91: ='0₦'!BC94 + 0 | AD91: ='0₦'!BD94 | AE91: ='0₦'!AX94 | AF91: =hcbi!AA95+hcbi!Y95 | AG91: ='0₦'!AW94 | AH91: =0 | AK91: 596 | AL91: 112
B92: =B91+1 | C92: sf21 | D92: =SUM(Y92:AH92) | E92: ='0₦'!AF95 | F92: ='0₦'!AG95 | H92: =D92 | J92: =D92-H92 | L92: =D92-SUM(H92,J92) | N92: =D92-SUM(H92,J92,L92,) | P92: =D92-SUM(H92,J92,L92,N92) | R92: =D92-SUM(H92,J92,L92,N92,P92) | T92: =D92-SUM(H92,J92,L92,N92,P92,R92) | V92: =D92-SUM(H92,J92,L92,N92,P92,R92,T92) | X92: =D92-SUM(H92,J92,L92,N92,P92,R92,T92,V92) | Y92: =12*COUNT(G92,I92,K92,M92,O92,Q92,U92,W92,S92) | Z92: =IF(AND('0₦'!T95<>0,'0₦'!T95<>""),9,0) + 0 | AA92: ='0₦'!BI95 + 0 | AB92: ='0₦'!BE95 | AC92: ='0₦'!BC95 + 0 | AD92: ='0₦'!BD95 | AE92: ='0₦'!AX95 | AF92: =hcbi!AA96+hcbi!Y96 | AG92: ='0₦'!AW95 | AH92: =0 | AK92: 723 | AL92: 153
A93: =A58+1 | B93: =B92+1 | C93: sf21 | D93: =SUM(Y93:AH93) | E93: ='0₦'!AF96 | F93: ='0₦'!AG96 | H93: =D93 | J93: =D93-H93 | L93: =D93-SUM(H93,J93) | N93: =D93-SUM(H93,J93,L93,) | P93: =D93-SUM(H93,J93,L93,N93) | R93: =D93-SUM(H93,J93,L93,N93,P93) | T93: =D93-SUM(H93,J93,L93,N93,P93,R93) | V93: =D93-SUM(H93,J93,L93,N93,P93,R93,T93) | X93: =D93-SUM(H93,J93,L93,N93,P93,R93,T93,V93) | Y93: =12*COUNT(G93,I93,K93,M93,O93,Q93,U93,W93,S93) | Z93: =IF(AND('0₦'!T96<>0,'0₦'!T96<>""),9,0) + 0 | AA93: ='0₦'!BI96 + 0 | AB93: ='0₦'!BE96 | AC93: ='0₦'!BC96 + 0 | AD93: ='0₦'!BD96 | AE93: ='0₦'!AX96 | AF93: =hcbi!AA97+hcbi!Y97 | AG93: ='0₦'!AW96 | AH93: =0 | AK93: 667 | AL93: 320
B94: =B93+1 | C94: sf21 | D94: =SUM(Y94:AH94) | E94: ='0₦'!AF97 | F94: ='0₦'!AG97 | H94: =D94 | J94: =D94-H94 | L94: =D94-SUM(H94,J94) | N94: =D94-SUM(H94,J94,L94,) | P94: =D94-SUM(H94,J94,L94,N94) | R94: =D94-SUM(H94,J94,L94,N94,P94) | T94: =D94-SUM(H94,J94,L94,N94,P94,R94) | V94: =D94-SUM(H94,J94,L94,N94,P94,R94,T94) | X94: =D94-SUM(H94,J94,L94,N94,P94,R94,T94,V94) | Y94: =12*COUNT(G94,I94,K94,M94,O94,Q94,U94,W94,S94) | Z94: =IF(AND('0₦'!T97<>0,'0₦'!T97<>""),9,0) + 0 | AA94: ='0₦'!BI97 + 0 | AB94: ='0₦'!BE97 | AC94: ='0₦'!BC97 + 0 | AD94: ='0₦'!BD97 | AE94: ='0₦'!AX97 | AF94: =hcbi!AA98+hcbi!Y98 | AG94: ='0₦'!AW97 | AH94: =0 | AK94: 571 | AL94: 100
B95: =B94+1 | C95: sf21 | D95: =SUM(Y95:AH95) | E95: ='0₦'!AF98 | F95: ='0₦'!AG98 | H95: =D95 | J95: =D95-H95 | L95: =D95-SUM(H95,J95) | N95: =D95-SUM(H95,J95,L95,) | P95: =D95-SUM(H95,J95,L95,N95) | R95: =D95-SUM(H95,J95,L95,N95,P95) | T95: =D95-SUM(H95,J95,L95,N95,P95,R95) | V95: =D95-SUM(H95,J95,L95,N95,P95,R95,T95) | X95: =D95-SUM(H95,J95,L95,N95,P95,R95,T95,V95) | Y95: =12*COUNT(G95,I95,K95,M95,O95,Q95,U95,W95,S95) | Z95: =IF(AND('0₦'!T98<>0,'0₦'!T98<>""),9,0) + 0 | AA95: ='0₦'!BI98 + 0 | AB95: ='0₦'!BE98 | AC95: ='0₦'!BC98 + 0 | AD95: ='0₦'!BD98 | AE95: ='0₦'!AX98 | AF95: =hcbi!AA99+hcbi!Y99 | AG95: ='0₦'!AW98 | AH95: =0 | AK95: 722 | AL95: 100
B96: =B95+1 | C96: sf21 | D96: =SUM(Y96:AH96) | E96: ='0₦'!AF99 | F96: ='0₦'!AG99 | H96: =D96 | J96: =D96-H96 | L96: =D96-SUM(H96,J96) | N96: =D96-SUM(H96,J96,L96,) | P96: =D96-SUM(H96,J96,L96,N96) | R96: =D96-SUM(H96,J96,L96,N96,P96) | T96: =D96-SUM(H96,J96,L96,N96,P96,R96) | V96: =D96-SUM(H96,J96,L96,N96,P96,R96,T96) | X96: =D96-SUM(H96,J96,L96,N96,P96,R96,T96,V96) | Y96: =12*COUNT(G96,I96,K96,M96,O96,Q96,U96,W96,S96) | Z96: =IF(AND('0₦'!T99<>0,'0₦'!T99<>""),9,0) + 0 | AA96: ='0₦'!BI99 + 0 | AB96: ='0₦'!BE99 | AC96: ='0₦'!BC99 + 0 | AD96: ='0₦'!BD99 | AE96: ='0₦'!AX99 | AF96: =hcbi!AA100+hcbi!Y100 | AG96: ='0₦'!AW99 | AH96: =0 | AK96: 633 | AL96: 100
B97: =B96+1 | C97: sf21 | D97: =SUM(Y97:AH97) | E97: ='0₦'!AF100 | F97: ='0₦'!AG100 | H97: =D97 | J97: =D97-H97 | L97: =D97-SUM(H97,J97) | N97: =D97-SUM(H97,J97,L97,) | P97: =D97-SUM(H97,J97,L97,N97) | R97: =D97-SUM(H97,J97,L97,N97,P97) | T97: =D97-SUM(H97,J97,L97,N97,P97,R97) | V97: =D97-SUM(H97,J97,L97,N97,P97,R97,T97) | X97: =D97-SUM(H97,J97,L97,N97,P97,R97,T97,V97) | Y97: =12*COUNT(G97,I97,K97,M97,O97,Q97,U97,W97,S97) | Z97: =IF(AND('0₦'!T100<>0,'0₦'!T100<>""),9,0) + 0 | AA97: ='0₦'!BI100 + 0 | AB97: ='0₦'!BE100 | AC97: ='0₦'!BC100 + 0 | AD97: ='0₦'!BD100 | AE97: ='0₦'!AX100 | AF97: =hcbi!AA101+hcbi!Y101 | AG97: ='0₦'!AW100 | AH97: =0 | AK97: 777 | AL97: 196
B98: =B97+1 | C98: sf21 | D98: =SUM(Y98:AH98) | E98: ='0₦'!AF101 | F98: ='0₦'!AG101 | H98: =D98 | J98: =D98-H98 | L98: =D98-SUM(H98,J98) | N98: =D98-SUM(H98,J98,L98,) | P98: =D98-SUM(H98,J98,L98,N98) | R98: =D98-SUM(H98,J98,L98,N98,P98) | T98: =D98-SUM(H98,J98,L98,N98,P98,R98) | V98: =D98-SUM(H98,J98,L98,N98,P98,R98,T98) | X98: =D98-SUM(H98,J98,L98,N98,P98,R98,T98,V98) | Y98: =12*COUNT(G98,I98,K98,M98,O98,Q98,U98,W98,S98) | Z98: =IF(AND('0₦'!T101<>0,'0₦'!T101<>""),9,0) + 0 | AA98: ='0₦'!BI101 + 0 | AB98: ='0₦'!BE101 | AC98: ='0₦'!BC101 + 0 | AD98: ='0₦'!BD101 | AE98: ='0₦'!AX101 | AF98: =hcbi!AA102+hcbi!Y102 | AG98: ='0₦'!AW101 | AH98: =0 | AK98: 735 | AL98: 825
B99: =B98+1 | C99: sf21 | D99: =SUM(Y99:AH99) | E99: ='0₦'!AF102 | F99: ='0₦'!AG102 | H99: =D99 | J99: =D99-H99 | L99: =D99-SUM(H99,J99) | N99: =D99-SUM(H99,J99,L99,) | P99: =D99-SUM(H99,J99,L99,N99) | R99: =D99-SUM(H99,J99,L99,N99,P99) | T99: =D99-SUM(H99,J99,L99,N99,P99,R99) | V99: =D99-SUM(H99,J99,L99,N99,P99,R99,T99) | X99: =D99-SUM(H99,J99,L99,N99,P99,R99,T99,V99) | Y99: =12*COUNT(G99,I99,K99,M99,O99,Q99,U99,W99,S99) | Z99: =IF(AND('0₦'!T102<>0,'0₦'!T102<>""),9,0) + 0 | AA99: ='0₦'!BI102 + 0 | AB99: ='0₦'!BE102 | AC99: ='0₦'!BC102 + 0 | AD99: ='0₦'!BD102 | AE99: ='0₦'!AX102 | AF99: =hcbi!AA103+hcbi!Y103+20+5 | AG99: ='0₦'!AW102 | AH99: =0 | AK99: 733 | AL99: 319
A100: =A93+0.1 | B100: =B99+1 | C100: sf21 | D100: =SUM(Y100:AH100) | E100: ='0₦'!AF103 | F100: ='0₦'!AG103 | H100: =D100 | J100: =D100-H100 | L100: =D100-SUM(H100,J100) | N100: =D100-SUM(H100,J100,L100,) | P100: =D100-SUM(H100,J100,L100,N100) | R100: =D100-SUM(H100,J100,L100,N100,P100) | T100: =D100-SUM(H100,J100,L100,N100,P100,R100) | V100: =D100-SUM(H100,J100,L100,N100,P100,R100,T100) | X100: =D100-SUM(H100,J100,L100,N100,P100,R100,T100,V100) | Y100: =12*COUNT(G100,I100,K100,M100,O100,Q100,U100,W100,S100) | Z100: =IF(AND('0₦'!T103<>0,'0₦'!T103<>""),9,0) + 0 | AA100: ='0₦'!BI103 + 0 | AB100: ='0₦'!BE103 | AC100: ='0₦'!BC103 + 0 | AD100: ='0₦'!BD103 | AE100: ='0₦'!AX103 | AF100: =hcbi!AA104+hcbi!Y104 | AG100: ='0₦'!AW103 | AH100: =0 | AK100: 757 | AL100: 358
...

Sheet 0₦
C1: 2026 | D1: 睡觉 | E1: cpap | F1: 起 | G1: i444 | H1: i47 | I1: 充 | J1: tmrw | K1: 2hci | L1: d hci | M1: @jm | N1: 新闻 | O1: 词汇 | P1: hcmc | Q1: 0t | R1: ₦156 | S1: 0l | T1: 0₲ | U1: stats | V1: notes | W1: @microsoft, @github | X1: 代 | Y1: tms | Z1: slack | AA1: slack | AB1: @m5 | AC1: dash | AD1: 早餐 | AE1: hiit | AF1: ⎣₦ | AG1: ⎣∀clr | AH1: # | AI1: 问学 | AJ1: qft | AK1: lx:qt | AL1: NVC + e | AM1: ص | AN1: o314 | AO1: 冥想 | AP1: 其他人 | AR1: 1+ | AS1: -1 | AT1: -2/-4 | AU1: -3 | AW1: ∑xk87 | AX1: ∑hcmt | AY1: ∑hcmc | AZ1: ∑hcb | BA1: 蠢之后 | BD1: hcmc | BE1: m5x2
C2: ⊖分 | D2: 30 | E2: 10 | F2: 6 | G2: 5 | H2: 5 | I2: 3 | J2: 5 | K2: 7 | L2: 26 | M2: 5 | N2: 2 | O2: 7 | P2: 10 | Q2: 10 | R2: 4 | S2: 20 | T2: 8 | U2: 10 | V2: 8 | W2: 20 | X2: 30 | Y2: 7 | Z2: 5 | AA2: 3 | AB2: 15 | AC2: 15 | AD2: 5 | AE2: 7 | AF2: =SUM(V2:AB2,S2:T2,M2,) | AI2: 60 | AJ2: 30 | AK2: 30 | AL2: 1 | AM2: 60 | AN2: 15 | AO2: 10 | AP2: 5 | AR2: 0 | AS2: 10 | AT2: 60 | AU2: 15 | AW2: =SUM(AI2:AL2) | AX2: =SUM(AM2:AP2) | AY2: =SUM(AU2+AT2*0.5)-AR2-#REF!*0.5+#REF!*0.5
C3: p(t) | D3: 500 | E3: 2 | H3: 5 | I3: 3 | J3: 3 | K3: 10 | L3: 25 | M3: 7 | Q3: 12 | R3: 4 | S3: 12 | T3: 6 | U3: 8 | V3: 5 | X3: 40 | AA3: 30 | AB3: 5 | AC3: 3 | AI3: 60 | AM3: 20 | AN3: 15 | AO3: 10 | AP3: 5 | AR3: 54
C4: Ideal time | D4: 480 | E4: 2 | F4: 5 | H4: 3 | I4: 1 | J4: 1 | K4: 8 | L4: 11 | M4: 6 | N4: 7 | O4: 7 | Q4: 5 | R4: 3 | S4: 8 | T4: 5 | U4: 6 | V4: 4 | X4: 30 | AA4: 10 | AB4: 3 | AC4: 2 | AD4: 12 | AE4: 35 | AH4: 3 | AI4: 45 | AJ4: 45 | AK4: 30 | AL4: 1 | AM4: 5 | AN4: =SUM(AN5:AN101)-COUNT(AN5:AN101)*15 | AO4: =SUM(AO5:AO101)-COUNT(AO5:AO101)*15 | AP4: =SUM(AP5:AP101)-COUNT(AP5:AP101)*5
A5: 1.1 | B5: S | C5: 46026 | D5: 540 | E5: 2 | F5: 13 | H5: 1 | I5: 1 | J5: 1 | K5: 5 | L5: 13 | M5: 1 | N5: 7 | O5: 5 | P5: 30 | Q5: 4 | R5: 1 | S5: 23 | T5: 3 | U5: 3 | V5: 4 | W5: 2 | Y5: 3 | Z5: 1 | AA5: 1 | AB5: 10 | AC5: 1 | AD5: 3 | AE5: 1 | AF5: 915 | AG5: 1406 | AH5: 2 | AI5: =51+10 | AJ5: =123+61 | AK5: 30 | AL5: 1 | AM5: 85 | AN5: 0 | AO5: 0 | AP5: 0 | AR5: -1 | AS5: =P5 | AT5: 10 | AU5: 7 | AW5: =SUM(AH5:AI5,AJ5/2,AK5:AL5) | AX5: =AM5*0.5+SUM(AN5:AP5) | AY5: =SUM(-AR5+AS5*0.01+AT5*0.5+AU5) | AZ5: ='0分'!AF2 | BA5: =SUM(AY5,AX5,AW5) | BC5: {=SUMPRODUCT(--(NOT(ISBLANK('0₦'!D5:M5))), '0₦'!D$2:M$2) + SUMPRODUCT(--(NOT(ISBLANK('0₦'!Q5:T5))), '0₦'!Q$2:T$2)} | BD5: {=SUMPRODUCT(--(NOT(ISBLANK('0₦'!N5:P5))),'0₦'!N$2:P$2)+'0₦'!AY5} | BE5: {=SUMPRODUCT(--(NOT(ISBLANK('0₦'!AA5:AC5))),'0₦'!AA$2:AC$2) + BF5} | BG5: {=SUMPRODUCT(--(NOT(ISBLANK('0₦'!U5:Z5))), '0₦'!U$2:Z$2)} | BI5: =SUM(BG5:BH5)
B6: M | C6: =C5+1 | D6: 484 | E6: 1 | F6: 3 | H6: 1 | I6: 1 | J6: 1 | K6: 7 | L6: 17 | M6: 3 | N6: 10 | P6: 65 | Q6: 1 | R6: 1 | S6: 6 | T6: 3 | U6: 2 | V6: 1 | W6: 1 | Y6: 1 | Z6: 1 | AA6: 1 | AB6: 1 | AC6: 1 | AD6: 3 | AE6: 1 | AF6: 753 | AG6: 1527 | AH6: 1 | AI6: =5+25+23+15 + 50 + 45 + 10 | AJ6: =22+60 | AK6: =15+36 | AL6: 1 | AM6: 90 | AN6: 9 | AO6: 0 | AP6: 0 | AR6: -1 | AS6: =P6 | AT6: 10 | AU6: 10 | AW6: =SUM(AH6:AI6,AJ6/2,AK6:AL6) | AX6: =AM6*0.5+SUM(AN6:AP6) | AY6: =SUM(-AR6+AS6*0.01+AT6*0.5+AU6) | AZ6: ='0分'!AF3 | BA6: =SUM(AY6,AX6,AW6) | BC6: {=SUMPRODUCT(--(NOT(ISBLANK('0₦'!D6:M6))), '0₦'!D$2:M$2) + SUMPRODUCT(--(NOT(ISBLANK('0₦'!Q6:T6))), '0₦'!Q$2:T$2)} | BD6: {=SUMPRODUCT(--(NOT(ISBLANK('0₦'!N6:P6))),'0₦'!N$2:P$2)+'0₦'!AY6} | BE6: {=SUMPRODUCT(--(NOT(ISBLANK('0₦'!AA6:AC6))),'0₦'!AA$2:AC$2) + BF6} | BG6: {=SUMPRODUCT(--(NOT(ISBLANK('0₦'!U6:Z6))), '0₦'!U$2:Z$2)} | BI6: =SUM(BG6:BH6)
B7: T | C7: =C6+1 | D7: 510 | E7: 2 | F7: 2 | G7: 240 | H7: 1 | I7: 1 | J7: 1 | K7: 5 | L7: 17 | M7: 7 | N7: 11 | P7: 30 | Q7: 4 | R7: 1 | S7: 8 | T7: 3 | U7: 2 | V7: 9 | W7: 20 | X7: 3 | Y7: 7 | Z7: 1 | AA7: 1 | AB7: 8 | AC7: 1 | AD7: 10 | AE7: 1 | AF7: 640 | AG7: 2145 | AH7: 0 | AI7: 0 | AJ7: 5 | AK7: 34 | AL7: 1 | AM7: 91 | AN7: 44 | AO7: 31 | AP7: 0 | AR7: -1 | AS7: =P7 | AT7: 10 | AU7: =11+12+44 | AW7: =SUM(AH7:AI7,AJ7/2,AK7:AL7) | AX7: =AM7*0.5+SUM(AN7:AP7) | AY7: =SUM(-AR7+AS7*0.01+AT7*0.5+AU7) | AZ7: ='0分'!AF4 | BA7: =SUM(AY7,AX7,AW7) | BC7: {=SUMPRODUCT(--(NOT(ISBLANK('0₦'!D7:M7))), '0₦'!D$2:M$2) + SUMPRODUCT(--(NOT(ISBLANK('0₦'!Q7:T7))), '0₦'!Q$2:T$2)} | BD7: {=SUMPRODUCT(--(NOT(ISBLANK('0₦'!N7:P7))),'0₦'!N$2:P$2)+'0₦'!AY7} | BE7: {=SUMPRODUCT(--(NOT(ISBLANK('0₦'!AA7:AC7))),'0₦'!AA$2:AC$2) + BF7} | BG7: {=SUMPRODUCT(--(NOT(ISBLANK('0₦'!U7:Z7))), '0₦'!U$2:Z$2)} | BI7: =SUM(BG7:BH7)
B8: W | C8: =C7+1 | D8: 523 | E8: 0 | F8: 3 | G8: 12 | H8: 1 | I8: 1 | J8: 1 | K8: 4 | L8: 30 | M8: 3 | N8: 12 | P8: 30 | Q8: 3 | R8: 4 | S8: 5 | T8: 3 | U8: 3 | V8: 4 | W8: 15 | Y8: 10 | Z8: 3 | AA8: 4 | AB8: 15 | AC8: 1 | AD8: 5 | AE8: 1 | AF8: 2102 | AH8: 0 | AI8: 0 | AJ8: 5 | AK8: 30 | AL8: 1 | AM8: 60 | AN8: 0 | AO8: 18 | AP8: 0 | AR8: 20 | AS8: =P8 | AT8: 10 | AU8: 12 | AW8: =SUM(AH8:AI8,AJ8/2,AK8:AL8) | AX8: =AM8*0.5+SUM(AN8:AP8) | AY8: =SUM(-AR8+AS8*0.01+AT8*0.5+AU8) | AZ8: ='0分'!AF5 | BA8: =SUM(AY8,AX8,AW8) | BC8: {=SUMPRODUCT(--(NOT(ISBLANK('0₦'!D8:M8))), '0₦'!D$2:M$2) + SUMPRODUCT(--(NOT(ISBLANK('0₦'!Q8:T8))), '0₦'!Q$2:T$2)} | BD8: {=SUMPRODUCT(--(NOT(ISBLANK('0₦'!N8:P8))),'0₦'!N$2:P$2)+'0₦'!AY8} | BE8: {=SUMPRODUCT(--(NOT(ISBLANK('0₦'!AA8:AC8))),'0₦'!AA$2:AC$2) + BF8} | BG8: {=SUMPRODUCT(--(NOT(ISBLANK('0₦'!U8:Z8))), '0₦'!U$2:Z$2)} | BI8: =SUM(BG8:BH8)
B9: Th | C9: =C8+1 | D9: 490 | E9: 0 | F9: 5 | G9: 15 | H9: 2 | I9: 1 | J9: 1 | K9: 3 | L9: 15 | M9: 2 | N9: 10 | P9: 30 | Q9: 2 | R9: 1 | S9: 6 | T9: 3 | U9: 2 | V9: 26 | W9: 15 | Y9: 15 | Z9: 2 | AA9: 1 | AB9: 5 | AC9: 1 | AD9: 22 | AE9: 1 | AF9: 1341 | AG9: 1344 | AH9: 1 | AI9: 0 | AJ9: 0 | AK9: 35 | AL9: 1 | AM9: 47 | AN9: 0 | AO9: 15 | AP9: 0 | AR9: -1 | AS9: 90 | AT9: 20 | AU9: 10 | AW9: =SUM(AH9:AI9,AJ9/2,AK9:AL9) | AX9: =AM9*0.5+SUM(AN9:AP9) | AY9: =SUM(-AR9+AS9*0.01+AT9*0.5+AU9) | AZ9: ='0分'!AF6 | BA9: =SUM(AY9,AX9,AW9) | BC9: {=SUMPRODUCT(--(NOT(ISBLANK('0₦'!D9:M9))), '0₦'!D$2:M$2) + SUMPRODUCT(--(NOT(ISBLANK('0₦'!Q9:T9))), '0₦'!Q$2:T$2)} | BD9: {=SUMPRODUCT(--(NOT(ISBLANK('0₦'!N9:P9))),'0₦'!N$2:P$2)+'0₦'!AY9} | BE9: {=SUMPRODUCT(--(NOT(ISBLANK('0₦'!AA9:AC9))),'0₦'!AA$2:AC$2) + BF9} | BG9: {=SUMPRODUCT(--(NOT(ISBLANK('0₦'!U9:Z9))), '0₦'!U$2:Z$2)} | BI9: =SUM(BG9:BH9)
B10: F | C10: =C9+1 | D10: 510 | E10: 0 | F10: 23 | G10: 15 | H10: 1 | I10: 1 | J10: 1 | K10: 4 | L10: 15 | M10: 3 | N10: 12 | P10: 30 | Q10: 4 | R10: 1 | S10: 4 | T10: 4 | U10: 2 | V10: 6 | W10: 20 | Y10: 10 | Z10: 1 | AA10: 3 | AB10: 15 | AC10: 3 | AD10: 25 | AE10: 1 | AF10: 901 | AG10: 2216 | AH10: 0 | AI10: =70+30+15+10+5+5 | AJ10: 45 | AK10: 35 | AL10: 1 | AM10: 67 | AN10: 15 | AO10: 16 | AP10: =18+22 | AR10: 2 | AS10: 30 | AT10: 35 | AU10: 12 | AW10: =SUM(AH10:AI10,AJ10/2,AK10:AL10) | AX10: =AM10*0.5+SUM(AN10:AP10) | AY10: =SUM(-AR10+AS10*0.01+AT10*0.5+AU10) | AZ10: ='0分'!AF7 | BA10: =SUM(AY10,AX10,AW10) | BC10: {=SUMPRODUCT(--(NOT(ISBLANK('0₦'!D10:M10))), '0₦'!D$2:M$2) + SUMPRODUCT(--(NOT(ISBLANK('0₦'!Q10:T10))), '0₦'!Q$2:T$2)} | BD10: {=SUMPRODUCT(--(NOT(ISBLANK('0₦'!N10:P10))),'0₦'!N$2:P$2)+'0₦'!AY10} | BE10: {=SUMPRODUCT(--(NOT(ISBLANK('0₦'!AA10:AC10))),'0₦'!AA$2:AC$2) + BF10} | BG10: {=SUMPRODUCT(--(NOT(ISBLANK('0₦'!U10:Z10))), '0₦'!U$2:Z$2)} | BI10: =SUM(BG10:BH10)
B11: S | C11: =C10+1 | D11: 422 | E11: 0 | F11: 15 | G11: 15 | H11: 1 | I11: 1 | J11: 1 | K11: 3 | L11: 12 | M11: 5 | N11: 13 | P11: 20 | Q11: 7 | R11: 1 | S11: 9 | T11: 5 | U11: 3 | V11: 2 | W11: 2 | Y11: 10 | Z11: 1 | AA11: 1 | AB11: 9 | AC11: 1 | AD11: 5 | AE11: 7 | AF11: 757 | AG11: 1537 | AH11: 0 | AI11: =23+10 + 18 + 5 + 17 + 35 + 10 + 61 | AJ11: 200 | AK11: 54 | AL11: 1 | AM11: 81 | AN11: 0 | AO11: 0 | AP11: 21 | AR11: -1 | AS11: 30 | AT11: 5 | AU11: 13 | AW11: =SUM(AH11:AI11,AJ11/2,AK11:AL11) | AX11: =AM11*0.5+SUM(AN11:AP11) | AY11: =SUM(-AR11+AS11*0.01+AT11*0.5+AU11) | AZ11: ='0分'!AF8 | BA11: =SUM(AY11,AX11,AW11) | BC11: {=SUMPRODUCT(--(NOT(ISBLANK('0₦'!D11:M11))), '0₦'!D$2:M$2) + SUMPRODUCT(--(NOT(ISBLANK('0₦'!Q11:T11))), '0₦'!Q$2:T$2)} | BD11: {=SUMPRODUCT(--(NOT(ISBLANK('0₦'!N11:P11))),'0₦'!N$2:P$2)+'0₦'!AY11} | BE11: {=SUMPRODUCT(--(NOT(ISBLANK('0₦'!AA11:AC11))),'0₦'!AA$2:AC$2) + BF11} | BG11: {=SUMPRODUCT(--(NOT(ISBLANK('0₦'!U11:Z11))), '0₦'!U$2:Z$2)} | BI11: =SUM(BG11:BH11)
A12: =A5+0.1 | B12: S | C12: =C11+1 | D12: 505 | E12: 0 | F12: 3 | H12: 1 | I12: 1 | J12: 1 | K12: 3 | L12: 15 | M12: 3 | N12: 11 | P12: 30 | Q12: 3 | R12: 2 | S12: 3 | T12: 4 | U12: 10 | V12: 5 | W12: 3 | Y12: 1 | Z12: 1 | AA12: 1 | AB12: 1 | AC12: 1 | AD12: 10 | AE12: 20 | AF12: 759 | AG12: 1315 | AH12: 0 | AI12: =70+33+24+10 | AJ12: 135 | AK12: 18 | AL12: 1 | AM12: 102 | AN12: 0 | AO12: 0 | AP12: =19+16 | AR12: -1 | AS12: 30 | AT12: 20 | AU12: =N12+O12 | AW12: =SUM(AH12:AI12,AJ12/2,AK12:AL12) | AX12: =AM12*0.5+SUM(AN12:AP12) | AY12: =SUM(-AR12+AS12*0.01+AT12*0.5+AU12) | AZ12: ='0分'!AF9 | BA12: =SUM(AY12,AX12,AW12) | BC12: {=SUMPRODUCT(--(NOT(ISBLANK('0₦'!D12:M12))), '0₦'!D$2:M$2) + SUMPRODUCT(--(NOT(ISBLANK('0₦'!Q12:T12))), '0₦'!Q$2:T$2)} | BD12: {=SUMPRODUCT(--(NOT(ISBLANK('0₦'!N12:P12))),'0₦'!N$2:P$2)+'0₦'!AY12} | BE12: {=SUMPRODUCT(--(NOT(ISBLANK('0₦'!AA12:AC12))),'0₦'!AA$2:AC$2) + BF12} | BG12: {=SUMPRODUCT(--(NOT(ISBLANK('0₦'!U12:Z12))), '0₦'!U$2:Z$2)} | BI12: =SUM(BG12:BH12)
B13: M | C13: =C12+1 | D13: 510 | E13: 0 | F13: 2 | G13: 12 | H13: 1 | I13: 1 | J13: 1 | K13: 3 | L13: 15 | M13: 3 | N13: 8 | P13: 30 | Q13: 6 | R13: 1 | S13: 12 | T13: 5 | U13: 4 | V13: 2 | W13: 10 | Y13: 15 | Z13: 1 | AA13: 3 | AB13: 2 | AC13: 1 | AD13: 15 | AE13: 43 | AF13: 811 | AG13: 1900 | AH13: 0 | AI13: =63+10+30+10 | AJ13: 0 | AK13: 24 | AL13: 1 | AM13: 88 | AN13: 0 | AO13: 0 | AP13: 0 | AR13: 20 | AS13: 150 | AT13: 30 | AU13: 16 | AW13: =SUM(AH13:AI13,AJ13/2,AK13:AL13) | AX13: =AM13*0.5+SUM(AN13:AP13) | AY13: =SUM(-AR13+AS13*0.01+AT13*0.5+AU13) | AZ13: ='0分'!AF10 | BA13: =SUM(AY13,AX13,AW13) | BC13: {=SUMPRODUCT(--(NOT(ISBLANK('0₦'!D13:M13))), '0₦'!D$2:M$2) + SUMPRODUCT(--(NOT(ISBLANK('0₦'!Q13:T13))), '0₦'!Q$2:T$2)} | BD13: {=SUMPRODUCT(--(NOT(ISBLANK('0₦'!N13:P13))),'0₦'!N$2:P$2)+'0₦'!AY13} | BE13: {=SUMPRODUCT(--(NOT(ISBLANK('0₦'!AA13:AC13))),'0₦'!AA$2:AC$2) + BF13} | BG13: {=SUMPRODUCT(--(NOT(ISBLANK('0₦'!U13:Z13))), '0₦'!U$2:Z$2)} | BI13: =SUM(BG13:BH13)
B14: T | C14: =C13+1 | D14: 570 | E14: 0 | F14: 2 | H14: 1 | I14: 1 | J14: 1 | K14: 2 | L14: 15 | M14: 2 | N14: 20 | P14: 60 | Q14: 4 | R14: 1 | S14: 12 | T14: 3 | U14: 6 | V14: 2 | W14: 5 | Y14: 15 | Z14: 3 | AA14: 3 | AB14: 17 | AC14: 1 | AD14: 15 | AE14: 1 | AF14: 1223 | AG14: 1952 | AH14: 0 | AI14: =45+5 + 20 + 5 + 60 + 5 | AJ14: 45 | AK14: =15+60 | AL14: 1 | AM14: 60 | AN14: 0 | AO14: 0 | AP14: 0 | AR14: -1 | AS14: 30 | AT14: 5 | AU14: =N14+O14 | AW14: =SUM(AH14:AI14,AJ14/2,AK14:AL14) | AX14: =AM14*0.5+SUM(AN14:AP14) | AY14: =SUM(-AR14+AS14*0.01+AT14*0.5+AU14) | AZ14: ='0分'!AF11 | BA14: =SUM(AY14,AX14,AW14) | BC14: {=SUMPRODUCT(--(NOT(ISBLANK('0₦'!D14:M14))), '0₦'!D$2:M$2) + SUMPRODUCT(--(NOT(ISBLANK('0₦'!Q14:T14))), '0₦'!Q$2:T$2)} | BD14: {=SUMPRODUCT(--(NOT(ISBLANK('0₦'!N14:P14))),'0₦'!N$2:P$2)+'0₦'!AY14} | BE14: {=SUMPRODUCT(--(NOT(ISBLANK('0₦'!AA14:AC14))),'0₦'!AA$2:AC$2) + BF14} | BG14: {=SUMPRODUCT(--(NOT(ISBLANK('0₦'!U14:Z14))), '0₦'!U$2:Z$2)} | BI14: =SUM(BG14:BH14)
B15: W | C15: =C14+1 | D15: 491 | E15: 2 | F15: 2 | H15: 1 | I15: 1 | J15: 1 | K15: 3 | L15: 15 | M15: 3 | N15: 11 | P15: 30 | Q15: 7 | R15: 2 | S15: 3 | T15: 1 | U15: 5 | V15: 6 | W15: 6 | Y15: 15 | Z15: 1 | AA15: 1 | AB15: 3 | AC15: 4 | AD15: 13 | AE15: 1 | AF15: 805 | AG15: 1348 | AH15: 0 | AI15: 54 | AJ15: 0 | AK15: =25+30 | AL15: 1 | AM15: 63 | AN15: 59 | AO15: =13+8 | AP15: =12 | AR15: -1 | AS15: 30 | AT15: 15 | AU15: 26 | AW15: =SUM(AH15:AI15,AJ15/2,AK15:AL15) | AX15: =AM15*0.5+SUM(AN15:AP15) | AY15: =SUM(-AR15+AS15*0.01+AT15*0.5+AU15) | AZ15: ='0分'!AF12 | BA15: =SUM(AY15,AX15,AW15) | BC15: {=SUMPRODUCT(--(NOT(ISBLANK('0₦'!D15:M15))), '0₦'!D$2:M$2) + SUMPRODUCT(--(NOT(ISBLANK('0₦'!Q15:T15))), '0₦'!Q$2:T$2)} | BD15: {=SUMPRODUCT(--(NOT(ISBLANK('0₦'!N15:P15))),'0₦'!N$2:P$2)+'0₦'!AY15} | BE15: {=SUMPRODUCT(--(NOT(ISBLANK('0₦'!AA15:AC15))),'0₦'!AA$2:AC$2) + BF15} | BG15: {=SUMPRODUCT(--(NOT(ISBLANK('0₦'!U15:Z15))), '0₦'!U$2:Z$2)} | BI15: =SUM(BG15:BH15)
B16: Th | C16: =C15+1 | D16: 431 | E16: 2 | F16: 14 | G16: 15 | H16: 1 | I16: 1 | J16: 1 | K16: 2 | L16: 20 | M16: 3 | N16: 20 | O16: 7 | P16: 30 | Q16: 5 | R16: 1 | S16: 4 | T16: 3 | U16: 3 | V16: 7 | W16: 10 | Y16: 10 | Z16: 1 | AA16: 1 | AB16: 14 | AC16: 1 | AD16: 17 | AE16: 1 | AF16: 1400 | AH16: 0 | AI16: 0 | AJ16: 0 | AK16: 15 | AL16: 1 | AM16: 39 | AN16: 14 | AO16: 0 | AP16: 0 | AR16: 65 | AS16: 25 | AT16: 30 | AU16: =N16+O16-14 | AW16: =SUM(AH16:AI16,AJ16/2,AK16:AL16) | AX16: =AM16*0.5+SUM(AN16:AP16) | AY16: =SUM(-AR16+AS16*0.01+AT16*0.5+AU16) | AZ16: ='0分'!AF13 | BA16: =SUM(AY16,AX16,AW16) | BC16: {=SUMPRODUCT(--(NOT(ISBLANK('0₦'!D16:M16))), '0₦'!D$2:M$2) + SUMPRODUCT(--(NOT(ISBLANK('0₦'!Q16:T16))), '0₦'!Q$2:T$2)} | BD16: {=SUMPRODUCT(--(NOT(ISBLANK('0₦'!N16:P16))),'0₦'!N$2:P$2)+'0₦'!AY16} | BE16: {=SUMPRODUCT(--(NOT(ISBLANK('0₦'!AA16:AC16))),'0₦'!AA$2:AC$2) + BF16} | BG16: {=SUMPRODUCT(--(NOT(ISBLANK('0₦'!U16:Z16))), '0₦'!U$2:Z$2)} | BI16: =SUM(BG16:BH16)
B17: F | C17: =C16+1 | D17: 475 | E17: 2 | F17: 10 | G17: 15 | H17: 1 | I17: 1 | J17: 1 | K17: 3 | L17: 15 | M17: 2 | N17: 10 | O17: 8 | P17: 20 | Q17: 2 | R17: 1 | S17: 13 | T17: 4 | U17: 4 | V17: 8 | W17: 10 | Y17: 15 | Z17: 1 | AA17: 1 | AB17: 5 | AC17: 1 | AD17: 16 | AE17: 1 | AF17: 841 | AG17: 1339 | AH17: 1 | AI17: 0 | AJ17: 0 | AK17: =10+48 | AL17: 1 | AM17: 67 | AN17: 0 | AO17: 37 | AP17: 28 | AR17: -1 | AS17: 30 | AT17: =10+25 | AU17: 14 | AW17: =SUM(AH17:AI17,AJ17/2,AK17:AL17) | AX17: =AM17*0.5+SUM(AN17:AP17) | AY17: =SUM(-AR17+AS17*0.01+AT17*0.5+AU17) | AZ17: ='0分'!AF14 | BA17: =SUM(AY17,AX17,AW17) | BC17: {=SUMPRODUCT(--(NOT(ISBLANK('0₦'!D17:M17))), '0₦'!D$2:M$2) + SUMPRODUCT(--(NOT(ISBLANK('0₦'!Q17:T17))), '0₦'!Q$2:T$2)} | BD17: {=SUMPRODUCT(--(NOT(ISBLANK('0₦'!N17:P17))),'0₦'!N$2:P$2)+'0₦'!AY17} | BE17: {=SUMPRODUCT(--(NOT(ISBLANK('0₦'!AA17:AC17))),'0₦'!AA$2:AC$2) + BF17} | BG17: {=SUMPRODUCT(--(NOT(ISBLANK('0₦'!U17:Z17))), '0₦'!U$2:Z$2)} | BI17: =SUM(BG17:BH17)
B18: S | C18: =C17+1 | D18: 449 | E18: 1 | F18: 10 | G18: 25 | H18: 1 | I18: 1 | J18: 1 | K18: 3 | L18: 10 | M18: 2 | N18: 11 | O18: 6 | P18: 30 | Q18: 5 | R18: 1 | S18: 8 | T18: 4 | U18: 5 | V18: 3 | W18: 21 | Y18: 6 | Z18: 1 | AA18: 1 | AB18: 5 | AC18: 1 | AD18: 10 | AE18: 20 | AF18: 904 | AG18: 1937 | AH18: 0 | AI18: =38+15+10+5+10 + 89+5 | AJ18: 200 | AK18: 60 | AL18: 1 | AM18: 92 | AN18: 0 | AO18: 0 | AP18: 30 | AR18: -1 | AS18: 30 | AT18: 0 | AU18: =N18+O18 | AW18: =SUM(AH18:AI18,AJ18/2,AK18:AL18) | AX18: =AM18*0.5+SUM(AN18:AP18) | AY18: =SUM(-AR18+AS18*0.01+AT18*0.5+AU18) | AZ18: ='0分'!AF15 | BA18: =SUM(AY18,AX18,AW18) | BC18: {=SUMPRODUCT(--(NOT(ISBLANK('0₦'!D18:M18))), '0₦'!D$2:M$2) + SUMPRODUCT(--(NOT(ISBLANK('0₦'!Q18:T18))), '0₦'!Q$2:T$2)} | BD18: {=SUMPRODUCT(--(NOT(ISBLANK('0₦'!N18:P18))),'0₦'!N$2:P$2)+'0₦'!AY18} | BE18: {=SUMPRODUCT(--(NOT(ISBLANK('0₦'!AA18:AC18))),'0₦'!AA$2:AC$2) + BF18} | BG18: {=SUMPRODUCT(--(NOT(ISBLANK('0₦'!U18:Z18))), '0₦'!U$2:Z$2)} | BI18: =SUM(BG18:BH18)
A19: =A12+0.1 | B19: S | C19: =C18+1 | D19: 524 | E19: 2 | F19: 3 | G19: 15 | H19: 1 | I19: 1 | J19: 1 | K19: 3 | L19: 15 | M19: 2 | N19: 10 | O19: 5 | P19: 30 | Q19: 4 | R19: 1 | S19: 8 | T19: 2 | U19: 5 | V19: 1 | W19: 5 | Y19: 1 | Z19: 1 | AA19: 1 | AB19: 13 | AC19: 1 | AD19: 15 | AE19: 1 | AF19: 808 | AH19: 0 | AI19: =48+5 + 38 + 5 + 63 + 43 + 10 | AJ19: 200 | AK19: 30 | AL19: 1 | AM19: 65 | AN19: 0 | AO19: 0 | AP19: 0 | AR19: -1 | AS19: 0 | AT19: 0 | AU19: 24 | AW19: =SUM(AH19:AI19,AJ19/2,AK19:AL19) | AX19: =AM19*0.5+SUM(AN19:AP19) | AY19: =SUM(-AR19+AS19*0.01+AT19*0.5+AU19) | AZ19: ='0分'!AF16 | BA19: =SUM(AY19,AX19,AW19) | BC19: {=SUMPRODUCT(--(NOT(ISBLANK('0₦'!D19:M19))), '0₦'!D$2:M$2) + SUMPRODUCT(--(NOT(ISBLANK('0₦'!Q19:T19))), '0₦'!Q$2:T$2)} | BD19: {=SUMPRODUCT(--(NOT(ISBLANK('0₦'!N19:P19))),'0₦'!N$2:P$2)+'0₦'!AY19} | BE19: {=SUMPRODUCT(--(NOT(ISBLANK('0₦'!AA19:AC19))),'0₦'!AA$2:AC$2) + BF19} | BG19: {=SUMPRODUCT(--(NOT(ISBLANK('0₦'!U19:Z19))), '0₦'!U$2:Z$2)} | BI19: =SUM(BG19:BH19)
B20: M | C20: =C19+1 | D20: 566 | E20: 2 | F20: 15 | G20: 30 | H20: 1 | I20: 1 | J20: 1 | K20: 3 | L20: 15 | M20: 2 | N20: 12 | O20: 5 | P20: 30 | Q20: 4 | R20: 1 | S20: 10 | T20: 5 | V20: 2 | W20: 10 | Y20: 5 | Z20: 1 | AA20: 1 | AB20: 9 | AC20: 1 | AD20: 10 | AE20: 1 | AF20: 3000 | AH20: 1 | AI20: =78+8+10 | AJ20: 200 | AK20: 120 | AL20: 1 | AM20: 79 | AN20: 20 | AO20: 0 | AP20: 14 | AR20: -1 | AS20: 90 | AT20: 0 | AU20: =N20 | AW20: =SUM(AH20:AI20,AJ20/2,AK20:AL20) | AX20: =AM20*0.5+SUM(AN20:AP20) | AY20: =SUM(-AR20+AS20*0.01+AT20*0.5+AU20) | AZ20: ='0分'!AF17 | BA20: =SUM(AY20,AX20,AW20) | BC20: {=SUMPRODUCT(--(NOT(ISBLANK('0₦'!D20:M20))), '0₦'!D$2:M$2) + SUMPRODUCT(--(NOT(ISBLANK('0₦'!Q20:T20))), '0₦'!Q$2:T$2)} | BD20: {=SUMPRODUCT(--(NOT(ISBLANK('0₦'!N20:P20))),'0₦'!N$2:P$2)+'0₦'!AY20} | BE20: {=SUMPRODUCT(--(NOT(ISBLANK('0₦'!AA20:AC20))),'0₦'!AA$2:AC$2) + BF20} | BG20: {=SUMPRODUCT(--(NOT(ISBLANK('0₦'!U20:Z20))), '0₦'!U$2:Z$2)} | BI20: =SUM(BG20:BH20)
B21: T | C21: =C20+1 | D21: 555 | E21: 1 | F21: 10 | H21: 1 | I21: 1 | J21: 1 | K21: 4 | L21: 15 | M21: 1 | N21: 11 | O21: 6 | P21: 90 | Q21: 5 | R21: 1 | S21: 4 | T21: 4 | U21: 5 | V21: 3 | W21: 10 | X21: 8 | Y21: 5 | Z21: 1 | AA21: 1 | AB21: 9 | AC21: 1 | AD21: 8 | AE21: 1 | AF21: 955 | AG21: 1014 | AH21: 2 | AI21: =24+31+10 | AJ21: 0 | AK21: =32+27 | AL21: 1 | AM21: 78 | AN21: 42 | AO21: 18 | AP21: 18 | AR21: -1 | AS21: 20 | AT21: 18 | AU21: =N21+O21 + 10 + 21 + 25 | AW21: =SUM(AH21:AI21,AJ21/2,AK21:AL21) | AX21: =AM21*0.5+SUM(AN21:AP21) | AY21: =SUM(-AR21+AS21*0.01+AT21*0.5+AU21) | AZ21: ='0分'!AF18 | BA21: =SUM(AY21,AX21,AW21) | BC21: {=SUMPRODUCT(--(NOT(ISBLANK('0₦'!D21:M21))), '0₦'!D$2:M$2) + SUMPRODUCT(--(NOT(ISBLANK('0₦'!Q21:T21))), '0₦'!Q$2:T$2)} | BD21: {=SUMPRODUCT(--(NOT(ISBLANK('0₦'!N21:P21))),'0₦'!N$2:P$2)+'0₦'!AY21} | BE21: {=SUMPRODUCT(--(NOT(ISBLANK('0₦'!AA21:AC21))),'0₦'!AA$2:AC$2) + BF21} | BG21: {=SUMPRODUCT(--(NOT(ISBLANK('0₦'!U21:Z21))), '0₦'!U$2:Z$2)} | BI21: =SUM(BG21:BH21)
B22: W | C22: =C21+1 | D22: 496 | E22: 0 | F22: 10 | G22: 15 | H22: 1 | I22: 1 | J22: 1 | K22: 4 | L22: 25 | M22: 2 | N22: 11 | P22: 20 | Q22: 4 | R22: 1 | S22: 5 | T22: 4 | U22: 7 | V22: 5 | W22: 10 | Y22: 10 | Z22: 1 | AA22: 5 | AB22: 15 | AC22: 1 | AD22: 20 | AE22: 1 | AF22: 826 | AG22: 2115 | AH22: 1 | AI22: 0 | AJ22: 0 | AK22: =15 | AL22: 1 | AM22: 25 | AN22: 0 | AO22: =15+15 | AP22: 0 | AR22: 1 | AS22: 0 | AT22: 20 | AU22: =N22+O22 + 0 | AW22: =SUM(AH22:AI22,AJ22/2,AK22:AL22) | AX22: =AM22*0.5+SUM(AN22:AP22) | AY22: =SUM(-AR22+AS22*0.01+AT22*0.5+AU22) | AZ22: ='0分'!AF19 | BA22: =SUM(AY22,AX22,AW22) | BC22: {=SUMPRODUCT(--(NOT(ISBLANK('0₦'!D22:M22))), '0₦'!D$2:M$2) + SUMPRODUCT(--(NOT(ISBLANK('0₦'!Q22:T22))), '0₦'!Q$2:T$2)} | BD22: {=SUMPRODUCT(--(NOT(ISBLANK('0₦'!N22:P22))),'0₦'!N$2:P$2)+'0₦'!AY22} | BE22: {=SUMPRODUCT(--(NOT(ISBLANK('0₦'!AA22:AC22))),'0₦'!AA$2:AC$2) + BF22} | BG22: {=SUMPRODUCT(--(NOT(ISBLANK('0₦'!U22:Z22))), '0₦'!U$2:Z$2)} | BI22: =SUM(BG22:BH22)
B23: Th | C23: =C22+1 | D23: 540 | E23: 0 | F23: 10 | G23: 15 | H23: 1 | I23: 1 | J23: 1 | K23: 3 | L23: 15 | M23: 2 | N23: 11 | P23: 5 | Q23: 2 | R23: 1 | S23: 3 | T23: 4 | U23: 6 | V23: 8 | W23: 10 | X23: 0 | Y23: 10 | Z23: 1 | AA23: 1 | AB23: 25 | AC23: 1 | AD23: 7 | AE23: 18 | AF23: 749 | AH23: 0 | AI23: 0 | AJ23: 0 | AK23: =18 + 29 | AL23: 1 | AM23: 63 | AN23: 50 | AO23: =15+31+22 | AP23: 0 | AR23: -1 | AS23: 0 | AT23: 0 | AU23: =N23+O23 + 0 | AW23: =SUM(AH23:AI23,AJ23/2,AK23:AL23) | AX23: =AM23*0.5+SUM(AN23:AP23) | AY23: =SUM(-AR23+AS23*0.01+AT23*0.5+AU23) | AZ23: ='0分'!AF20 | BA23: =SUM(AY23,AX23,AW23) | BC23: {=SUMPRODUCT(--(NOT(ISBLANK('0₦'!D23:M23))), '0₦'!D$2:M$2) + SUMPRODUCT(--(NOT(ISBLANK('0₦'!Q23:T23))), '0₦'!Q$2:T$2)} | BD23: {=SUMPRODUCT(--(NOT(ISBLANK('0₦'!N23:P23))),'0₦'!N$2:P$2)+'0₦'!AY23} | BE23: {=SUMPRODUCT(--(NOT(ISBLANK('0₦'!AA23:AC23))),'0₦'!AA$2:AC$2) + BF23} | BG23: {=SUMPRODUCT(--(NOT(ISBLANK('0₦'!U23:Z23))), '0₦'!U$2:Z$2)} | BI23: =SUM(BG23:BH23)
B24: F | C24: =C23+1 | D24: 471 | E24: 0 | F24: 15 | G24: 15 | H24: 1 | I24: 1 | J24: 1 | K24: 7 | M24: 2 | N24: 11 | P24: 15 | Q24: 2 | R24: 1 | S24: 5 | T24: 4 | U24: 4 | V24: 4 | W24: 10 | Y24: 15 | Z24: 1 | AA24: 1 | AB24: 2 | AC24: 1 | AD24: 10 | AE24: 25 | AF24: 735 | AG24: 1138 | AH24: 1 | AI24: =120+20 | AJ24: 20 | AK24: =25+15 | AL24: 1 | AM24: 51 | AN24: 24 | AO24: 31 | AP24: 0 | AR24: -1 | AS24: 0 | AT24: 85 | AU24: =N24+O24 + 23 | AW24: =SUM(AH24:AI24,AJ24/2,AK24:AL24) | AX24: =AM24*0.5+SUM(AN24:AP24) | AY24: =SUM(-AR24+AS24*0.01+AT24*0.5+AU24) | AZ24: ='0分'!AF21 | BA24: =SUM(AY24,AX24,AW24) | BC24: {=SUMPRODUCT(--(NOT(ISBLANK('0₦'!D24:M24))), '0₦'!D$2:M$2) + SUMPRODUCT(--(NOT(ISBLANK('0₦'!Q24:T24))), '0₦'!Q$2:T$2)} | BD24: {=SUMPRODUCT(--(NOT(ISBLANK('0₦'!N24:P24))),'0₦'!N$2:P$2)+'0₦'!AY24} | BE24: {=SUMPRODUCT(--(NOT(ISBLANK('0₦'!AA24:AC24))),'0₦'!AA$2:AC$2) + BF24} | BG24: {=SUMPRODUCT(--(NOT(ISBLANK('0₦'!U24:Z24))), '0₦'!U$2:Z$2)} | BI24: =SUM(BG24:BH24)
B25: S | C25: =C24+1 | D25: 522 | E25: 0 | F25: 15 | G25: 15 | H25: 1 | I25: 1 | J25: 1 | M25: 3 | N25: 12 | P25: 2 | R25: 1 | AH25: 0 | AM25: 4 | AN25: 0 | AO25: 0 | AP25: 0 | AR25: -1 | AT25: 2 | AU25: =N25+O25 + 0 | AW25: =SUM(AH25:AI25,AJ25/2,AK25:AL25) | AX25: =AM25*0.5+SUM(AN25:AP25) | AY25: =SUM(-AR25+AS25*0.01+AT25*0.5+AU25) | AZ25: ='0分'!AF22 | BA25: =SUM(AY25,AX25,AW25) | BC25: {=SUMPRODUCT(--(NOT(ISBLANK('0₦'!D25:M25))), '0₦'!D$2:M$2) + SUMPRODUCT(--(NOT(ISBLANK('0₦'!Q25:T25))), '0₦'!Q$2:T$2)} | BD25: {=SUMPRODUCT(--(NOT(ISBLANK('0₦'!N25:P25))),'0₦'!N$2:P$2)+'0₦'!AY25} | BE25: {=SUMPRODUCT(--(NOT(ISBLANK('0₦'!AA25:AC25))),'0₦'!AA$2:AC$2) + BF25} | BG25: {=SUMPRODUCT(--(NOT(ISBLANK('0₦'!U25:Z25))), '0₦'!U$2:Z$2)} | BI25: =SUM(BG25:BH25)
A26: =A19+0.1 | B26: S | C26: =C25+1 | AR26: 40 | AU26: =N26+O26 + 0 | AW26: =SUM(AH26:AI26,AJ26/2,AK26:AL26) | AX26: =AM26*0.5+SUM(AN26:AP26) | AY26: =SUM(-AR26+AS26*0.01+AT26*0.5+AU26) | AZ26: ='0分'!AF23 | BA26: =SUM(AY26,AX26,AW26) | BC26: {=SUMPRODUCT(--(NOT(ISBLANK('0₦'!D26:M26))), '0₦'!D$2:M$2) + SUMPRODUCT(--(NOT(ISBLANK('0₦'!Q26:T26))), '0₦'!Q$2:T$2)} | BD26: {=SUMPRODUCT(--(NOT(ISBLANK('0₦'!N26:P26))),'0₦'!N$2:P$2)+'0₦'!AY26} | BE26: {=SUMPRODUCT(--(NOT(ISBLANK('0₦'!AA26:AC26))),'0₦'!AA$2:AC$2) + BF26} | BG26: {=SUMPRODUCT(--(NOT(ISBLANK('0₦'!U26:Z26))), '0₦'!U$2:Z$2)} | BI26: =SUM(BG26:BH26)
B27: M | C27: =C26+1 | AR27: 40 | AU27: =N27+O27 + 0 | AW27: =SUM(AH27:AI27,AJ27/2,AK27:AL27) | AX27: =AM27*0.5+SUM(AN27:AP27) | AY27: =SUM(-AR27+AS27*0.01+AT27*0.5+AU27) | AZ27: ='0分'!AF24 | BA27: =SUM(AY27,AX27,AW27) | BC27: {=SUMPRODUCT(--(NOT(ISBLANK('0₦'!D27:M27))), '0₦'!D$2:M$2) + SUMPRODUCT(--(NOT(ISBLANK('0₦'!Q27:T27))), '0₦'!Q$2:T$2)} | BD27: {=SUMPRODUCT(--(NOT(ISBLANK('0₦'!N27:P27))),'0₦'!N$2:P$2)+'0₦'!AY27} | BE27: {=SUMPRODUCT(--(NOT(ISBLANK('0₦'!AA27:AC27))),'0₦'!AA$2:AC$2) + BF27} | BG27: {=SUMPRODUCT(--(NOT(ISBLANK('0₦'!U27:Z27))), '0₦'!U$2:Z$2)} | BI27: =SUM(BG27:BH27)
B28: T | C28: =C27+1 | AR28: 40 | AU28: =N28+O28 + 0 | AW28: =SUM(AH28:AI28,AJ28/2,AK28:AL28) | AX28: =AM28*0.5+SUM(AN28:AP28) | AY28: =SUM(-AR28+AS28*0.01+AT28*0.5+AU28) | AZ28: ='0分'!AF25 | BA28: =SUM(AY28,AX28,AW28) | BC28: {=SUMPRODUCT(--(NOT(ISBLANK('0₦'!D28:M28))), '0₦'!D$2:M$2) + SUMPRODUCT(--(NOT(ISBLANK('0₦'!Q28:T28))), '0₦'!Q$2:T$2)} | BD28: {=SUMPRODUCT(--(NOT(ISBLANK('0₦'!N28:P28))),'0₦'!N$2:P$2)+'0₦'!AY28} | BE28: {=SUMPRODUCT(--(NOT(ISBLANK('0₦'!AA28:AC28))),'0₦'!AA$2:AC$2) + BF28} | BG28: {=SUMPRODUCT(--(NOT(ISBLANK('0₦'!U28:Z28))), '0₦'!U$2:Z$2)} | BI28: =SUM(BG28:BH28)
B29: W | C29: =C28+1 | AR29: 40 | AU29: =N29+O29 + 0 | AW29: =SUM(AH29:AI29,AJ29/2,AK29:AL29) | AX29: =AM29*0.5+SUM(AN29:AP29) | AY29: =SUM(-AR29+AS29*0.01+AT29*0.5+AU29) | AZ29: ='0分'!AF26 | BA29: =SUM(AY29,AX29,AW29) | BC29: {=SUMPRODUCT(--(NOT(ISBLANK('0₦'!D29:M29))), '0₦'!D$2:M$2) + SUMPRODUCT(--(NOT(ISBLANK('0₦'!Q29:T29))), '0₦'!Q$2:T$2)} | BD29: {=SUMPRODUCT(--(NOT(ISBLANK('0₦'!N29:P29))),'0₦'!N$2:P$2)+'0₦'!AY29} | BE29: {=SUMPRODUCT(--(NOT(ISBLANK('0₦'!AA29:AC29))),'0₦'!AA$2:AC$2) + BF29} | BG29: {=SUMPRODUCT(--(NOT(ISBLANK('0₦'!U29:Z29))), '0₦'!U$2:Z$2)} | BI29: =SUM(BG29:BH29)
B30: Th | C30: =C29+1 | AR30: 40 | AU30: =N30+O30 + 0 | AW30: =SUM(AH30:AI30,AJ30/2,AK30:AL30) | AX30: =AM30*0.5+SUM(AN30:AP30) | AY30: =SUM(-AR30+AS30*0.01+AT30*0.5+AU30) | AZ30: ='0分'!AF27 | BA30: =SUM(AY30,AX30,AW30) | BC30: {=SUMPRODUCT(--(NOT(ISBLANK('0₦'!D30:M30))), '0₦'!D$2:M$2) + SUMPRODUCT(--(NOT(ISBLANK('0₦'!Q30:T30))), '0₦'!Q$2:T$2)} | BD30: {=SUMPRODUCT(--(NOT(ISBLANK('0₦'!N30:P30))),'0₦'!N$2:P$2)+'0₦'!AY30} | BE30: {=SUMPRODUCT(--(NOT(ISBLANK('0₦'!AA30:AC30))),'0₦'!AA$2:AC$2) + BF30} | BG30: {=SUMPRODUCT(--(NOT(ISBLANK('0₦'!U30:Z30))), '0₦'!U$2:Z$2)} | BI30: =SUM(BG30:BH30)
B31: F | C31: =C30+1 | AR31: 40 | AU31: =N31+O31 + 0 | AW31: =SUM(AH31:AI31,AJ31/2,AK31:AL31) | AX31: =AM31*0.5+SUM(AN31:AP31) | AY31: =SUM(-AR31+AS31*0.01+AT31*0.5+AU31) | AZ31: ='0分'!AF28 | BA31: =SUM(AY31,AX31,AW31) | BC31: {=SUMPRODUCT(--(NOT(ISBLANK('0₦'!D31:M31))), '0₦'!D$2:M$2) + SUMPRODUCT(--(NOT(ISBLANK('0₦'!Q31:T31))), '0₦'!Q$2:T$2)} | BD31: {=SUMPRODUCT(--(NOT(ISBLANK('0₦'!N31:P31))),'0₦'!N$2:P$2)+'0₦'!AY31} | BE31: {=SUMPRODUCT(--(NOT(ISBLANK('0₦'!AA31:AC31))),'0₦'!AA$2:AC$2) + BF31} | BG31: {=SUMPRODUCT(--(NOT(ISBLANK('0₦'!U31:Z31))), '0₦'!U$2:Z$2)} | BI31: =SUM(BG31:BH31)
B32: S | C32: =C31+1 | AR32: 40 | AU32: =N32+O32 + 0 | AW32: =SUM(AH32:AI32,AJ32/2,AK32:AL32) | AX32: =AM32*0.5+SUM(AN32:AP32) | AY32: =SUM(-AR32+AS32*0.01+AT32*0.5+AU32) | AZ32: ='0分'!AF29 | BA32: =SUM(AY32,AX32,AW32) | BC32: {=SUMPRODUCT(--(NOT(ISBLANK('0₦'!D32:M32))), '0₦'!D$2:M$2) + SUMPRODUCT(--(NOT(ISBLANK('0₦'!Q32:T32))), '0₦'!Q$2:T$2)} | BD32: {=SUMPRODUCT(--(NOT(ISBLANK('0₦'!N32:P32))),'0₦'!N$2:P$2)+'0₦'!AY32} | BE32: {=SUMPRODUCT(--(NOT(ISBLANK('0₦'!AA32:AC32))),'0₦'!AA$2:AC$2) + BF32} | BG32: {=SUMPRODUCT(--(NOT(ISBLANK('0₦'!U32:Z32))), '0₦'!U$2:Z$2)} | BI32: =SUM(BG32:BH32)
A33: =A5+1 | B33: S | C33: =C32+1 | AR33: 40 | AU33: =N33+O33 + 0 | AW33: =SUM(AH33:AI33,AJ33/2,AK33:AL33) | AX33: =AM33*0.5+SUM(AN33:AP33) | AY33: =SUM(-AR33+AS33*0.01+AT33*0.5+AU33) | AZ33: ='0分'!AF30 | BA33: =SUM(AY33,AX33,AW33) | BC33: {=SUMPRODUCT(--(NOT(ISBLANK('0₦'!D33:M33))), '0₦'!D$2:M$2) + SUMPRODUCT(--(NOT(ISBLANK('0₦'!Q33:T33))), '0₦'!Q$2:T$2)} | BD33: {=SUMPRODUCT(--(NOT(ISBLANK('0₦'!N33:P33))),'0₦'!N$2:P$2)+'0₦'!AY33} | BE33: {=SUMPRODUCT(--(NOT(ISBLANK('0₦'!AA33:AC33))),'0₦'!AA$2:AC$2) + BF33} | BG33: {=SUMPRODUCT(--(NOT(ISBLANK('0₦'!U33:Z33))), '0₦'!U$2:Z$2)} | BI33: =SUM(BG33:BH33)
B34: M | C34: =C33+1 | AR34: 40 | AU34: =N34+O34 + 0 | AW34: =SUM(AH34:AI34,AJ34/2,AK34:AL34) | AX34: =AM34*0.5+SUM(AN34:AP34) | AY34: =SUM(-AR34+AS34*0.01+AT34*0.5+AU34) | AZ34: ='0分'!AF31 | BA34: =SUM(AY34,AX34,AW34) | BC34: {=SUMPRODUCT(--(NOT(ISBLANK('0₦'!D34:M34))), '0₦'!D$2:M$2) + SUMPRODUCT(--(NOT(ISBLANK('0₦'!Q34:T34))), '0₦'!Q$2:T$2)} | BD34: {=SUMPRODUCT(--(NOT(ISBLANK('0₦'!N34:P34))),'0₦'!N$2:P$2)+'0₦'!AY34} | BE34: {=SUMPRODUCT(--(NOT(ISBLANK('0₦'!AA34:AC34))),'0₦'!AA$2:AC$2) + BF34} | BG34: {=SUMPRODUCT(--(NOT(ISBLANK('0₦'!U34:Z34))), '0₦'!U$2:Z$2)} | BI34: =SUM(BG34:BH34)
B35: T | C35: =C34+1 | AR35: 40 | AU35: =N35+O35 + 0 | AW35: =SUM(AH35:AI35,AJ35/2,AK35:AL35) | AX35: =AM35*0.5+SUM(AN35:AP35) | AY35: =SUM(-AR35+AS35*0.01+AT35*0.5+AU35) | AZ35: ='0分'!AF32 | BA35: =SUM(AY35,AX35,AW35) | BC35: {=SUMPRODUCT(--(NOT(ISBLANK('0₦'!D35:M35))), '0₦'!D$2:M$2) + SUMPRODUCT(--(NOT(ISBLANK('0₦'!Q35:T35))), '0₦'!Q$2:T$2)} | BD35: {=SUMPRODUCT(--(NOT(ISBLANK('0₦'!N35:P35))),'0₦'!N$2:P$2)+'0₦'!AY35} | BE35: {=SUMPRODUCT(--(NOT(ISBLANK('0₦'!AA35:AC35))),'0₦'!AA$2:AC$2) + BF35} | BG35: {=SUMPRODUCT(--(NOT(ISBLANK('0₦'!U35:Z35))), '0₦'!U$2:Z$2)} | BI35: =SUM(BG35:BH35)
B36: W | C36: =C35+1 | AR36: 40 | AU36: =N36+O36 + 0 | AW36: =SUM(AH36:AI36,AJ36/2,AK36:AL36) | AX36: =AM36*0.5+SUM(AN36:AP36) | AY36: =SUM(-AR36+AS36*0.01+AT36*0.5+AU36) | AZ36: ='0分'!AF33 | BA36: =SUM(AY36,AX36,AW36) | BC36: {=SUMPRODUCT(--(NOT(ISBLANK('0₦'!D36:M36))), '0₦'!D$2:M$2) + SUMPRODUCT(--(NOT(ISBLANK('0₦'!Q36:T36))), '0₦'!Q$2:T$2)} | BD36: {=SUMPRODUCT(--(NOT(ISBLANK('0₦'!N36:P36))),'0₦'!N$2:P$2)+'0₦'!AY36} | BE36: {=SUMPRODUCT(--(NOT(ISBLANK('0₦'!AA36:AC36))),'0₦'!AA$2:AC$2) + BF36} | BG36: {=SUMPRODUCT(--(NOT(ISBLANK('0₦'!U36:Z36))), '0₦'!U$2:Z$2)} | BI36: =SUM(BG36:BH36)
B37: Th | C37: =C36+1 | AR37: 40 | AU37: =N37+O37 + 0 | AW37: =SUM(AH37:AI37,AJ37/2,AK37:AL37) | AX37: =AM37*0.5+SUM(AN37:AP37) | AY37: =SUM(-AR37+AS37*0.01+AT37*0.5+AU37) | AZ37: ='0分'!AF34 | BA37: =SUM(AY37,AX37,AW37) | BC37: {=SUMPRODUCT(--(NOT(ISBLANK('0₦'!D37:M37))), '0₦'!D$2:M$2) + SUMPRODUCT(--(NOT(ISBLANK('0₦'!Q37:T37))), '0₦'!Q$2:T$2)} | BD37: {=SUMPRODUCT(--(NOT(ISBLANK('0₦'!N37:P37))),'0₦'!N$2:P$2)+'0₦'!AY37} | BE37: {=SUMPRODUCT(--(NOT(ISBLANK('0₦'!AA37:AC37))),'0₦'!AA$2:AC$2) + BF37} | BG37: {=SUMPRODUCT(--(NOT(ISBLANK('0₦'!U37:Z37))), '0₦'!U$2:Z$2)} | BI37: =SUM(BG37:BH37)
B38: F | C38: =C37+1 | AR38: 40 | AU38: =N38+O38 + 0 | AW38: =SUM(AH38:AI38,AJ38/2,AK38:AL38) | AX38: =AM38*0.5+SUM(AN38:AP38) | AY38: =SUM(-AR38+AS38*0.01+AT38*0.5+AU38) | AZ38: ='0分'!AF35 | BA38: =SUM(AY38,AX38,AW38) | BC38: {=SUMPRODUCT(--(NOT(ISBLANK('0₦'!D38:M38))), '0₦'!D$2:M$2) + SUMPRODUCT(--(NOT(ISBLANK('0₦'!Q38:T38))), '0₦'!Q$2:T$2)} | BD38: {=SUMPRODUCT(--(NOT(ISBLANK('0₦'!N38:P38))),'0₦'!N$2:P$2)+'0₦'!AY38} | BE38: {=SUMPRODUCT(--(NOT(ISBLANK('0₦'!AA38:AC38))),'0₦'!AA$2:AC$2) + BF38} | BG38: {=SUMPRODUCT(--(NOT(ISBLANK('0₦'!U38:Z38))), '0₦'!U$2:Z$2)} | BI38: =SUM(BG38:BH38)
B39: S | C39: =C38+1 | AR39: 40 | AU39: =N39+O39 + 0 | AW39: =SUM(AH39:AI39,AJ39/2,AK39:AL39) | AX39: =AM39*0.5+SUM(AN39:AP39) | AY39: =SUM(-AR39+AS39*0.01+AT39*0.5+AU39) | AZ39: ='0分'!AF36 | BA39: =SUM(AY39,AX39,AW39) | BC39: {=SUMPRODUCT(--(NOT(ISBLANK('0₦'!D39:M39))), '0₦'!D$2:M$2) + SUMPRODUCT(--(NOT(ISBLANK('0₦'!Q39:T39))), '0₦'!Q$2:T$2)} | BD39: {=SUMPRODUCT(--(NOT(ISBLANK('0₦'!N39:P39))),'0₦'!N$2:P$2)+'0₦'!AY39} | BE39: {=SUMPRODUCT(--(NOT(ISBLANK('0₦'!AA39:AC39))),'0₦'!AA$2:AC$2) + BF39} | BG39: {=SUMPRODUCT(--(NOT(ISBLANK('0₦'!U39:Z39))), '0₦'!U$2:Z$2)} | BI39: =SUM(BG39:BH39)
A40: =A33+0.1 | B40: S | C40: =C39+1 | AR40: 40 | AU40: =N40+O40 + 0 | AW40: =SUM(AH40:AI40,AJ40/2,AK40:AL40) | AX40: =AM40*0.5+SUM(AN40:AP40) | AY40: =SUM(-AR40+AS40*0.01+AT40*0.5+AU40) | AZ40: ='0分'!AF37 | BA40: =SUM(AY40,AX40,AW40) | BC40: {=SUMPRODUCT(--(NOT(ISBLANK('0₦'!D40:M40))), '0₦'!D$2:M$2) + SUMPRODUCT(--(NOT(ISBLANK('0₦'!Q40:T40))), '0₦'!Q$2:T$2)} | BD40: {=SUMPRODUCT(--(NOT(ISBLANK('0₦'!N40:P40))),'0₦'!N$2:P$2)+'0₦'!AY40} | BE40: {=SUMPRODUCT(--(NOT(ISBLANK('0₦'!AA40:AC40))),'0₦'!AA$2:AC$2) + BF40} | BG40: {=SUMPRODUCT(--(NOT(ISBLANK('0₦'!U40:Z40))), '0₦'!U$2:Z$2)} | BI40: =SUM(BG40:BH40)
B41: M | C41: =C40+1 | AM41: =1+1+1 | AR41: 40 | AU41: =N41+O41 + 0 | AW41: =SUM(AH41:AI41,AJ41/2,AK41:AL41) | AX41: =AM41*0.5+SUM(AN41:AP41) | AY41: =SUM(-AR41+AS41*0.01+AT41*0.5+AU41) | AZ41: ='0分'!AF38 | BA41: =SUM(AY41,AX41,AW41) | BC41: {=SUMPRODUCT(--(NOT(ISBLANK('0₦'!D41:M41))), '0₦'!D$2:M$2) + SUMPRODUCT(--(NOT(ISBLANK('0₦'!Q41:T41))), '0₦'!Q$2:T$2)} | BD41: {=SUMPRODUCT(--(NOT(ISBLANK('0₦'!N41:P41))),'0₦'!N$2:P$2)+'0₦'!AY41} | BE41: {=SUMPRODUCT(--(NOT(ISBLANK('0₦'!AA41:AC41))),'0₦'!AA$2:AC$2) + BF41} | BG41: {=SUMPRODUCT(--(NOT(ISBLANK('0₦'!U41:Z41))), '0₦'!U$2:Z$2)} | BI41: =SUM(BG41:BH41)
B42: T | C42: =C41+1 | AR42: 40 | AU42: =N42+O42 + 0 | AW42: =SUM(AH42:AI42,AJ42/2,AK42:AL42) | AX42: =AM42*0.5+SUM(AN42:AP42) | AY42: =SUM(-AR42+AS42*0.01+AT42*0.5+AU42) | AZ42: ='0分'!AF39 | BA42: =SUM(AY42,AX42,AW42) | BC42: {=SUMPRODUCT(--(NOT(ISBLANK('0₦'!D42:M42))), '0₦'!D$2:M$2) + SUMPRODUCT(--(NOT(ISBLANK('0₦'!Q42:T42))), '0₦'!Q$2:T$2)} | BD42: {=SUMPRODUCT(--(NOT(ISBLANK('0₦'!N42:P42))),'0₦'!N$2:P$2)+'0₦'!AY42} | BE42: {=SUMPRODUCT(--(NOT(ISBLANK('0₦'!AA42:AC42))),'0₦'!AA$2:AC$2) + BF42} | BG42: {=SUMPRODUCT(--(NOT(ISBLANK('0₦'!U42:Z42))), '0₦'!U$2:Z$2)} | BI42: =SUM(BG42:BH42)
B43: W | C43: =C42+1 | AR43: 40 | AU43: =N43+O43 + 0 | AW43: =SUM(AH43:AI43,AJ43/2,AK43:AL43) | AX43: =AM43*0.5+SUM(AN43:AP43) | AY43: =SUM(-AR43+AS43*0.01+AT43*0.5+AU43) | AZ43: ='0分'!AF40 | BA43: =SUM(AY43,AX43,AW43) | BC43: {=SUMPRODUCT(--(NOT(ISBLANK('0₦'!D43:M43))), '0₦'!D$2:M$2) + SUMPRODUCT(--(NOT(ISBLANK('0₦'!Q43:T43))), '0₦'!Q$2:T$2)} | BD43: {=SUMPRODUCT(--(NOT(ISBLANK('0₦'!N43:P43))),'0₦'!N$2:P$2)+'0₦'!AY43} | BE43: {=SUMPRODUCT(--(NOT(ISBLANK('0₦'!AA43:AC43))),'0₦'!AA$2:AC$2) + BF43} | BG43: {=SUMPRODUCT(--(NOT(ISBLANK('0₦'!U43:Z43))), '0₦'!U$2:Z$2)} | BI43: =SUM(BG43:BH43)
B44: Th | C44: =C43+1 | AR44: 40 | AU44: =N44+O44 + 0 | AW44: =SUM(AH44:AI44,AJ44/2,AK44:AL44) | AX44: =AM44*0.5+SUM(AN44:AP44) | AY44: =SUM(-AR44+AS44*0.01+AT44*0.5+AU44) | AZ44: ='0分'!AF41 | BA44: =SUM(AY44,AX44,AW44) | BC44: {=SUMPRODUCT(--(NOT(ISBLANK('0₦'!D44:M44))), '0₦'!D$2:M$2) + SUMPRODUCT(--(NOT(ISBLANK('0₦'!Q44:T44))), '0₦'!Q$2:T$2)} | BD44: {=SUMPRODUCT(--(NOT(ISBLANK('0₦'!N44:P44))),'0₦'!N$2:P$2)+'0₦'!AY44} | BE44: {=SUMPRODUCT(--(NOT(ISBLANK('0₦'!AA44:AC44))),'0₦'!AA$2:AC$2) + BF44} | BG44: {=SUMPRODUCT(--(NOT(ISBLANK('0₦'!U44:Z44))), '0₦'!U$2:Z$2)} | BI44: =SUM(BG44:BH44)
B45: F | C45: =C44+1 | AR45: 40 | AU45: =N45+O45 + 0 | AW45: =SUM(AH45:AI45,AJ45/2,AK45:AL45) | AX45: =AM45*0.5+SUM(AN45:AP45) | AY45: =SUM(-AR45+AS45*0.01+AT45*0.5+AU45) | AZ45: ='0分'!AF42 | BA45: =SUM(AY45,AX45,AW45) | BC45: {=SUMPRODUCT(--(NOT(ISBLANK('0₦'!D45:M45))), '0₦'!D$2:M$2) + SUMPRODUCT(--(NOT(ISBLANK('0₦'!Q45:T45))), '0₦'!Q$2:T$2)} | BD45: {=SUMPRODUCT(--(NOT(ISBLANK('0₦'!N45:P45))),'0₦'!N$2:P$2)+'0₦'!AY45} | BE45: {=SUMPRODUCT(--(NOT(ISBLANK('0₦'!AA45:AC45))),'0₦'!AA$2:AC$2) + BF45} | BG45: {=SUMPRODUCT(--(NOT(ISBLANK('0₦'!U45:Z45))), '0₦'!U$2:Z$2)} | BI45: =SUM(BG45:BH45)
B46: S | C46: =C45+1 | AR46: 40 | AU46: =N46+O46 + 0 | AW46: =SUM(AH46:AI46,AJ46/2,AK46:AL46) | AX46: =AM46*0.5+SUM(AN46:AP46) | AY46: =SUM(-AR46+AS46*0.01+AT46*0.5+AU46) | AZ46: ='0分'!AF43 | BA46: =SUM(AY46,AX46,AW46) | BC46: {=SUMPRODUCT(--(NOT(ISBLANK('0₦'!D46:M46))), '0₦'!D$2:M$2) + SUMPRODUCT(--(NOT(ISBLANK('0₦'!Q46:T46))), '0₦'!Q$2:T$2)} | BD46: {=SUMPRODUCT(--(NOT(ISBLANK('0₦'!N46:P46))),'0₦'!N$2:P$2)+'0₦'!AY46} | BE46: {=SUMPRODUCT(--(NOT(ISBLANK('0₦'!AA46:AC46))),'0₦'!AA$2:AC$2) + BF46} | BG46: {=SUMPRODUCT(--(NOT(ISBLANK('0₦'!U46:Z46))), '0₦'!U$2:Z$2)} | BI46: =SUM(BG46:BH46)
A47: =A40+0.1 | B47: S | C47: =C46+1 | AR47: 40 | AU47: =N47+O47 + 0 | AW47: =SUM(AH47:AI47,AJ47/2,AK47:AL47) | AX47: =AM47*0.5+SUM(AN47:AP47) | AY47: =SUM(-AR47+AS47*0.01+AT47*0.5+AU47) | AZ47: ='0分'!AF44 | BA47: =SUM(AY47,AX47,AW47) | BC47: {=SUMPRODUCT(--(NOT(ISBLANK('0₦'!D47:M47))), '0₦'!D$2:M$2) + SUMPRODUCT(--(NOT(ISBLANK('0₦'!Q47:T47))), '0₦'!Q$2:T$2)} | BD47: {=SUMPRODUCT(--(NOT(ISBLANK('0₦'!N47:P47))),'0₦'!N$2:P$2)+'0₦'!AY47} | BE47: {=SUMPRODUCT(--(NOT(ISBLANK('0₦'!AA47:AC47))),'0₦'!AA$2:AC$2) + BF47} | BG47: {=SUMPRODUCT(--(NOT(ISBLANK('0₦'!U47:Z47))), '0₦'!U$2:Z$2)} | BI47: =SUM(BG47:BH47)
B48: M | C48: =C47+1 | AR48: 40 | AU48: =N48+O48 + 0 | AW48: =SUM(AH48:AI48,AJ48/2,AK48:AL48) | AX48: =AM48*0.5+SUM(AN48:AP48) | AY48: =SUM(-AR48+AS48*0.01+AT48*0.5+AU48) | AZ48: ='0分'!AF45 | BA48: =SUM(AY48,AX48,AW48) | BC48: {=SUMPRODUCT(--(NOT(ISBLANK('0₦'!D48:M48))), '0₦'!D$2:M$2) + SUMPRODUCT(--(NOT(ISBLANK('0₦'!Q48:T48))), '0₦'!Q$2:T$2)} | BD48: {=SUMPRODUCT(--(NOT(ISBLANK('0₦'!N48:P48))),'0₦'!N$2:P$2)+'0₦'!AY48} | BE48: {=SUMPRODUCT(--(NOT(ISBLANK('0₦'!AA48:AC48))),'0₦'!AA$2:AC$2) + BF48} | BG48: {=SUMPRODUCT(--(NOT(ISBLANK('0₦'!U48:Z48))), '0₦'!U$2:Z$2)} | BI48: =SUM(BG48:BH48)
B49: T | C49: =C48+1 | AR49: 40 | AU49: =N49+O49 + 0 | AW49: =SUM(AH49:AI49,AJ49/2,AK49:AL49) | AX49: =AM49*0.5+SUM(AN49:AP49) | AY49: =SUM(-AR49+AS49*0.01+AT49*0.5+AU49) | AZ49: ='0分'!AF46 | BA49: =SUM(AY49,AX49,AW49) | BC49: {=SUMPRODUCT(--(NOT(ISBLANK('0₦'!D49:M49))), '0₦'!D$2:M$2) + SUMPRODUCT(--(NOT(ISBLANK('0₦'!Q49:T49))), '0₦'!Q$2:T$2)} | BD49: {=SUMPRODUCT(--(NOT(ISBLANK('0₦'!N49:P49))),'0₦'!N$2:P$2)+'0₦'!AY49} | BE49: {=SUMPRODUCT(--(NOT(ISBLANK('0₦'!AA49:AC49))),'0₦'!AA$2:AC$2) + BF49} | BG49: {=SUMPRODUCT(--(NOT(ISBLANK('0₦'!U49:Z49))), '0₦'!U$2:Z$2)} | BI49: =SUM(BG49:BH49)
B50: W | C50: =C49+1 | AR50: 40 | AU50: =N50+O50 + 0 | AW50: =SUM(AH50:AI50,AJ50/2,AK50:AL50) | AX50: =AM50*0.5+SUM(AN50:AP50) | AY50: =SUM(-AR50+AS50*0.01+AT50*0.5+AU50) | AZ50: ='0分'!AF47 | BA50: =SUM(AY50,AX50,AW50) | BC50: {=SUMPRODUCT(--(NOT(ISBLANK('0₦'!D50:M50))), '0₦'!D$2:M$2) + SUMPRODUCT(--(NOT(ISBLANK('0₦'!Q50:T50))), '0₦'!Q$2:T$2)} | BD50: {=SUMPRODUCT(--(NOT(ISBLANK('0₦'!N50:P50))),'0₦'!N$2:P$2)+'0₦'!AY50} | BE50: {=SUMPRODUCT(--(NOT(ISBLANK('0₦'!AA50:AC50))),'0₦'!AA$2:AC$2) + BF50} | BG50: {=SUMPRODUCT(--(NOT(ISBLANK('0₦'!U50:Z50))), '0₦'!U$2:Z$2)} | BI50: =SUM(BG50:BH50)
B51: Th | C51: =C50+1 | AR51: 40 | AU51: =N51+O51 + 0 | AW51: =SUM(AH51:AI51,AJ51/2,AK51:AL51) | AX51: =AM51*0.5+SUM(AN51:AP51) | AY51: =SUM(-AR51+AS51*0.01+AT51*0.5+AU51) | AZ51: ='0分'!AF48 | BA51: =SUM(AY51,AX51,AW51) | BC51: {=SUMPRODUCT(--(NOT(ISBLANK('0₦'!D51:M51))), '0₦'!D$2:M$2) + SUMPRODUCT(--(NOT(ISBLANK('0₦'!Q51:T51))), '0₦'!Q$2:T$2)} | BD51: {=SUMPRODUCT(--(NOT(ISBLANK('0₦'!N51:P51))),'0₦'!N$2:P$2)+'0₦'!AY51} | BE51: {=SUMPRODUCT(--(NOT(ISBLANK('0₦'!AA51:AC51))),'0₦'!AA$2:AC$2) + BF51} | BG51: {=SUMPRODUCT(--(NOT(ISBLANK('0₦'!U51:Z51))), '0₦'!U$2:Z$2)} | BI51: =SUM(BG51:BH51)
B52: F | C52: =C51+1 | AR52: 40 | AU52: =N52+O52 + 0 | AW52: =SUM(AH52:AI52,AJ52/2,AK52:AL52) | AX52: =AM52*0.5+SUM(AN52:AP52) | AY52: =SUM(-AR52+AS52*0.01+AT52*0.5+AU52) | AZ52: ='0分'!AF49 | BA52: =SUM(AY52,AX52,AW52) | BC52: {=SUMPRODUCT(--(NOT(ISBLANK('0₦'!D52:M52))), '0₦'!D$2:M$2) + SUMPRODUCT(--(NOT(ISBLANK('0₦'!Q52:T52))), '0₦'!Q$2:T$2)} | BD52: {=SUMPRODUCT(--(NOT(ISBLANK('0₦'!N52:P52))),'0₦'!N$2:P$2)+'0₦'!AY52} | BE52: {=SUMPRODUCT(--(NOT(ISBLANK('0₦'!AA52:AC52))),'0₦'!AA$2:AC$2) + BF52} | BG52: {=SUMPRODUCT(--(NOT(ISBLANK('0₦'!U52:Z52))), '0₦'!U$2:Z$2)} | BI52: =SUM(BG52:BH52)
B53: S | C53: =C52+1 | AR53: 40 | AU53: =N53+O53 + 0 | AW53: =SUM(AH53:AI53,AJ53/2,AK53:AL53) | AX53: =AM53*0.5+SUM(AN53:AP53) | AY53: =SUM(-AR53+AS53*0.01+AT53*0.5+AU53) | AZ53: ='0分'!AF50 | BA53: =SUM(AY53,AX53,AW53) | BC53: {=SUMPRODUCT(--(NOT(ISBLANK('0₦'!D53:M53))), '0₦'!D$2:M$2) + SUMPRODUCT(--(NOT(ISBLANK('0₦'!Q53:T53))), '0₦'!Q$2:T$2)} | BD53: {=SUMPRODUCT(--(NOT(ISBLANK('0₦'!N53:P53))),'0₦'!N$2:P$2)+'0₦'!AY53} | BE53: {=SUMPRODUCT(--(NOT(ISBLANK('0₦'!AA53:AC53))),'0₦'!AA$2:AC$2) + BF53} | BG53: {=SUMPRODUCT(--(NOT(ISBLANK('0₦'!U53:Z53))), '0₦'!U$2:Z$2)} | BI53: =SUM(BG53:BH53)
A54: =A47+0.1 | B54: S | C54: =C53+1 | AR54: 40 | AU54: =N54+O54 + 0 | AW54: =SUM(AH54:AI54,AJ54/2,AK54:AL54) | AX54: =AM54*0.5+SUM(AN54:AP54) | AY54: =SUM(-AR54+AS54*0.01+AT54*0.5+AU54) | AZ54: ='0分'!AF51 | BA54: =SUM(AY54,AX54,AW54) | BC54: {=SUMPRODUCT(--(NOT(ISBLANK('0₦'!D54:M54))), '0₦'!D$2:M$2) + SUMPRODUCT(--(NOT(ISBLANK('0₦'!Q54:T54))), '0₦'!Q$2:T$2)} | BD54: {=SUMPRODUCT(--(NOT(ISBLANK('0₦'!N54:P54))),'0₦'!N$2:P$2)+'0₦'!AY54} | BE54: {=SUMPRODUCT(--(NOT(ISBLANK('0₦'!AA54:AC54))),'0₦'!AA$2:AC$2) + BF54} | BG54: {=SUMPRODUCT(--(NOT(ISBLANK('0₦'!U54:Z54))), '0₦'!U$2:Z$2)} | BI54: =SUM(BG54:BH54)
B55: M | C55: =C54+1 | AR55: 40 | AU55: =N55+O55 + 0 | AW55: =SUM(AH55:AI55,AJ55/2,AK55:AL55) | AX55: =AM55*0.5+SUM(AN55:AP55) | AY55: =SUM(-AR55+AS55*0.01+AT55*0.5+AU55) | AZ55: ='0分'!AF52 | BA55: =SUM(AY55,AX55,AW55) | BC55: {=SUMPRODUCT(--(NOT(ISBLANK('0₦'!D55:M55))), '0₦'!D$2:M$2) + SUMPRODUCT(--(NOT(ISBLANK('0₦'!Q55:T55))), '0₦'!Q$2:T$2)} | BD55: {=SUMPRODUCT(--(NOT(ISBLANK('0₦'!N55:P55))),'0₦'!N$2:P$2)+'0₦'!AY55} | BE55: {=SUMPRODUCT(--(NOT(ISBLANK('0₦'!AA55:AC55))),'0₦'!AA$2:AC$2) + BF55} | BG55: {=SUMPRODUCT(--(NOT(ISBLANK('0₦'!U55:Z55))), '0₦'!U$2:Z$2)} | BI55: =SUM(BG55:BH55)
B56: T | C56: =C55+1 | AR56: 40 | AU56: =N56+O56 + 0 | AW56: =SUM(AH56:AI56,AJ56/2,AK56:AL56) | AX56: =AM56*0.5+SUM(AN56:AP56) | AY56: =SUM(-AR56+AS56*0.01+AT56*0.5+AU56) | AZ56: ='0分'!AF53 | BA56: =SUM(AY56,AX56,AW56) | BC56: {=SUMPRODUCT(--(NOT(ISBLANK('0₦'!D56:M56))), '0₦'!D$2:M$2) + SUMPRODUCT(--(NOT(ISBLANK('0₦'!Q56:T56))), '0₦'!Q$2:T$2)} | BD56: {=SUMPRODUCT(--(NOT(ISBLANK('0₦'!N56:P56))),'0₦'!N$2:P$2)+'0₦'!AY56} | BE56: {=SUMPRODUCT(--(NOT(ISBLANK('0₦'!AA56:AC56))),'0₦'!AA$2:AC$2) + BF56} | BG56: {=SUMPRODUCT(--(NOT(ISBLANK('0₦'!U56:Z56))), '0₦'!U$2:Z$2)} | BI56: =SUM(BG56:BH56)
B57: W | C57: =C56+1 | AR57: 40 | AU57: =N57+O57 + 0 | AW57: =SUM(AH57:AI57,AJ57/2,AK57:AL57) | AX57: =AM57*0.5+SUM(AN57:AP57) | AY57: =SUM(-AR57+AS57*0.01+AT57*0.5+AU57) | AZ57: ='0分'!AF54 | BA57: =SUM(AY57,AX57,AW57) | BC57: {=SUMPRODUCT(--(NOT(ISBLANK('0₦'!D57:M57))), '0₦'!D$2:M$2) + SUMPRODUCT(--(NOT(ISBLANK('0₦'!Q57:T57))), '0₦'!Q$2:T$2)} | BD57: {=SUMPRODUCT(--(NOT(ISBLANK('0₦'!N57:P57))),'0₦'!N$2:P$2)+'0₦'!AY57} | BE57: {=SUMPRODUCT(--(NOT(ISBLANK('0₦'!AA57:AC57))),'0₦'!AA$2:AC$2) + BF57} | BG57: {=SUMPRODUCT(--(NOT(ISBLANK('0₦'!U57:Z57))), '0₦'!U$2:Z$2)} | BI57: =SUM(BG57:BH57)
B58: Th | C58: =C57+1 | AR58: 40 | AU58: =N58+O58 + 0 | AW58: =SUM(AH58:AI58,AJ58/2,AK58:AL58) | AX58: =AM58*0.5+SUM(AN58:AP58) | AY58: =SUM(-AR58+AS58*0.01+AT58*0.5+AU58) | AZ58: ='0分'!AF55 | BA58: =SUM(AY58,AX58,AW58) | BC58: {=SUMPRODUCT(--(NOT(ISBLANK('0₦'!D58:M58))), '0₦'!D$2:M$2) + SUMPRODUCT(--(NOT(ISBLANK('0₦'!Q58:T58))), '0₦'!Q$2:T$2)} | BD58: {=SUMPRODUCT(--(NOT(ISBLANK('0₦'!N58:P58))),'0₦'!N$2:P$2)+'0₦'!AY58} | BE58: {=SUMPRODUCT(--(NOT(ISBLANK('0₦'!AA58:AC58))),'0₦'!AA$2:AC$2) + BF58} | BG58: {=SUMPRODUCT(--(NOT(ISBLANK('0₦'!U58:Z58))), '0₦'!U$2:Z$2)} | BI58: =SUM(BG58:BH58)
B59: F | C59: =C58+1 | AR59: 40 | AU59: =N59+O59 + 0 | AW59: =SUM(AH59:AI59,AJ59/2,AK59:AL59) | AX59: =AM59*0.5+SUM(AN59:AP59) | AY59: =SUM(-AR59+AS59*0.01+AT59*0.5+AU59) | AZ59: ='0分'!AF56 | BA59: =SUM(AY59,AX59,AW59) | BC59: {=SUMPRODUCT(--(NOT(ISBLANK('0₦'!D59:M59))), '0₦'!D$2:M$2) + SUMPRODUCT(--(NOT(ISBLANK('0₦'!Q59:T59))), '0₦'!Q$2:T$2)} | BD59: {=SUMPRODUCT(--(NOT(ISBLANK('0₦'!N59:P59))),'0₦'!N$2:P$2)+'0₦'!AY59} | BE59: {=SUMPRODUCT(--(NOT(ISBLANK('0₦'!AA59:AC59))),'0₦'!AA$2:AC$2) + BF59} | BG59: {=SUMPRODUCT(--(NOT(ISBLANK('0₦'!U59:Z59))), '0₦'!U$2:Z$2)} | BI59: =SUM(BG59:BH59)
B60: S | C60: =C59+1 | AR60: 40 | AU60: =N60+O60 + 0 | AW60: =SUM(AH60:AI60,AJ60/2,AK60:AL60) | AX60: =AM60*0.5+SUM(AN60:AP60) | AY60: =SUM(-AR60+AS60*0.01+AT60*0.5+AU60) | AZ60: ='0分'!AF57 | BA60: =SUM(AY60,AX60,AW60) | BC60: {=SUMPRODUCT(--(NOT(ISBLANK('0₦'!D60:M60))), '0₦'!D$2:M$2) + SUMPRODUCT(--(NOT(ISBLANK('0₦'!Q60:T60))), '0₦'!Q$2:T$2)} | BD60: {=SUMPRODUCT(--(NOT(ISBLANK('0₦'!N60:P60))),'0₦'!N$2:P$2)+'0₦'!AY60} | BE60: {=SUMPRODUCT(--(NOT(ISBLANK('0₦'!AA60:AC60))),'0₦'!AA$2:AC$2) + BF60} | BG60: {=SUMPRODUCT(--(NOT(ISBLANK('0₦'!U60:Z60))), '0₦'!U$2:Z$2)} | BI60: =SUM(BG60:BH60)
A61: =A33+1 | B61: S | C61: =C60+1 | AR61: 40 | AU61: =N61+O61 + 0 | AW61: =SUM(AH61:AI61,AJ61/2,AK61:AL61) | AX61: =AM61*0.5+SUM(AN61:AP61) | AY61: =SUM(-AR61+AS61*0.01+AT61*0.5+AU61) | AZ61: ='0分'!AF58 | BA61: =SUM(AY61,AX61,AW61) | BC61: {=SUMPRODUCT(--(NOT(ISBLANK('0₦'!D61:M61))), '0₦'!D$2:M$2) + SUMPRODUCT(--(NOT(ISBLANK('0₦'!Q61:T61))), '0₦'!Q$2:T$2)} | BD61: {=SUMPRODUCT(--(NOT(ISBLANK('0₦'!N61:P61))),'0₦'!N$2:P$2)+'0₦'!AY61} | BE61: {=SUMPRODUCT(--(NOT(ISBLANK('0₦'!AA61:AC61))),'0₦'!AA$2:AC$2) + BF61} | BG61: {=SUMPRODUCT(--(NOT(ISBLANK('0₦'!U61:Z61))), '0₦'!U$2:Z$2)} | BI61: =SUM(BG61:BH61)
B62: M | C62: =C61+1 | AR62: 40 | AU62: =N62+O62 + 0 | AW62: =SUM(AH62:AI62,AJ62/2,AK62:AL62) | AX62: =AM62*0.5+SUM(AN62:AP62) | AY62: =SUM(-AR62+AS62*0.01+AT62*0.5+AU62) | AZ62: ='0分'!AF59 | BA62: =SUM(AY62,AX62,AW62) | BC62: {=SUMPRODUCT(--(NOT(ISBLANK('0₦'!D62:M62))), '0₦'!D$2:M$2) + SUMPRODUCT(--(NOT(ISBLANK('0₦'!Q62:T62))), '0₦'!Q$2:T$2)} | BD62: {=SUMPRODUCT(--(NOT(ISBLANK('0₦'!N62:P62))),'0₦'!N$2:P$2)+'0₦'!AY62} | BE62: {=SUMPRODUCT(--(NOT(ISBLANK('0₦'!AA62:AC62))),'0₦'!AA$2:AC$2) + BF62} | BG62: {=SUMPRODUCT(--(NOT(ISBLANK('0₦'!U62:Z62))), '0₦'!U$2:Z$2)} | BI62: =SUM(BG62:BH62)
B63: T | C63: =C62+1 | AR63: 40 | AU63: =N63+O63 + 0 | AW63: =SUM(AH63:AI63,AJ63/2,AK63:AL63) | AX63: =AM63*0.5+SUM(AN63:AP63) | AY63: =SUM(-AR63+AS63*0.01+AT63*0.5+AU63) | AZ63: ='0分'!AF60 | BA63: =SUM(AY63,AX63,AW63) | BC63: {=SUMPRODUCT(--(NOT(ISBLANK('0₦'!D63:M63))), '0₦'!D$2:M$2) + SUMPRODUCT(--(NOT(ISBLANK('0₦'!Q63:T63))), '0₦'!Q$2:T$2)} | BD63: {=SUMPRODUCT(--(NOT(ISBLANK('0₦'!N63:P63))),'0₦'!N$2:P$2)+'0₦'!AY63} | BE63: {=SUMPRODUCT(--(NOT(ISBLANK('0₦'!AA63:AC63))),'0₦'!AA$2:AC$2) + BF63} | BG63: {=SUMPRODUCT(--(NOT(ISBLANK('0₦'!U63:Z63))), '0₦'!U$2:Z$2)} | BI63: =SUM(BG63:BH63)
B64: W | C64: =C63+1 | AR64: 40 | AU64: =N64+O64 + 0 | AW64: =SUM(AH64:AI64,AJ64/2,AK64:AL64) | AX64: =AM64*0.5+SUM(AN64:AP64) | AY64: =SUM(-AR64+AS64*0.01+AT64*0.5+AU64) | AZ64: ='0分'!AF61 | BA64: =SUM(AY64,AX64,AW64) | BC64: {=SUMPRODUCT(--(NOT(ISBLANK('0₦'!D64:M64))), '0₦'!D$2:M$2) + SUMPRODUCT(--(NOT(ISBLANK('0₦'!Q64:T64))), '0₦'!Q$2:T$2)} | BD64: {=SUMPRODUCT(--(NOT(ISBLANK('0₦'!N64:P64))),'0₦'!N$2:P$2)+'0₦'!AY64} | BE64: {=SUMPRODUCT(--(NOT(ISBLANK('0₦'!AA64:AC64))),'0₦'!AA$2:AC$2) + BF64} | BG64: {=SUMPRODUCT(--(NOT(ISBLANK('0₦'!U64:Z64))), '0₦'!U$2:Z$2)} | BI64: =SUM(BG64:BH64)
B65: Th | C65: =C64+1 | AR65: 40 | AU65: =N65+O65 + 0 | AW65: =SUM(AH65:AI65,AJ65/2,AK65:AL65) | AX65: =AM65*0.5+SUM(AN65:AP65) | AY65: =SUM(-AR65+AS65*0.01+AT65*0.5+AU65) | AZ65: ='0分'!AF62 | BA65: =SUM(AY65,AX65,AW65) | BC65: {=SUMPRODUCT(--(NOT(ISBLANK('0₦'!D65:M65))), '0₦'!D$2:M$2) + SUMPRODUCT(--(NOT(ISBLANK('0₦'!Q65:T65))), '0₦'!Q$2:T$2)} | BD65: {=SUMPRODUCT(--(NOT(ISBLANK('0₦'!N65:P65))),'0₦'!N$2:P$2)+'0₦'!AY65} | BE65: {=SUMPRODUCT(--(NOT(ISBLANK('0₦'!AA65:AC65))),'0₦'!AA$2:AC$2) + BF65} | BG65: {=SUMPRODUCT(--(NOT(ISBLANK('0₦'!U65:Z65))), '0₦'!U$2:Z$2)} | BI65: =SUM(BG65:BH65)
B66: F | C66: =C65+1 | AR66: 40 | AU66: =N66+O66 + 0 | AW66: =SUM(AH66:AI66,AJ66/2,AK66:AL66) | AX66: =AM66*0.5+SUM(AN66:AP66) | AY66: =SUM(-AR66+AS66*0.01+AT66*0.5+AU66) | AZ66: ='0分'!AF63 | BA66: =SUM(AY66,AX66,AW66) | BC66: {=SUMPRODUCT(--(NOT(ISBLANK('0₦'!D66:M66))), '0₦'!D$2:M$2) + SUMPRODUCT(--(NOT(ISBLANK('0₦'!Q66:T66))), '0₦'!Q$2:T$2)} | BD66: {=SUMPRODUCT(--(NOT(ISBLANK('0₦'!N66:P66))),'0₦'!N$2:P$2)+'0₦'!AY66} | BE66: {=SUMPRODUCT(--(NOT(ISBLANK('0₦'!AA66:AC66))),'0₦'!AA$2:AC$2) + BF66} | BG66: {=SUMPRODUCT(--(NOT(ISBLANK('0₦'!U66:Z66))), '0₦'!U$2:Z$2)} | BI66: =SUM(BG66:BH66)
B67: S | C67: =C66+1 | AR67: 40 | AU67: =N67+O67 + 0 | AW67: =SUM(AH67:AI67,AJ67/2,AK67:AL67) | AX67: =AM67*0.5+SUM(AN67:AP67) | AY67: =SUM(-AR67+AS67*0.01+AT67*0.5+AU67) | AZ67: ='0分'!AF64 | BA67: =SUM(AY67,AX67,AW67) | BC67: {=SUMPRODUCT(--(NOT(ISBLANK('0₦'!D67:M67))), '0₦'!D$2:M$2) + SUMPRODUCT(--(NOT(ISBLANK('0₦'!Q67:T67))), '0₦'!Q$2:T$2)} | BD67: {=SUMPRODUCT(--(NOT(ISBLANK('0₦'!N67:P67))),'0₦'!N$2:P$2)+'0₦'!AY67} | BE67: {=SUMPRODUCT(--(NOT(ISBLANK('0₦'!AA67:AC67))),'0₦'!AA$2:AC$2) + BF67} | BG67: {=SUMPRODUCT(--(NOT(ISBLANK('0₦'!U67:Z67))), '0₦'!U$2:Z$2)} | BI67: =SUM(BG67:BH67)
A68: =A61+0.1 | B68: S | C68: =C67+1 | AR68: 40 | AU68: =N68+O68 + 0 | AW68: =SUM(AH68:AI68,AJ68/2,AK68:AL68) | AX68: =AM68*0.5+SUM(AN68:AP68) | AY68: =SUM(-AR68+AS68*0.01+AT68*0.5+AU68) | AZ68: ='0分'!AF65 | BA68: =SUM(AY68,AX68,AW68) | BC68: {=SUMPRODUCT(--(NOT(ISBLANK('0₦'!D68:M68))), '0₦'!D$2:M$2) + SUMPRODUCT(--(NOT(ISBLANK('0₦'!Q68:T68))), '0₦'!Q$2:T$2)} | BD68: {=SUMPRODUCT(--(NOT(ISBLANK('0₦'!N68:P68))),'0₦'!N$2:P$2)+'0₦'!AY68} | BE68: {=SUMPRODUCT(--(NOT(ISBLANK('0₦'!AA68:AC68))),'0₦'!AA$2:AC$2) + BF68} | BG68: {=SUMPRODUCT(--(NOT(ISBLANK('0₦'!U68:Z68))), '0₦'!U$2:Z$2)} | BI68: =SUM(BG68:BH68)
B69: M | C69: =C68+1 | AR69: 40 | AU69: =N69+O69 + 0 | AW69: =SUM(AH69:AI69,AJ69/2,AK69:AL69) | AX69: =AM69*0.5+SUM(AN69:AP69) | AY69: =SUM(-AR69+AS69*0.01+AT69*0.5+AU69) | AZ69: ='0分'!AF66 | BA69: =SUM(AY69,AX69,AW69) | BC69: {=SUMPRODUCT(--(NOT(ISBLANK('0₦'!D69:M69))), '0₦'!D$2:M$2) + SUMPRODUCT(--(NOT(ISBLANK('0₦'!Q69:T69))), '0₦'!Q$2:T$2)} | BD69: {=SUMPRODUCT(--(NOT(ISBLANK('0₦'!N69:P69))),'0₦'!N$2:P$2)+'0₦'!AY69} | BE69: {=SUMPRODUCT(--(NOT(ISBLANK('0₦'!AA69:AC69))),'0₦'!AA$2:AC$2) + BF69} | BG69: {=SUMPRODUCT(--(NOT(ISBLANK('0₦'!U69:Z69))), '0₦'!U$2:Z$2)} | BI69: =SUM(BG69:BH69)
B70: T | C70: =C69+1 | AR70: 40 | AU70: =N70+O70 + 0 | AW70: =SUM(AH70:AI70,AJ70/2,AK70:AL70) | AX70: =AM70*0.5+SUM(AN70:AP70) | AY70: =SUM(-AR70+AS70*0.01+AT70*0.5+AU70) | AZ70: ='0分'!AF67 | BA70: =SUM(AY70,AX70,AW70) | BC70: {=SUMPRODUCT(--(NOT(ISBLANK('0₦'!D70:M70))), '0₦'!D$2:M$2) + SUMPRODUCT(--(NOT(ISBLANK('0₦'!Q70:T70))), '0₦'!Q$2:T$2)} | BD70: {=SUMPRODUCT(--(NOT(ISBLANK('0₦'!N70:P70))),'0₦'!N$2:P$2)+'0₦'!AY70} | BE70: {=SUMPRODUCT(--(NOT(ISBLANK('0₦'!AA70:AC70))),'0₦'!AA$2:AC$2) + BF70} | BG70: {=SUMPRODUCT(--(NOT(ISBLANK('0₦'!U70:Z70))), '0₦'!U$2:Z$2)} | BI70: =SUM(BG70:BH70)
B71: W | C71: =C70+1 | AR71: 40 | AU71: =N71+O71 + 0 | AW71: =SUM(AH71:AI71,AJ71/2,AK71:AL71) | AX71: =AM71*0.5+SUM(AN71:AP71) | AY71: =SUM(-AR71+AS71*0.01+AT71*0.5+AU71) | AZ71: ='0分'!AF68 | BA71: =SUM(AY71,AX71,AW71) | BC71: {=SUMPRODUCT(--(NOT(ISBLANK('0₦'!D71:M71))), '0₦'!D$2:M$2) + SUMPRODUCT(--(NOT(ISBLANK('0₦'!Q71:T71))), '0₦'!Q$2:T$2)} | BD71: {=SUMPRODUCT(--(NOT(ISBLANK('0₦'!N71:P71))),'0₦'!N$2:P$2)+'0₦'!AY71} | BE71: {=SUMPRODUCT(--(NOT(ISBLANK('0₦'!AA71:AC71))),'0₦'!AA$2:AC$2) + BF71} | BG71: {=SUMPRODUCT(--(NOT(ISBLANK('0₦'!U71:Z71))), '0₦'!U$2:Z$2)} | BI71: =SUM(BG71:BH71)
B72: Th | C72: =C71+1 | AR72: 40 | AU72: =N72+O72 + 0 | AW72: =SUM(AH72:AI72,AJ72/2,AK72:AL72) | AX72: =AM72*0.5+SUM(AN72:AP72) | AY72: =SUM(-AR72+AS72*0.01+AT72*0.5+AU72) | AZ72: ='0分'!AF69 | BA72: =SUM(AY72,AX72,AW72) | BC72: {=SUMPRODUCT(--(NOT(ISBLANK('0₦'!D72:M72))), '0₦'!D$2:M$2) + SUMPRODUCT(--(NOT(ISBLANK('0₦'!Q72:T72))), '0₦'!Q$2:T$2)} | BD72: {=SUMPRODUCT(--(NOT(ISBLANK('0₦'!N72:P72))),'0₦'!N$2:P$2)+'0₦'!AY72} | BE72: {=SUMPRODUCT(--(NOT(ISBLANK('0₦'!AA72:AC72))),'0₦'!AA$2:AC$2) + BF72} | BG72: {=SUMPRODUCT(--(NOT(ISBLANK('0₦'!U72:Z72))), '0₦'!U$2:Z$2)} | BI72: =SUM(BG72:BH72)
B73: F | C73: =C72+1 | AR73: 40 | AU73: =N73+O73 + 0 | AW73: =SUM(AH73:AI73,AJ73/2,AK73:AL73) | AX73: =AM73*0.5+SUM(AN73:AP73) | AY73: =SUM(-AR73+AS73*0.01+AT73*0.5+AU73) | AZ73: ='0分'!AF70 | BA73: =SUM(AY73,AX73,AW73) | BC73: {=SUMPRODUCT(--(NOT(ISBLANK('0₦'!D73:M73))), '0₦'!D$2:M$2) + SUMPRODUCT(--(NOT(ISBLANK('0₦'!Q73:T73))), '0₦'!Q$2:T$2)} | BD73: {=SUMPRODUCT(--(NOT(ISBLANK('0₦'!N73:P73))),'0₦'!N$2:P$2)+'0₦'!AY73} | BE73: {=SUMPRODUCT(--(NOT(ISBLANK('0₦'!AA73:AC73))),'0₦'!AA$2:AC$2) + BF73} | BG73: {=SUMPRODUCT(--(NOT(ISBLANK('0₦'!U73:Z73))), '0₦'!U$2:Z$2)} | BI73: =SUM(BG73:BH73)
B74: S | C74: =C73+1 | AR74: 40 | AU74: =N74+O74 + 0 | AW74: =SUM(AH74:AI74,AJ74/2,AK74:AL74) | AX74: =AM74*0.5+SUM(AN74:AP74) | AY74: =SUM(-AR74+AS74*0.01+AT74*0.5+AU74) | AZ74: ='0分'!AF71 | BA74: =SUM(AY74,AX74,AW74) | BC74: {=SUMPRODUCT(--(NOT(ISBLANK('0₦'!D74:M74))), '0₦'!D$2:M$2) + SUMPRODUCT(--(NOT(ISBLANK('0₦'!Q74:T74))), '0₦'!Q$2:T$2)} | BD74: {=SUMPRODUCT(--(NOT(ISBLANK('0₦'!N74:P74))),'0₦'!N$2:P$2)+'0₦'!AY74} | BE74: {=SUMPRODUCT(--(NOT(ISBLANK('0₦'!AA74:AC74))),'0₦'!AA$2:AC$2) + BF74} | BG74: {=SUMPRODUCT(--(NOT(ISBLANK('0₦'!U74:Z74))), '0₦'!U$2:Z$2)} | BI74: =SUM(BG74:BH74)
A75: =A68+0.1 | B75: S | C75: =C74+1 | AR75: 40 | AU75: =N75+O75 + 0 | AW75: =SUM(AH75:AI75,AJ75/2,AK75:AL75) | AX75: =AM75*0.5+SUM(AN75:AP75) | AY75: =SUM(-AR75+AS75*0.01+AT75*0.5+AU75) | AZ75: ='0分'!AF72 | BA75: =SUM(AY75,AX75,AW75) | BC75: {=SUMPRODUCT(--(NOT(ISBLANK('0₦'!D75:M75))), '0₦'!D$2:M$2) + SUMPRODUCT(--(NOT(ISBLANK('0₦'!Q75:T75))), '0₦'!Q$2:T$2)} | BD75: {=SUMPRODUCT(--(NOT(ISBLANK('0₦'!N75:P75))),'0₦'!N$2:P$2)+'0₦'!AY75} | BE75: {=SUMPRODUCT(--(NOT(ISBLANK('0₦'!AA75:AC75))),'0₦'!AA$2:AC$2) + BF75} | BG75: {=SUMPRODUCT(--(NOT(ISBLANK('0₦'!U75:Z75))), '0₦'!U$2:Z$2)} | BI75: =SUM(BG75:BH75)
B76: M | C76: =C75+1 | AR76: 40 | AU76: =N76+O76 + 0 | AW76: =SUM(AH76:AI76,AJ76/2,AK76:AL76) | AX76: =AM76*0.5+SUM(AN76:AP76) | AY76: =SUM(-AR76+AS76*0.01+AT76*0.5+AU76) | AZ76: ='0分'!AF73 | BA76: =SUM(AY76,AX76,AW76) | BC76: {=SUMPRODUCT(--(NOT(ISBLANK('0₦'!D76:M76))), '0₦'!D$2:M$2) + SUMPRODUCT(--(NOT(ISBLANK('0₦'!Q76:T76))), '0₦'!Q$2:T$2)} | BD76: {=SUMPRODUCT(--(NOT(ISBLANK('0₦'!N76:P76))),'0₦'!N$2:P$2)+'0₦'!AY76} | BE76: {=SUMPRODUCT(--(NOT(ISBLANK('0₦'!AA76:AC76))),'0₦'!AA$2:AC$2) + BF76} | BG76: {=SUMPRODUCT(--(NOT(ISBLANK('0₦'!U76:Z76))), '0₦'!U$2:Z$2)} | BI76: =SUM(BG76:BH76)
B77: T | C77: =C76+1 | AR77: 40 | AU77: =N77+O77 + 0 | AW77: =SUM(AH77:AI77,AJ77/2,AK77:AL77) | AX77: =AM77*0.5+SUM(AN77:AP77) | AY77: =SUM(-AR77+AS77*0.01+AT77*0.5+AU77) | AZ77: ='0分'!AF74 | BA77: =SUM(AY77,AX77,AW77) | BC77: {=SUMPRODUCT(--(NOT(ISBLANK('0₦'!D77:M77))), '0₦'!D$2:M$2) + SUMPRODUCT(--(NOT(ISBLANK('0₦'!Q77:T77))), '0₦'!Q$2:T$2)} | BD77: {=SUMPRODUCT(--(NOT(ISBLANK('0₦'!N77:P77))),'0₦'!N$2:P$2)+'0₦'!AY77} | BE77: {=SUMPRODUCT(--(NOT(ISBLANK('0₦'!AA77:AC77))),'0₦'!AA$2:AC$2) + BF77} | BG77: {=SUMPRODUCT(--(NOT(ISBLANK('0₦'!U77:Z77))), '0₦'!U$2:Z$2)} | BI77: =SUM(BG77:BH77)
B78: W | C78: =C77+1 | AR78: 40 | AU78: =N78+O78 + 0 | AW78: =SUM(AH78:AI78,AJ78/2,AK78:AL78) | AX78: =AM78*0.5+SUM(AN78:AP78) | AY78: =SUM(-AR78+AS78*0.01+AT78*0.5+AU78) | AZ78: ='0分'!AF75 | BA78: =SUM(AY78,AX78,AW78) | BC78: {=SUMPRODUCT(--(NOT(ISBLANK('0₦'!D78:M78))), '0₦'!D$2:M$2) + SUMPRODUCT(--(NOT(ISBLANK('0₦'!Q78:T78))), '0₦'!Q$2:T$2)} | BD78: {=SUMPRODUCT(--(NOT(ISBLANK('0₦'!N78:P78))),'0₦'!N$2:P$2)+'0₦'!AY78} | BE78: {=SUMPRODUCT(--(NOT(ISBLANK('0₦'!AA78:AC78))),'0₦'!AA$2:AC$2) + BF78} | BG78: {=SUMPRODUCT(--(NOT(ISBLANK('0₦'!U78:Z78))), '0₦'!U$2:Z$2)} | BI78: =SUM(BG78:BH78)
B79: Th | C79: =C78+1 | AR79: 40 | AU79: =N79+O79 + 0 | AW79: =SUM(AH79:AI79,AJ79/2,AK79:AL79) | AX79: =AM79*0.5+SUM(AN79:AP79) | AY79: =SUM(-AR79+AS79*0.01+AT79*0.5+AU79) | AZ79: ='0分'!AF76 | BA79: =SUM(AY79,AX79,AW79) | BC79: {=SUMPRODUCT(--(NOT(ISBLANK('0₦'!D79:M79))), '0₦'!D$2:M$2) + SUMPRODUCT(--(NOT(ISBLANK('0₦'!Q79:T79))), '0₦'!Q$2:T$2)} | BD79: {=SUMPRODUCT(--(NOT(ISBLANK('0₦'!N79:P79))),'0₦'!N$2:P$2)+'0₦'!AY79} | BE79: {=SUMPRODUCT(--(NOT(ISBLANK('0₦'!AA79:AC79))),'0₦'!AA$2:AC$2) + BF79} | BG79: {=SUMPRODUCT(--(NOT(ISBLANK('0₦'!U79:Z79))), '0₦'!U$2:Z$2)} | BI79: =SUM(BG79:BH79)
B80: F | C80: =C79+1 | AR80: 40 | AU80: =N80+O80 + 0 | AW80: =SUM(AH80:AI80,AJ80/2,AK80:AL80) | AX80: =AM80*0.5+SUM(AN80:AP80) | AY80: =SUM(-AR80+AS80*0.01+AT80*0.5+AU80) | AZ80: ='0分'!AF77 | BA80: =SUM(AY80,AX80,AW80) | BC80: {=SUMPRODUCT(--(NOT(ISBLANK('0₦'!D80:M80))), '0₦'!D$2:M$2) + SUMPRODUCT(--(NOT(ISBLANK('0₦'!Q80:T80))), '0₦'!Q$2:T$2)} | BD80: {=SUMPRODUCT(--(NOT(ISBLANK('0₦'!N80:P80))),'0₦'!N$2:P$2)+'0₦'!AY80} | BE80: {=SUMPRODUCT(--(NOT(ISBLANK('0₦'!AA80:AC80))),'0₦'!AA$2:AC$2) + BF80} | BG80: {=SUMPRODUCT(--(NOT(ISBLANK('0₦'!U80:Z80))), '0₦'!U$2:Z$2)} | BI80: =SUM(BG80:BH80)
B81: S | C81: =C80+1 | AR81: 40 | AU81: =N81+O81 + 0 | AW81: =SUM(AH81:AI81,AJ81/2,AK81:AL81) | AX81: =AM81*0.5+SUM(AN81:AP81) | AY81: =SUM(-AR81+AS81*0.01+AT81*0.5+AU81) | AZ81: ='0分'!AF78 | BA81: =SUM(AY81,AX81,AW81) | BC81: {=SUMPRODUCT(--(NOT(ISBLANK('0₦'!D81:M81))), '0₦'!D$2:M$2) + SUMPRODUCT(--(NOT(ISBLANK('0₦'!Q81:T81))), '0₦'!Q$2:T$2)} | BD81: {=SUMPRODUCT(--(NOT(ISBLANK('0₦'!N81:P81))),'0₦'!N$2:P$2)+'0₦'!AY81} | BE81: {=SUMPRODUCT(--(NOT(ISBLANK('0₦'!AA81:AC81))),'0₦'!AA$2:AC$2) + BF81} | BG81: {=SUMPRODUCT(--(NOT(ISBLANK('0₦'!U81:Z81))), '0₦'!U$2:Z$2)} | BI81: =SUM(BG81:BH81)
A82: =A75+0.1 | B82: S | C82: =C81+1 | AR82: 40 | AU82: =N82+O82 + 0 | AW82: =SUM(AH82:AI82,AJ82/2,AK82:AL82) | AX82: =AM82*0.5+SUM(AN82:AP82) | AY82: =SUM(-AR82+AS82*0.01+AT82*0.5+AU82) | AZ82: ='0分'!AF79 | BA82: =SUM(AY82,AX82,AW82) | BC82: {=SUMPRODUCT(--(NOT(ISBLANK('0₦'!D82:M82))), '0₦'!D$2:M$2) + SUMPRODUCT(--(NOT(ISBLANK('0₦'!Q82:T82))), '0₦'!Q$2:T$2)} | BD82: {=SUMPRODUCT(--(NOT(ISBLANK('0₦'!N82:P82))),'0₦'!N$2:P$2)+'0₦'!AY82} | BE82: {=SUMPRODUCT(--(NOT(ISBLANK('0₦'!AA82:AC82))),'0₦'!AA$2:AC$2) + BF82} | BG82: {=SUMPRODUCT(--(NOT(ISBLANK('0₦'!U82:Z82))), '0₦'!U$2:Z$2)} | BI82: =SUM(BG82:BH82)
B83: M | C83: =C82+1 | AR83: 40 | AU83: =N83+O83 + 0 | AW83: =SUM(AH83:AI83,AJ83/2,AK83:AL83) | AX83: =AM83*0.5+SUM(AN83:AP83) | AY83: =SUM(-AR83+AS83*0.01+AT83*0.5+AU83) | AZ83: ='0分'!AF80 | BA83: =SUM(AY83,AX83,AW83) | BC83: {=SUMPRODUCT(--(NOT(ISBLANK('0₦'!D83:M83))), '0₦'!D$2:M$2) + SUMPRODUCT(--(NOT(ISBLANK('0₦'!Q83:T83))), '0₦'!Q$2:T$2)} | BD83: {=SUMPRODUCT(--(NOT(ISBLANK('0₦'!N83:P83))),'0₦'!N$2:P$2)+'0₦'!AY83} | BE83: {=SUMPRODUCT(--(NOT(ISBLANK('0₦'!AA83:AC83))),'0₦'!AA$2:AC$2) + BF83} | BG83: {=SUMPRODUCT(--(NOT(ISBLANK('0₦'!U83:Z83))), '0₦'!U$2:Z$2)} | BI83: =SUM(BG83:BH83)
B84: T | C84: =C83+1 | AR84: 40 | AU84: =N84+O84 + 0 | AW84: =SUM(AH84:AI84,AJ84/2,AK84:AL84) | AX84: =AM84*0.5+SUM(AN84:AP84) | AY84: =SUM(-AR84+AS84*0.01+AT84*0.5+AU84) | AZ84: ='0分'!AF81 | BA84: =SUM(AY84,AX84,AW84) | BC84: {=SUMPRODUCT(--(NOT(ISBLANK('0₦'!D84:M84))), '0₦'!D$2:M$2) + SUMPRODUCT(--(NOT(ISBLANK('0₦'!Q84:T84))), '0₦'!Q$2:T$2)} | BD84: {=SUMPRODUCT(--(NOT(ISBLANK('0₦'!N84:P84))),'0₦'!N$2:P$2)+'0₦'!AY84} | BE84: {=SUMPRODUCT(--(NOT(ISBLANK('0₦'!AA84:AC84))),'0₦'!AA$2:AC$2) + BF84} | BG84: {=SUMPRODUCT(--(NOT(ISBLANK('0₦'!U84:Z84))), '0₦'!U$2:Z$2)} | BI84: =SUM(BG84:BH84)
B85: W | C85: =C84+1 | AR85: 40 | AU85: =N85+O85 + 0 | AW85: =SUM(AH85:AI85,AJ85/2,AK85:AL85) | AX85: =AM85*0.5+SUM(AN85:AP85) | AY85: =SUM(-AR85+AS85*0.01+AT85*0.5+AU85) | AZ85: ='0分'!AF82 | BA85: =SUM(AY85,AX85,AW85) | BC85: {=SUMPRODUCT(--(NOT(ISBLANK('0₦'!D85:M85))), '0₦'!D$2:M$2) + SUMPRODUCT(--(NOT(ISBLANK('0₦'!Q85:T85))), '0₦'!Q$2:T$2)} | BD85: {=SUMPRODUCT(--(NOT(ISBLANK('0₦'!N85:P85))),'0₦'!N$2:P$2)+'0₦'!AY85} | BE85: {=SUMPRODUCT(--(NOT(ISBLANK('0₦'!AA85:AC85))),'0₦'!AA$2:AC$2) + BF85} | BG85: {=SUMPRODUCT(--(NOT(ISBLANK('0₦'!U85:Z85))), '0₦'!U$2:Z$2)} | BI85: =SUM(BG85:BH85)
B86: Th | C86: =C85+1 | AR86: 40 | AU86: =N86+O86 + 0 | AW86: =SUM(AH86:AI86,AJ86/2,AK86:AL86) | AX86: =AM86*0.5+SUM(AN86:AP86) | AY86: =SUM(-AR86+AS86*0.01+AT86*0.5+AU86) | AZ86: ='0分'!AF83 | BA86: =SUM(AY86,AX86,AW86) | BC86: {=SUMPRODUCT(--(NOT(ISBLANK('0₦'!D86:M86))), '0₦'!D$2:M$2) + SUMPRODUCT(--(NOT(ISBLANK('0₦'!Q86:T86))), '0₦'!Q$2:T$2)} | BD86: {=SUMPRODUCT(--(NOT(ISBLANK('0₦'!N86:P86))),'0₦'!N$2:P$2)+'0₦'!AY86} | BE86: {=SUMPRODUCT(--(NOT(ISBLANK('0₦'!AA86:AC86))),'0₦'!AA$2:AC$2) + BF86} | BG86: {=SUMPRODUCT(--(NOT(ISBLANK('0₦'!U86:Z86))), '0₦'!U$2:Z$2)} | BI86: =SUM(BG86:BH86)
B87: F | C87: =C86+1 | AR87: 40 | AU87: =N87+O87 + 0 | AW87: =SUM(AH87:AI87,AJ87/2,AK87:AL87) | AX87: =AM87*0.5+SUM(AN87:AP87) | AY87: =SUM(-AR87+AS87*0.01+AT87*0.5+AU87) | AZ87: ='0分'!AF84 | BA87: =SUM(AY87,AX87,AW87) | BC87: {=SUMPRODUCT(--(NOT(ISBLANK('0₦'!D87:M87))), '0₦'!D$2:M$2) + SUMPRODUCT(--(NOT(ISBLANK('0₦'!Q87:T87))), '0₦'!Q$2:T$2)} | BD87: {=SUMPRODUCT(--(NOT(ISBLANK('0₦'!N87:P87))),'0₦'!N$2:P$2)+'0₦'!AY87} | BE87: {=SUMPRODUCT(--(NOT(ISBLANK('0₦'!AA87:AC87))),'0₦'!AA$2:AC$2) + BF87} | BG87: {=SUMPRODUCT(--(NOT(ISBLANK('0₦'!U87:Z87))), '0₦'!U$2:Z$2)} | BI87: =SUM(BG87:BH87)
B88: S | C88: =C87+1 | AR88: 40 | AU88: =N88+O88 + 0 | AW88: =SUM(AH88:AI88,AJ88/2,AK88:AL88) | AX88: =AM88*0.5+SUM(AN88:AP88) | AY88: =SUM(-AR88+AS88*0.01+AT88*0.5+AU88) | AZ88: ='0分'!AF85 | BA88: =SUM(AY88,AX88,AW88) | BC88: {=SUMPRODUCT(--(NOT(ISBLANK('0₦'!D88:M88))), '0₦'!D$2:M$2) + SUMPRODUCT(--(NOT(ISBLANK('0₦'!Q88:T88))), '0₦'!Q$2:T$2)} | BD88: {=SUMPRODUCT(--(NOT(ISBLANK('0₦'!N88:P88))),'0₦'!N$2:P$2)+'0₦'!AY88} | BE88: {=SUMPRODUCT(--(NOT(ISBLANK('0₦'!AA88:AC88))),'0₦'!AA$2:AC$2) + BF88} | BG88: {=SUMPRODUCT(--(NOT(ISBLANK('0₦'!U88:Z88))), '0₦'!U$2:Z$2)} | BI88: =SUM(BG88:BH88)
A89: =A82+0.1 | B89: S | C89: =C88+1 | AR89: 40 | AU89: =N89+O89 + 0 | AW89: =SUM(AH89:AI89,AJ89/2,AK89:AL89) | AX89: =AM89*0.5+SUM(AN89:AP89) | AY89: =SUM(-AR89+AS89*0.01+AT89*0.5+AU89) | AZ89: ='0分'!AF86 | BA89: =SUM(AY89,AX89,AW89) | BC89: {=SUMPRODUCT(--(NOT(ISBLANK('0₦'!D89:M89))), '0₦'!D$2:M$2) + SUMPRODUCT(--(NOT(ISBLANK('0₦'!Q89:T89))), '0₦'!Q$2:T$2)} | BD89: {=SUMPRODUCT(--(NOT(ISBLANK('0₦'!N89:P89))),'0₦'!N$2:P$2)+'0₦'!AY89} | BE89: {=SUMPRODUCT(--(NOT(ISBLANK('0₦'!AA89:AC89))),'0₦'!AA$2:AC$2) + BF89} | BG89: {=SUMPRODUCT(--(NOT(ISBLANK('0₦'!U89:Z89))), '0₦'!U$2:Z$2)} | BI89: =SUM(BG89:BH89)
B90: M | C90: =C89+1 | AR90: 40 | AU90: =N90+O90 + 0 | AW90: =SUM(AH90:AI90,AJ90/2,AK90:AL90) | AX90: =AM90*0.5+SUM(AN90:AP90) | AY90: =SUM(-AR90+AS90*0.01+AT90*0.5+AU90) | AZ90: ='0分'!AF87 | BA90: =SUM(AY90,AX90,AW90) | BC90: {=SUMPRODUCT(--(NOT(ISBLANK('0₦'!D90:M90))), '0₦'!D$2:M$2) + SUMPRODUCT(--(NOT(ISBLANK('0₦'!Q90:T90))), '0₦'!Q$2:T$2)} | BD90: {=SUMPRODUCT(--(NOT(ISBLANK('0₦'!N90:P90))),'0₦'!N$2:P$2)+'0₦'!AY90} | BE90: {=SUMPRODUCT(--(NOT(ISBLANK('0₦'!AA90:AC90))),'0₦'!AA$2:AC$2) + BF90} | BG90: {=SUMPRODUCT(--(NOT(ISBLANK('0₦'!U90:Z90))), '0₦'!U$2:Z$2)} | BI90: =SUM(BG90:BH90)
B91: T | C91: =C90+1 | AR91: 40 | AU91: =N91+O91 + 0 | AW91: =SUM(AH91:AI91,AJ91/2,AK91:AL91) | AX91: =AM91*0.5+SUM(AN91:AP91) | AY91: =SUM(-AR91+AS91*0.01+AT91*0.5+AU91) | AZ91: ='0分'!AF88 | BA91: =SUM(AY91,AX91,AW91) | BC91: {=SUMPRODUCT(--(NOT(ISBLANK('0₦'!D91:M91))), '0₦'!D$2:M$2) + SUMPRODUCT(--(NOT(ISBLANK('0₦'!Q91:T91))), '0₦'!Q$2:T$2)} | BD91: {=SUMPRODUCT(--(NOT(ISBLANK('0₦'!N91:P91))),'0₦'!N$2:P$2)+'0₦'!AY91} | BE91: {=SUMPRODUCT(--(NOT(ISBLANK('0₦'!AA91:AC91))),'0₦'!AA$2:AC$2) + BF91} | BG91: {=SUMPRODUCT(--(NOT(ISBLANK('0₦'!U91:Z91))), '0₦'!U$2:Z$2)} | BI91: =SUM(BG91:BH91)
B92: W | C92: =C91+1 | AR92: 40 | AU92: =N92+O92 + 0 | AW92: =SUM(AH92:AI92,AJ92/2,AK92:AL92) | AX92: =AM92*0.5+SUM(AN92:AP92) | AY92: =SUM(-AR92+AS92*0.01+AT92*0.5+AU92) | AZ92: ='0分'!AF89 | BA92: =SUM(AY92,AX92,AW92) | BC92: {=SUMPRODUCT(--(NOT(ISBLANK('0₦'!D92:M92))), '0₦'!D$2:M$2) + SUMPRODUCT(--(NOT(ISBLANK('0₦'!Q92:T92))), '0₦'!Q$2:T$2)} | BD92: {=SUMPRODUCT(--(NOT(ISBLANK('0₦'!N92:P92))),'0₦'!N$2:P$2)+'0₦'!AY92} | BE92: {=SUMPRODUCT(--(NOT(ISBLANK('0₦'!AA92:AC92))),'0₦'!AA$2:AC$2) + BF92} | BG92: {=SUMPRODUCT(--(NOT(ISBLANK('0₦'!U92:Z92))), '0₦'!U$2:Z$2)} | BI92: =SUM(BG92:BH92)
B93: Th | C93: =C92+1 | AR93: 40 | AU93: =N93+O93 + 0 | AW93: =SUM(AH93:AI93,AJ93/2,AK93:AL93) | AX93: =AM93*0.5+SUM(AN93:AP93) | AY93: =SUM(-AR93+AS93*0.01+AT93*0.5+AU93) | AZ93: ='0分'!AF90 | BA93: =SUM(AY93,AX93,AW93) | BC93: {=SUMPRODUCT(--(NOT(ISBLANK('0₦'!D93:M93))), '0₦'!D$2:M$2) + SUMPRODUCT(--(NOT(ISBLANK('0₦'!Q93:T93))), '0₦'!Q$2:T$2)} | BD93: {=SUMPRODUCT(--(NOT(ISBLANK('0₦'!N93:P93))),'0₦'!N$2:P$2)+'0₦'!AY93} | BE93: {=SUMPRODUCT(--(NOT(ISBLANK('0₦'!AA93:AC93))),'0₦'!AA$2:AC$2) + BF93} | BG93: {=SUMPRODUCT(--(NOT(ISBLANK('0₦'!U93:Z93))), '0₦'!U$2:Z$2)} | BI93: =SUM(BG93:BH93)
B94: F | C94: =C93+1 | AR94: 40 | AU94: =N94+O94 + 0 | AW94: =SUM(AH94:AI94,AJ94/2,AK94:AL94) | AX94: =AM94*0.5+SUM(AN94:AP94) | AY94: =SUM(-AR94+AS94*0.01+AT94*0.5+AU94) | AZ94: ='0分'!AF91 | BA94: =SUM(AY94,AX94,AW94) | BC94: {=SUMPRODUCT(--(NOT(ISBLANK('0₦'!D94:M94))), '0₦'!D$2:M$2) + SUMPRODUCT(--(NOT(ISBLANK('0₦'!Q94:T94))), '0₦'!Q$2:T$2)} | BD94: {=SUMPRODUCT(--(NOT(ISBLANK('0₦'!N94:P94))),'0₦'!N$2:P$2)+'0₦'!AY94} | BE94: {=SUMPRODUCT(--(NOT(ISBLANK('0₦'!AA94:AC94))),'0₦'!AA$2:AC$2) + BF94} | BG94: {=SUMPRODUCT(--(NOT(ISBLANK('0₦'!U94:Z94))), '0₦'!U$2:Z$2)} | BI94: =SUM(BG94:BH94)
B95: S | C95: =C94+1 | AR95: 40 | AU95: =N95+O95 + 0 | AW95: =SUM(AH95:AI95,AJ95/2,AK95:AL95) | AX95: =AM95*0.5+SUM(AN95:AP95) | AY95: =SUM(-AR95+AS95*0.01+AT95*0.5+AU95) | AZ95: ='0分'!AF92 | BA95: =SUM(AY95,AX95,AW95) | BC95: {=SUMPRODUCT(--(NOT(ISBLANK('0₦'!D95:M95))), '0₦'!D$2:M$2) + SUMPRODUCT(--(NOT(ISBLANK('0₦'!Q95:T95))), '0₦'!Q$2:T$2)} | BD95: {=SUMPRODUCT(--(NOT(ISBLANK('0₦'!N95:P95))),'0₦'!N$2:P$2)+'0₦'!AY95} | BE95: {=SUMPRODUCT(--(NOT(ISBLANK('0₦'!AA95:AC95))),'0₦'!AA$2:AC$2) + BF95} | BG95: {=SUMPRODUCT(--(NOT(ISBLANK('0₦'!U95:Z95))), '0₦'!U$2:Z$2)} | BI95: =SUM(BG95:BH95)
A96: =A61+1 | B96: S | C96: =C95+1 | AR96: 40 | AU96: =N96+O96 + 0 | AW96: =SUM(AH96:AI96,AJ96/2,AK96:AL96) | AX96: =AM96*0.5+SUM(AN96:AP96) | AY96: =SUM(-AR96+AS96*0.01+AT96*0.5+AU96) | AZ96: ='0分'!AF93 | BA96: =SUM(AY96,AX96,AW96) | BC96: {=SUMPRODUCT(--(NOT(ISBLANK('0₦'!D96:M96))), '0₦'!D$2:M$2) + SUMPRODUCT(--(NOT(ISBLANK('0₦'!Q96:T96))), '0₦'!Q$2:T$2)} | BD96: {=SUMPRODUCT(--(NOT(ISBLANK('0₦'!N96:P96))),'0₦'!N$2:P$2)+'0₦'!AY96} | BE96: {=SUMPRODUCT(--(NOT(ISBLANK('0₦'!AA96:AC96))),'0₦'!AA$2:AC$2) + BF96} | BG96: {=SUMPRODUCT(--(NOT(ISBLANK('0₦'!U96:Z96))), '0₦'!U$2:Z$2)} | BI96: =SUM(BG96:BH96)
B97: M | C97: =C96+1 | AR97: 40 | AU97: =N97+O97 + 0 | AW97: =SUM(AH97:AI97,AJ97/2,AK97:AL97) | AX97: =AM97*0.5+SUM(AN97:AP97) | AY97: =SUM(-AR97+AS97*0.01+AT97*0.5+AU97) | AZ97: ='0分'!AF94 | BA97: =SUM(AY97,AX97,AW97) | BC97: {=SUMPRODUCT(--(NOT(ISBLANK('0₦'!D97:M97))), '0₦'!D$2:M$2) + SUMPRODUCT(--(NOT(ISBLANK('0₦'!Q97:T97))), '0₦'!Q$2:T$2)} | BD97: {=SUMPRODUCT(--(NOT(ISBLANK('0₦'!N97:P97))),'0₦'!N$2:P$2)+'0₦'!AY97} | BE97: {=SUMPRODUCT(--(NOT(ISBLANK('0₦'!AA97:AC97))),'0₦'!AA$2:AC$2) + BF97} | BG97: {=SUMPRODUCT(--(NOT(ISBLANK('0₦'!U97:Z97))), '0₦'!U$2:Z$2)} | BI97: =SUM(BG97:BH97)
B98: T | C98: =C97+1 | AR98: 40 | AU98: =N98+O98 + 0 | AW98: =SUM(AH98:AI98,AJ98/2,AK98:AL98) | AX98: =AM98*0.5+SUM(AN98:AP98) | AY98: =SUM(-AR98+AS98*0.01+AT98*0.5+AU98) | AZ98: ='0分'!AF95 | BA98: =SUM(AY98,AX98,AW98) | BC98: {=SUMPRODUCT(--(NOT(ISBLANK('0₦'!D98:M98))), '0₦'!D$2:M$2) + SUMPRODUCT(--(NOT(ISBLANK('0₦'!Q98:T98))), '0₦'!Q$2:T$2)} | BD98: {=SUMPRODUCT(--(NOT(ISBLANK('0₦'!N98:P98))),'0₦'!N$2:P$2)+'0₦'!AY98} | BE98: {=SUMPRODUCT(--(NOT(ISBLANK('0₦'!AA98:AC98))),'0₦'!AA$2:AC$2) + BF98} | BG98: {=SUMPRODUCT(--(NOT(ISBLANK('0₦'!U98:Z98))), '0₦'!U$2:Z$2)} | BI98: =SUM(BG98:BH98)
B99: W | C99: =C98+1 | AR99: 40 | AU99: =N99+O99 + 0 | AW99: =SUM(AH99:AI99,AJ99/2,AK99:AL99) | AX99: =AM99*0.5+SUM(AN99:AP99) | AY99: =SUM(-AR99+AS99*0.01+AT99*0.5+AU99) | AZ99: ='0分'!AF96 | BA99: =SUM(AY99,AX99,AW99) | BC99: {=SUMPRODUCT(--(NOT(ISBLANK('0₦'!D99:M99))), '0₦'!D$2:M$2) + SUMPRODUCT(--(NOT(ISBLANK('0₦'!Q99:T99))), '0₦'!Q$2:T$2)} | BD99: {=SUMPRODUCT(--(NOT(ISBLANK('0₦'!N99:P99))),'0₦'!N$2:P$2)+'0₦'!AY99} | BE99: {=SUMPRODUCT(--(NOT(ISBLANK('0₦'!AA99:AC99))),'0₦'!AA$2:AC$2) + BF99} | BG99: {=SUMPRODUCT(--(NOT(ISBLANK('0₦'!U99:Z99))), '0₦'!U$2:Z$2)} | BI99: =SUM(BG99:BH99)
B100: Th | C100: =C99+1 | AR100: 40 | AU100: =N100+O100 + 0 | AW100: =SUM(AH100:AI100,AJ100/2,AK100:AL100) | AX100: =AM100*0.5+SUM(AN100:AP100) | AY100: =SUM(-AR100+AS100*0.01+AT100*0.5+AU100) | AZ100: ='0分'!AF97 | BA100: =SUM(AY100,AX100,AW100) | BC100: {=SUMPRODUCT(--(NOT(ISBLANK('0₦'!D100:M100))), '0₦'!D$2:M$2) + SUMPRODUCT(--(NOT(ISBLANK('0₦'!Q100:T100))), '0₦'!Q$2:T$2)} | BD100: {=SUMPRODUCT(--(NOT(ISBLANK('0₦'!N100:P100))),'0₦'!N$2:P$2)+'0₦'!AY100} | BE100: {=SUMPRODUCT(--(NOT(ISBLANK('0₦'!AA100:AC100))),'0₦'!AA$2:AC$2) + BF100} | BG100: {=SUMPRODUCT(--(NOT(ISBLANK('0₦'!U100:Z100))), '0₦'!U$2:Z$2)} | BI100: =SUM(BG100:BH100)
...

Sheet 0s
A1: 周 | B1: 5^0 | C1: dow | D1: What is my motivation for today? | E1: Title of the Day | F1: Who did I notice | G1: What am I thankful for? | H1: What was the biggest win today? (غسق} | I1: What was the biggest missed opportunity today? | J1: c084 | K1: 霓虹 | L1: 帮助 | M1: 身体 | N1: Body Notes | O1: ₹ | P1: ⌈ | Q1: ⌊ | R1: x̄ | S1: What am I proud of with regards to others? | T1: What do I regret with regards to others? | U1: Curriculum | V1: ⌈ | W1: ⌊ | X1: 1 hcme | Z1: Time | AA1: Event Review | AB1: Notes for Improvement / Upcoming | AD1: Name | AE1: Dates | AF1: Category | AG1: 分 | AH1: How I got out of it | AI1: Notes
A2: 1.1 | B2: 46023 | C2: Th | D2: n/a | E2: Slipping into Video Games | G2: It's nice to not feel guilty about gaming | H2: Able to track the day | I2: I think better to play video games after LAN | K2: 1 | L2: 1 | M2: 8 | O2: 514 | P2: 7.5 | Q2: 6 | R2: 6.5 | S2: Math in the morning | T2: Gaming is not the best use of time | V2: 7.5 | W2: 6.5 | X2: • Café Juanita, combined with the ability to have a little bit of 享受, was definitely a highlight of the week. • Getting to do neon in the morning is such a blessing. I should really keep doing it, and keep going to bed early to enable it. • I think I should continue to bow out of meetings or conferences if tehy are a waste of time or I'm not caught up on neon. • Interesting but not surprising that the stress pinches when I try and pick up for the slack left behind (i.e. Saturday rather than Thursday) | Z2: 641 | AA2: • LAN Party: B- [中量] • Call with Forest A | AB2: • The rule should be 1:1 time in event vs. prep for event, key being that I'm not the one doing the prep. • I can plan these things super far in advance. • Calling people is a great thing and I should keep doing it, even if at random.
B3: =B2+1 | C3: F | D3: n/a | E3: Reviving the LAN Party | G3: I can still find enjoyment in the adrenaline cycle | H3: Put together and executed the LAN party | I3: Playing AOE wasn't as coordinated as I wanted it to be | K3: 0 | L3: 1 | M3: 6 | N3: oof the shoes hurt | O3: 1199 | P3: 7.8 | Q3: 6.5 | R3: 7 | S3: Gave Forest a call | T3: Took a little debt from future days | V3: 7.5 | W3: 6.5
B4: =B3+1 | C4: S | D4: Family time is still my time | E4: Pay off family debt | G4: I found time in the evening | H4: Got some of the g245 done | I4: Didn't do neon in the morning | K4: 1 | L4: 1 | M4: 6 | O4: 1562 | P4: 7.5 | Q4: 5.5 | R4: 7 | S4: Good time with fam | T4: nervous about going back to work | V4: 7.5 | W4: 6.5
B5: =B4+1 | C5: S | D5: Be confident in my next step | E5: Pay off 0l debt | G5: Energy to get something meaningful done | H5: Getting through 0l | I5: Didn’t get to work | K5: 1 | L5: 1 | M5: 8 | O5: ='0分'!D2 | P5: 7.8 | Q5: 6 | R5: 7.1 | S5: They did lego together | T5: I did not like the walk | V5: 7.5 | W5: 5.5
B6: =B5+1 | C6: M | D6: Stay calm, move forward | E6: Tackle the hord things first | F6: Ben Glasses | G6: Solid time with family even when kids emotions high | H6: I felt like I had time to do important things | I6: Hiit is what fell below the line | K6: 1 | L6: 1 | M6: 8 | O6: ='0分'!D3 | P6: 7.8 | Q6: 6.5 | R6: 7.3 | S6: 自由式的lego | T6: Could I have done a better reading session with him? | V6: 7.6 | W6: 6.5
B7: =B6+1 | C7: T | D7: Time is still mine | E7: Fly to met | F7: VOC Logo | G7: Such unexpected memories | H7: I secretly enjoyed dinner | I7: I should have been more conscious about the time at the dinner | K7: 1 | L7: 1 | M7: 8 | O7: ='0分'!D4 | P7: 8 | Q7: 6.5 | R7: 7.1 | S7: Good call with LX | T7: nothing with kids | V7: 7.5 | W7: 6.5
B8: =B7+1 | C8: W | D8: n/a | E8: Conference fatigue | F8: Jay fashion | G8: Seattle friends + family | H8: Got the i9 done during the day | I8: didn't get to neon | L8: 1 | M8: 8 | O8: ='0分'!D5 | P8: 7.8 | Q8: 5.5 | R8: 6.8 | S8: Called LX + call with theo | T8: Bad to be away from the kids? | V8: 7.5 | W8: 6.5 | Z8: 684 | AA8: • Strangely enjoyed the dinner at Café Juanita: A. • Happy hour with coworkers: A. • House of Air w/Zach + Angela. B • Hang out and Dinner with Zach + Angela. B • Julia dinner and Hang out. A | AB8: • I think trying to enjoy the atmosphere is really good. • Staying social is a way to stay sane. • I need to get an assistant for personal life. • Doing playdates is a great way to hang out.
A9: =A2+0.1 | B9: =B8+1 | C9: Th | D9: 累不累，时间是我的 | E9: Avoiding the conference | F9: People noticed the monitor | G9: Friends to relax with | H9: Got qz12 done | I9: Morning lost task tracking a bit | K9: 1 | L9: 1 | M9: 8 | O9: ='0分'!D6 | P9: 7.5 | Q9: 6.5 | R9: 7 | S9: Good call with LX | T9: No kids time | V9: 7.5 | W9: 6.5 | X9: • Interesting that the 4.0 translates to about 700 points lost aginst what would be 'best days'. So I should invest time / money in a resilient tech stack. • Friday being good rolled into the weekend nicely. • There can be a lack of correlation between neon and 分。 • At least I was aware that things were going not great on Thursday, and doing the friend time was probably the best.
B10: =B9+1 | C10: F | D10: 我的时间 | E10: Private Jet is Normal | F10: Dan Lewis Beard | G10: SFO so much closer | H10: Got things done after SLT | I10: Afternoon tasks weren't crisp | K10: 1 | L10: 1 | M10: 8 | O10: ='0分'!D7 | P10: 8 | Q10: 6.5 | R10: 7.1 | S10: I just like spending time with the kids | T10: Initial not finishing math with theo | V10: 7.6 | W10: 6.4
B11: =B10+1 | C11: S | D11: ambitious family time | E11: Setting goals for family works | G11: Theo has friends | H11: House of Air + greens was great | I11: put myself into a food coma, no workout | K11: 1 | L11: 1 | M11: 6 | O11: ='0分'!D8 | P11: 7.9 | Q11: 6.5 | R11: 7.2 | S11: Getting the house of air activity together | T11: lost the plot in the evening? | V11: 7.8 | W11: 6.5
B12: =B11+1 | C12: S | D12: Ambitious time | E12: Book start, 5y old Chaos | G12: LX able to help with the kids | H12: Spent most of the day aligned | I12: Getting Ren to bed is so difficult | K12: 1 | L12: 1 | M12: 6 | O12: ='0分'!D9 | P12: 7.8 | Q12: 6.5 | R12: 7.2 | S12: 2x math with both is no pushover | T12: Would have been nice to do rolly polly | V12: 7.5 | W12: 5
B13: =B12+1 | C13: M | D13: See the good in the opportunities | E13: No Computer = 💀 | G13: Non computer aspets of life are great | H13: Math + Evening | I13: Work was a disaster | K13: 1 | L13: 1 | M13: 6 | O13: ='0分'!D10 | P13: 7.8 | Q13: 4 | R13: 5 | S13: Nearly finished with curriculum | T13: LX got angry as I was away after ashan | V13: 7.5 | W13: 5.5
B14: =B13+1 | C14: T | D14: Forgive myself for recovery | E14: Rebooting is slow | F14: Stuart setup | G14: A neighborhood walk with my wife | H14: Hanging out with LX | I14: Didn't get into anything meaty work wise | K14: 1 | L14: 1 | M14: 8 | O14: ='0分'!D11 | P14: 7.7 | Q14: 6.5 | R14: 7 | S14: Reading Ren Dogman | T14: Picked the wrong schedule? | V14: 7.5 | W14: 6.5 | Z14: =7*60+36+33 | AA14: • Stuart Catch up: A • Playdate, talk with Matt: A • 崇一：B | AB14: • Time with qz12 is really good. • I do need to get an assistant for personal life. • Playdates are a fun thing to do on Saturdays. • I should plan Muir woods with mom.
B15: =B14+1 | C15: W | D15: Keep my own momentum | E15: Keeping smooth transitions | F15: The phone mount | G15: Having a wifi subscription and 2nd monitor | H15: Getting out the weekly update | I15: I could have done HIIT | K15: 1 | L15: 1 | M15: 8 | O15: ='0分'!D12 | P15: 7.7 | Q15: 6.5 | R15: 7 | S15: Squeezing in math with both | T15: Theo in tears at the end | V15: 7.5 | W15: 6.5
A16: =A9+0.1 | B16: =B15+1 | C16: Th | D16: The sun is still there | E16: Schedule change stress | F16: Stuart Beard | G16: Good friends | H16: Able to at least recover the Amy preso | I16: The schedule change hurts | L16: 1 | M16: 6 | O16: ='0分'!D13 | P16: 7.5 | Q16: 5.5 | R16: 6.5 | S16: I think I can provide value here | T16: Didn't handle Aleks promo well | V16: 7.5 | W16: 6.5 | X16: • Gosh that was a magical flight. I certainly wasn't able to replicate it, but it's worth trying for it. • It's interesting to think that this might be one of the best week's I've ever had. Easy to forget that. • Professional wins, personal wins, and family wins. Getting out with the family in nature is one of the most rewarding things. • It's worth planning with mom for where to go next . • Some of the rituals really matter.
B17: =B16+1 | C17: F | D17: Keep moving forward | E17: Beautiful flight home | F17: Asha kid intro | G17: Figuring out travel | H17: GH Budget meeting | I17: Could I have improved the. Morning? | K17: 1 | L17: 1 | M17: 8 | O17: ='0分'!D14 | P17: 8.1 | Q17: 6.5 | R17: 7.3 | S17: Talking with LX at night | T17: Thank you's faster? | V17: 7.8 | W17: 6.5
B18: =B17+1 | C18: S | D18: 这还是我时间 | E18: Surprise beach day | F18: Beach bodies | G18: Living on the coast | H18: Did a good job maximizing xk87 | I18: Didn’t get to 2x math | K18: 1 | L18: 1 | M18: 8 | O18: ='0分'!D15 | P18: 8 | Q18: 6.5 | R18: 7.2 | S18: Getting to the beach and B&N | T18: Standing up family | V18: 7.9 | W18: 6.5
B19: =B18+1 | C19: S | D19: Forward but no need to strain | E19: Real estate -> Sunset | F19: Joggers coming down | G19: Interesting things outside | H19: kn47 roadmap and solid meetings | I19: Didn't outsource social planning | K19: 1 | L19: 1 | M19: 8 | O19: ='0分'!D16 | P19: 8 | Q19: 6.5 | R19: 7.2 | S19: Kids to the peak | T19: How could we make this more the Sunday meetings better for staff? | V19: 7.5 | W19: 6.5
B20: =B19+1 | C20: M | D20: n/a | E20: Playing in the rivers and trees of Berkeley | F20: lower BMI | G20: The kids are independent in nature | H20: Berkeley was great | I20: woke up late, no neon time slotted | K20: 0 | L20: 1 | M20: 7 | O20: ='0分'!D17 | P20: 8 | Q20: 6.5 | R20: 7 | S20: Kids just playing and exploring on their own | T20: Ren falls x2 | V20: 7.5 | W20: 6.5
B21: =B20+1 | C21: T | D21: Behind is only a state of mind. Focus on the opportunity | E21: Cache overflow | F21: Andy backdrop | G21: Incrementally better routines | H21: Solid points through the day, not stressed | I21: Wasn't able to get andy ramp doc | K21: 1 | L21: 1 | M21: 8 | O21: ='0分'!D18 | P21: 7.5 | Q21: 6.5 | R21: 7 | S21: Playing sum swamp with theo | T21: Too much of the relationship is math? | V21: 7.5 | W21: 6
B22: =B21+1 | C22: W | D22: Keep flow state | E22: +$10m | F22: Danton phD look | G22: Nice to get 1:1's with staff | H22: Got colors done through the day | I22: Email starting to lag | K22: 1 | L22: 1 | M22: 8 | O22: ='0分'!D19 | P22: 8.2 | Q22: 6.5 | R22: 7.1 | S22: The 1:1's were good | T22: I have to remember the power dynamic of being skip level | V22: 7.5 | W22: 6.5
A23: =A16+0.1 | B23: =B22+1 | C23: Th | D23: Cruising speed | E23: Suzallo | F23: Barista | G23: I can enjoy places much more | H23: Going to Suzzallo | I23: I forgot email! | K23: 1 | L23: 1 | M23: 8 | O23: ='0分'!D20 | P23: 8 | Q23: 6.5 | R23: 7.1 | S23: Called LX multiple times | T23: What about coworkers | V23: 7 | W23: 5
B24: =B23+1 | C24: F | O24: ='0分'!D21
B25: =B24+1 | C25: S | O25: ='0分'!D22
B26: =B25+1 | C26: S | O26: ='0分'!D23
B27: =B26+1 | C27: M | O27: ='0分'!D24
B28: =B27+1 | C28: T | O28: ='0分'!D25
B29: =B28+1 | C29: W | O29: ='0分'!D26
A30: =A2+1 | B30: =B29+1 | C30: Th | O30: ='0分'!D27
B31: =B30+1 | C31: F | O31: ='0分'!D28
B32: =B31+1 | C32: S | O32: ='0分'!D29
B33: =B32+1 | C33: S | O33: ='0分'!D30
B34: =B33+1 | C34: M | O34: ='0分'!D31
B35: =B34+1 | C35: T | O35: ='0分'!D32
B36: =B35+1 | C36: W | O36: ='0分'!D33
A37: =A30+0.1 | B37: =B36+1 | C37: Th | O37: ='0分'!D34
B38: =B37+1 | C38: F | O38: ='0分'!D35
B39: =B38+1 | C39: S | O39: ='0分'!D36
B40: =B39+1 | C40: S | O40: ='0分'!D37
B41: =B40+1 | C41: M | O41: ='0分'!D38
B42: =B41+1 | C42: T | O42: ='0分'!D39
B43: =B42+1 | C43: W | O43: ='0分'!D40
A44: =A37+0.1 | B44: =B43+1 | C44: Th | O44: ='0分'!D41
B45: =B44+1 | C45: F | O45: ='0分'!D42
B46: =B45+1 | C46: S | O46: ='0分'!D43
B47: =B46+1 | C47: S | O47: ='0分'!D44
B48: =B47+1 | C48: M | O48: ='0分'!D45
B49: =B48+1 | C49: T | O49: ='0分'!D46
B50: =B49+1 | C50: W | O50: ='0分'!D47
A51: =A44+0.1 | B51: =B50+1 | C51: Th | O51: ='0分'!D48
B52: =B51+1 | C52: F | O52: ='0分'!D49
B53: =B52+1 | C53: S | O53: ='0分'!D50
B54: =B53+1 | C54: S | O54: ='0分'!D51
B55: =B54+1 | C55: M | O55: ='0分'!D52
B56: =B55+1 | C56: T | O56: ='0分'!D53
B57: =B56+1 | C57: W | O57: ='0分'!D54
A58: =A30+1 | B58: =B57+1 | C58: Th | O58: ='0分'!D55
B59: =B58+1 | C59: F | O59: ='0分'!D56
B60: =B59+1 | C60: S | O60: ='0分'!D57
B61: =B60+1 | C61: S | O61: ='0分'!D58
B62: =B61+1 | C62: M | O62: ='0分'!D59
B63: =B62+1 | C63: T | O63: ='0分'!D60
B64: =B63+1 | C64: W | O64: ='0分'!D61
A65: =A58+0.1 | B65: =B64+1 | C65: Th | O65: ='0分'!D62
B66: =B65+1 | C66: F | O66: ='0分'!D63
B67: =B66+1 | C67: S | O67: ='0分'!D64
B68: =B67+1 | C68: S | O68: ='0分'!D65
B69: =B68+1 | C69: M | O69: ='0分'!D66
B70: =B69+1 | C70: T | O70: ='0分'!D67
B71: =B70+1 | C71: W | O71: ='0分'!D68
A72: =A65+0.1 | B72: =B71+1 | C72: Th | O72: ='0分'!D69
B73: =B72+1 | C73: F | O73: ='0分'!D70
B74: =B73+1 | C74: S | O74: ='0分'!D71
B75: =B74+1 | C75: S | O75: ='0分'!D72
B76: =B75+1 | C76: M | O76: ='0分'!D73
B77: =B76+1 | C77: T | O77: ='0分'!D74
B78: =B77+1 | C78: W | O78: ='0分'!D75
A79: =A72+0.1 | B79: =B78+1 | C79: Th | O79: ='0分'!D76
B80: =B79+1 | C80: F | O80: ='0分'!D77
B81: =B80+1 | C81: S | O81: ='0分'!D78
B82: =B81+1 | C82: S | O82: ='0分'!D79
B83: =B82+1 | C83: M | O83: ='0分'!D80
B84: =B83+1 | C84: T | O84: ='0分'!D81
B85: =B84+1 | C85: W | O85: ='0分'!D82
A86: =A79+0.1 | B86: =B85+1 | C86: Th | O86: ='0分'!D83
B87: =B86+1 | C87: F | O87: ='0分'!D84
B88: =B87+1 | C88: S | O88: ='0分'!D85
B89: =B88+1 | C89: S | O89: ='0分'!D86
B90: =B89+1 | C90: M | O90: ='0分'!D87
B91: =B90+1 | C91: T | O91: ='0分'!D88
B92: =B91+1 | C92: W | O92: ='0分'!D89
A93: =A58+1 | B93: =B92+1 | C93: Th | O93: ='0分'!D90
B94: =B93+1 | C94: F | O94: ='0分'!D91
B95: =B94+1 | C95: S | O95: ='0分'!D92
B96: =B95+1 | C96: S | O96: ='0分'!D93
B97: =B96+1 | C97: M | O97: ='0分'!D94
B98: =B97+1 | C98: T | O98: ='0分'!D95
B99: =B98+1 | C99: W | O99: ='0分'!D96
A100: =A93+0.1 | B100: =B99+1 | C100: Th | O100: ='0分'!D97
...

Sheet hcbi
A1: 周 | B1: Date | C1: d | D1: ∑ | E1: bn | F1: br | G1: fr | H1: cr | I1: gr | J1: vg | K1: fx | L1: g | M1: nt | N1: sp | O1: wtr | P1: protein | Q1: mg cfn | R1: g al | T1: 0₦ | U1: cal | W1: caf | X1: food | Y1: hcbp | AA1: ∑c | AB1: hcbc | AC1: hcbp | AD1: 社 | AE1: ff | AG1: 分享 | AJ1: Worst Out | AL1: Early Morning | AO1: Breakfast | AR1: Early Snack | AU1: Lunch | AX1: Afternoon Snack | BA1: Dinner | BD1: Late Snack | BH1: Weight | BI1: Notes | BJ1: Pic | BK1: Goals (w/hci) | BM1: ∑₹ | BN1: 洗澡 | BO1: 社
A3: 12.5 | B3: =B4-1 | C3: Th | D3: =SUM(T3,AA3) | E3: 2 | F3: 1 | G3: 0 | H3: 0 | I3: 0 | J3: 1 | K3: 0 | L3: 3 | M3: 0 | N3: 2 | O3: 2 | P3: =SUM(AN3,AQ3,AT3,AW3,AZ3,BC3,BF3) | R3: 0 | T3: 20 | U3: 2045 | V3: =AVERAGE(U3:U9) | W3: -35 | X3: =AA3-W3 | Y3: 2 | AA3: =SUM(E3:O3)/21*75 + IF(AM3, -(MAX((U3-1800)/10, -40)), 0)+T3 + S3 + (P3-100)*0.5+AI3 +W3 | AB3: =AVERAGE(AA3:AA9) | AC3: =AVERAGE(Y3:Y9) | AF3: =SUM(AE3:AE9) | AI3: 10 | AJ3: 1 | AL3: mocha | AM3: 345 | AN3: 12 | AO3: tea x 2 | AP3: 400 | AQ3: 6 | AR3: burrito | AS3: 700 | AT3: 52 | AU3: chicken + kimchee balls | AV3: 600 | BH3: 193.1 | BI3: • Tea has less caffeine than the coffee, and that's something I can consider for the future. • So important to have the right things in front of me • definitely better to be home than to be travelling. • The battle lines right now are around leafy greens. | BJ3: #VALUE! | BK3: • 21 leafy greens • 4 HIIT workouts
B4: =B5-1 | C4: F | D4: =SUM(T4,AA4) | E4: 1 | F4: 1 | G4: 0 | H4: 3 | I4: 3 | J4: 2 | K4: 1 | L4: 3 | M4: 0 | N4: 1 | O4: 2 | P4: =SUM(AN4,AQ4,AT4,AW4,AZ4,BC4,BF4) | R4: 0 | T4: 20 | U4: 1545 | W4: -35 | X4: =AA4-W4 | Y4: ='0₦'!AE4*2 + 0 | AA4: =SUM(E4:O4)/21*75 + IF(AM4, -(MAX((U4-1800)/10, -40)), 0)+T4 + S4 + (P4-100)*0.5+AI4 +W4 | AI4: 10 | AJ4: 1 | AL4: mocha | AM4: 345 | AN4: 12 | AO4: chicken, yoghurt, chinese | AP4: 400 | AQ4: 52 | AR4: tea | AS4: 200 | AT4: 5 | AU4: chicken + fries | AV4: 600 | AW4: 40 | BM4: =SUM(BN4:BO10) | BN4: =COUNTIF('0₦'!L3:L9,"<>")*23 | BO4: =41+340 | BP4: • The presentation was memorable. I could have given it one additional time in order to really nail it. • I should aim to give the talk more over time. • Overwore the sweater, need to get more GH Swag. • The second monitor was a statement. I didn't expect it to be but here we are. I don't care, I'm going to use it.
B5: =B6-1 | C5: S | D5: =SUM(T5,AA5) | E5: 2 | F5: 1 | G5: 1 | H5: 1 | I5: 1 | J5: 1 | K5: 5 | L5: 0 | M5: 0 | N5: 1 | O5: 2 | P5: =SUM(AN5,AQ5,AT5,AW5,AZ5,BC5,BF5) | R5: 0 | T5: 20 | U5: 1994 | W5: -35 | X5: =AA5-W5 | Y5: 2 | AA5: =SUM(E5:O5)/21*75 + IF(AM5, -(MAX((U5-1800)/10, -40)), 0)+T5 + S5 + (P5-100)*0.5+AI5 +W5 | AI5: 10 | AJ5: 1 | AL5: mocha | AM5: 345 | AN5: 12 | AO5: flax x 5 | AP5: 150 | AQ5: 5 | AR5: 1/4 beef sando, scone, tea, fruit | AS5: =400+75+50+74 | AT5: 12 | AU5: tea | AV5: 200 | AW5: 5 | AX5: 2 bao，green beans | AY5: 700 | AZ5: 35
A6: 1.1 | B6: 46026 | C6: S | D6: =SUM(T6,AA6) | E6: 2 | F6: 1 | G6: 0 | H6: 3 | I6: 2 | J6: 3 | K6: 2 | L6: 3 | M6: 4 | N6: 1 | O6: 2 | P6: =SUM(AN6,AQ6,AT6,AZ6,BC6,BF6,AW6) | R6: 0 | T6: 20 | U6: =SUM(AM6,AP6,AS6,AV6,AY6,BE6,BB6) | W6: -35 | X6: =AA6-W6 | Y6: ='0₦'!AE5*2 + 10 | AA6: =SUM(E6:O6)/21*75 + IF(AM6, -(MAX((U6-1800)/10, -40)), 0)+T6 + S6 + (P6-100)*0.5+AI6 +W6 | AI6: 10 | AJ6: 1 | AL6: pistachios + milk | AM6: 150 | AN6: 6 | AO6: 2 bao + cashew | AP6: 300 | AQ6: 15 | AR6: mocha340 | AS6: 340 | AT6: 12 | AU6: double chicken TLC burrito | AV6: 700 | AW6: 70 | AX6: tea + flax | AY6: =150+30 | AZ6: 7 | BA6: pistachios + flax | BB6: 90 | BC6: 6 | BD6: bao + brocolli + 辣椒 | BE6: 210 | BF6: 5
B7: =B6+1 | C7: M | D7: =SUM(T7,AA7) | E7: 2 | F7: 1 | G7: 2 | H7: 2 | I7: 2 | J7: 2 | K7: 3 | L7: 0 | M7: 1 | N7: 1 | O7: 2 | P7: =SUM(AN7,AQ7,AT7,AZ7,BC7,BF7,AW7) | R7: 0 | T7: 20 | U7: =SUM(AM7,AP7,AS7,AV7,AY7,BE7,BB7) | W7: -35 | X7: =AA7-W7 | Y7: ='0₦'!AE6*2 + 0 | AA7: =SUM(E7:O7)/21*75 + IF(AM7, -(MAX((U7-1800)/10, -40)), 0)+T7 + S7 + (P7-100)*0.5+AI7 +W7 | AI7: 10 | AJ7: 1 | AL7: mocha | AM7: 340 | AN7: 12 | AO7: berries + flax | AP7: 60 | AQ7: 2 | AR7: salad + berries | AS7: 380 | AT7: 32 | AU7: asha tea | AV7: 300 | AW7: 6 | AX7: nuts + flax + cheese | AY7: 130 | AZ7: 6 | BA7: 1/2 tlc burrito bowl | BB7: 200 | BC7: 30 | BD7: 2nd half tlc + chocolate | BE7: 450 | BF7: 36
B8: =B7+1 | C8: T | D8: =SUM(T8,AA8) | E8: 1 | F8: 1 | G8: 2 | H8: 2 | I8: 3 | J8: 1 | K8: 0 | L8: 1 | M8: 0 | N8: 1 | O8: 2 | P8: =SUM(AN8,AQ8,AT8,AZ8,BC8,BF8,AW8) | R8: 0 | T8: 20 | U8: =SUM(AM8,AP8,AS8,AV8,AY8,BE8,BB8) | W8: -70 | X8: =AA8-W8 | Y8: ='0₦'!AE7*2 + 0 | AA8: =SUM(E8:O8)/21*75 + IF(AM8, -(MAX((U8-1800)/10, -40)), 0)+T8 + S8 + (P8-100)*0.5+AI8 +W8 | AI8: 10 | AJ8: 1 | AL8: mocha | AM8: 390 | AN8: 9 | AO8: salad w/berries + blueberries + huevos rancheros | AP8: =250+200+50 | AQ8: =12+25 | AR8: coffee | AS8: 50 | AT8: 3 | AU8: meat + kale | AV8: 100 | AW8: 12 | AX8: mocha | AY8: 240 | AZ8: 6 | BA8: cafe juanita | BB8: 700 | BC8: 20
B9: =B8+1 | C9: W | D9: =SUM(T9,AA9) | E9: 3 | F9: 1 | G9: 2 | H9: 1 | I9: 2 | J9: 3 | K9: 0 | L9: 0 | M9: 3 | N9: 2 | O9: 2 | P9: =SUM(AN9,AQ9,AT9,AZ9,BC9,BF9,AW9) | R9: 0 | T9: 20 | U9: =SUM(AM9,AP9,AS9,AV9,AY9,BE9,BB9) | W9: -70 | X9: =AA9-W9 | Y9: ='0₦'!AE8*2 + 0 | AA9: =SUM(E9:O9)/21*75 + IF(AM9, -(MAX((U9-1800)/10, -40)), 0)+T9 + S9 + (P9-100)*0.5+AI9 +W9 | AI9: 10 | AJ9: 1 | AL9: mocha | AM9: 390 | AN9: 13 | AO9: berries, fruit sausage | AP9: 250 | AQ9: 15 | AR9: vegetables + 4 oz salmon | AS9: 25 | AT9: 24 | AU9: popcorn + vegetables | AV9: 250 | AW9: 5 | AX9: 水煮牛，豆苗，啤酒 | AY9: 700 | AZ9: 25 | BA9: nuts x 2 | BB9: 160 | BC9: 8
B10: =B9+1 | C10: Th | D10: =SUM(T10,AA10) | E10: 0 | F10: 1 | G10: 2 | H10: 1 | I10: 1 | J10: 1 | K10: 1 | L10: 0 | M10: 1 | N10: 1 | O10: 2 | P10: =SUM(AN10,AQ10,AT10,AZ10,BC10,BF10,AW10) | R10: 0 | T10: 20 | U10: =SUM(AM10,AP10,AS10,AV10,AY10,BE10,BB10) | V10: =AVERAGE(U10:U16) | W10: 105 | X10: =AA10-W10 | Y10: ='0₦'!AE9*2 + 0 | AA10: =SUM(E10:O10)/21*75 + IF(AM10, -(MAX((U10-1800)/10, -40)), 0)+T10 + S10 + (P10-100)*0.5+AI10 +W10 | AB10: =AVERAGE(AA10:AA16) | AC10: =AVERAGE(Y10:Y16) | AF10: =SUM(AE10:AE16) | AI10: 10 | AJ10: 1 | AL10: mocha | AM10: 390 | AN10: 12 | AO10: breakfast sandwich | AP10: 350 | AQ10: 15 | AR10: poke bowl w/2 piece unagi + latte | AS10: =480 | AT10: 48 | AU10: 2 things of decaf coffee | AV10: 100 | AW10: 4 | AX10: 2 chicken, 1 slider, wine, apricot, apples | AY10: =100+150+70+200 | AZ10: 35 | BH10: 194.2 | BI10: • I did two HIIT workouts, and owe myself another one, but how? • Still struggling to eat the greens on the plane. Nuts are an easy + good thing to bring though. | BJ10: #VALUE! | BK10: • 21 leafy greens • 4 HIIT workouts
B11: =B10+1 | C11: F | D11: =SUM(T11,AA11) | E11: 1 | F11: 1 | G11: 0 | H11: 2 | I11: 2 | J11: 1 | K11: 1 | L11: 1 | M11: 2 | N11: 1 | O11: 2 | P11: =SUM(AN11,AQ11,AT11,AZ11,BC11,BF11,AW11) | R11: 0 | T11: 20 | U11: =SUM(AM11,AP11,AS11,AV11,AY11,BE11,BB11) | W11: -70 | X11: =AA11-W11 | Y11: ='0₦'!AE10*2 + 0 | AA11: =SUM(E11:O11)/21*75 + IF(AM11, -(MAX((U11-1800)/10, -40)), 0)+T11 + S11 + (P11-100)*0.5+AI11 +W11 | AI11: 0 | AJ11: 3 | AL11: mocha | AM11: 390 | AN11: 12 | AO11: nuts + coffee | AP11: 110 | AQ11: 6 | AR11: medeterranian plate | AS11: 800 | AT11: 60 | AU11: mocha | AV11: 250 | AW11: 6 | AX11: nuts + berries | AY11: 150 | AZ11: 6 | BM11: =SUM(BN11:BO19) | BN11: =COUNTIF('0₦'!L10:L16,"<>")*23 - 15 | BO11: 131 | BP11: • I should view SLT as a little bit more of a show, and plan accordingly. That includes the way that I dress. • Last week's post was pretty good, but what am I going to write for February? • The offsite is also a chance to hone image.
B12: =B11+1 | C12: S | D12: =SUM(T12,AA12) | E12: 3 | F12: 1 | G12: 1 | H12: 0 | I12: 4 | J12: 3 | K12: 3 | L12: 1 | M12: 1 | N12: 1 | O12: 2 | P12: =SUM(AN12,AQ12,AT12,AZ12,BC12,BF12,AW12) | R12: 0 | T12: 20 | U12: =SUM(AM12,AP12,AS12,AV12,AY12,BE12,BB12) | W12: 70 | X12: =AA12-W12 | Y12: ='0₦'!AE11*2 + 35 | AA12: =SUM(E12:O12)/21*75 + IF(AM12, -(MAX((U12-1800)/10, -40)), 0)+T12 + S12 + (P12-100)*0.5+AI12 +W12 | AE12: 0.3 | AI12: 10 | AJ12: 1 | AL12: mocha | AM12: 390 | AN12: 12 | AO12: 3 cheese almonds, breakd | AP12: =300 | AQ12: 11 | AR12: flax + apple + berries | AS12: =30+50+30 | AT12: =2+1 | AU12: spinach | AV12: 35 | AW12: 5 | AX12: beans + eggn + hummus + falafel + muhammarah + labneh + songbing + potato cake + cabbage | AY12: =50+600 | AZ12: 25 | BA12: tea | BB12: 200 | BC12: 6 | BD12: 2 flax+ dumpling + tofu + peppers | BE12: =150+30+60 | BF12: 15
A13: =A6+0.1 | B13: =B12+1 | C13: S | D13: =SUM(T13,AA13) | E13: 4 | F13: 1 | G13: 0 | H13: 0 | I13: 1 | J13: 3 | K13: 3 | L13: 3 | M13: 2 | N13: 1 | O13: 2 | P13: =SUM(AN13,AQ13,AT13,AZ13,BC13,BF13,AW13) | R13: 0 | T13: 20 | U13: =SUM(AM13,AP13,AS13,AV13,AY13,BE13,BB13) | W13: 70 | X13: =AA13-W13 | Y13: ='0₦'!AE12*2 + 53 | AA13: =SUM(E13:O13)/21*75 + IF(AM13, -(MAX((U13-1800)/10, -40)), 0)+T13 + S13 + (P13-100)*0.5+AI13 +W13 | AE13: 1 | AI13: 10 | AJ13: 1 | AL13: mocha | AM13: 340 | AN13: 12 | AO13: 3 cheese, almonds + milk, 5 dumplings | AP13: =150+150+90 | AQ13: =10+6+5 | AR13: tuna sandwich | AS13: 480 | AT13: 35 | AU13: tea | AV13: 200 | AW13: 6 | AX13: 3 bao, cucumbers, tofu, almonds + milk | AY13: =300+50+150 | AZ13: 18 | BA13: carrots + hummus | BB13: 130 | BC13: 8
B14: =B13+1 | C14: M | D14: =SUM(T14,AA14) | E14: 2 | F14: 1 | G14: 0 | H14: 0 | I14: 0 | J14: 2 | K14: 2 | L14: 3 | M14: 1 | N14: 2 | O14: 2 | P14: =SUM(AN14,AQ14,AT14,AZ14,BC14,BF14,AW14) | R14: 0 | T14: 20 | U14: =SUM(AM14,AP14,AS14,AV14,AY14,BE14,BB14) | W14: 15 | X14: =AA14-W14 | Y14: ='0₦'!AE13*2 + 53 | AA14: =SUM(E14:O14)/21*75 + IF(AM14, -(MAX((U14-1800)/10, -40)), 0)+T14 + S14 + (P14-100)*0.5+AI14 +W14 | AE14: 1 | AI14: 10 | AJ14: 1 | AL14: mocha | AM14: 340 | AN14: 12 | AO14: huevos rancheros | AP14: 1000 | AQ14: 50 | AR14: tea x 2 | AS14: 400 | AT14: 11 | AU14: chicken + flax | AV14: 360 | AW14: 49 | AX14: chocolate | AY14: 100 | AZ14: 4
B15: =B14+1 | C15: T | D15: =SUM(T15,AA15) | E15: 3 | F15: 0 | G15: 0 | H15: 1 | I15: 1 | J15: 2 | K15: 2 | L15: 0 | M15: 0 | N15: 1 | O15: 2 | P15: =SUM(AN15,AQ15,AT15,AZ15,BC15,BF15,AW15) | R15: 0 | T15: 20 | U15: =SUM(AM15,AP15,AS15,AV15,AY15,BE15,BB15) | W15: 0 | X15: =AA15-W15 | Y15: ='0₦'!AE14*2 + 10 | AA15: =SUM(E15:O15)/21*75 + IF(AM15, -(MAX((U15-1800)/10, -40)), 0)+T15 + S15 + (P15-100)*0.5+AI15 +W15 | AI15: 10 | AJ15: 1 | AL15: mocha | AM15: 340 | AN15: 12 | AO15: chicken + yoghurt + falx | AP15: 300 | AQ15: 46 | AR15: 5 dumplings, beans cucuumbers | AS15: =150+80+10 | AT15: 10 | AU15: tea | AV15: 300 | AW15: 6 | AX15: mocha | AY15: 290 | AZ15: 6 | BA15: 4 饺子 tofu, beans cheese | BB15: =120+100+90
B16: =B15+1 | C16: W | D16: =SUM(T16,AA16) | E16: 0 | F16: 0 | G16: 0 | H16: 1 | I16: 2 | J16: 1 | K16: 1 | L16: 2 | M16: 2 | N16: 1 | O16: 2 | P16: =SUM(AN16,AQ16,AT16,AZ16,BC16,BF16,AW16) | R16: 0 | T16: 20 | U16: =SUM(AM16,AP16,AS16,AV16,AY16,BE16,BB16) | W16: 0 | X16: =AA16-W16 | Y16: ='0₦'!AE15*2 + 10 | AA16: =SUM(E16:O16)/21*75 + IF(AM16, -(MAX((U16-1800)/10, -40)), 0)+T16 + S16 + (P16-100)*0.5+AI16 +W16 | AI16: 10 | AJ16: 1 | AL16: mocha | AM16: 340 | AN16: 12 | AO16: 6 cheese, almonds | AP16: =180+150 | AQ16: =12+12 | AR16: 2 tacos + tea | AS16: 600 | AT16: =25+6 | AU16: mocha | AV16: 390 | AW16: 12 | AX16: 3 handrolls, salmon, cookies | AY16: 700 | AZ16: 65
B17: =B16+1 | C17: Th | D17: =SUM(T17,AA17) | E17: 0 | F17: 4 | G17: 1 | H17: 0 | I17: 1 | J17: 2 | K17: 0 | L17: 0 | M17: 4 | N17: 1 | O17: 2 | P17: =SUM(AN17,AQ17,AT17,AZ17,BC17,BF17,AW17) | R17: 0 | T17: 20 | U17: =SUM(AM17,AP17,AS17,AV17,AY17,BE17,BB17) | V17: =AVERAGE(U17:U23) | W17: 70 | X17: =AA17-W17 | Y17: ='0₦'!AE16*2 + 0 | AA17: =SUM(E17:O17)/21*75 + IF(AM17, -(MAX((U17-1800)/10, -40)), 0)+T17 + S17 + (P17-100)*0.5+AI17 +W17 | AB17: =AVERAGE(AA17:AA23) | AC17: =AVERAGE(Y17:Y23) | AF17: =SUM(AE17:AE23) | AI17: 10 | AJ17: 1 | AL17: mocha | AM17: 290 | AN17: 6 | AO17: havarti sandwich | AP17: 400 | AQ17: 15 | AR17: mocha | AS17: 290 | AT17: 6 | AU17: maotai with eggs, beef, pork, mushrooms, cabbage, ou | AV17: 600 | AW17: 30 | AX17: noodles + pb Cups + blueberries + nuts | AY17: =100+250+200 + 200 | AZ17: 25 | BH17: 194 | BI17: • Did HIIT in the hotel today, with plans for another which is good. • If I keep buying greens in tins and eating them as a snack, I'll be good to go. • I think a good piece of fruit + Chai tea + milk is probably better than the mocha that I'm doing. But I've got to get to that level first. The next challenge is wvegetables. | BK17: • Battleline at vegetables • 4 HIIT workouts
B18: =B17+1 | C18: F | D18: =SUM(T18,AA18) | E18: 2 | F18: 0 | G18: 0 | H18: 5 | I18: 5 | J18: 1 | K18: 0 | L18: 0 | M18: 1 | N18: 1 | O18: 2 | P18: =SUM(AN18,AQ18,AT18,AZ18,BC18,BF18,AW18) | R18: 0 | T18: 20 | U18: =SUM(AM18,AP18,AS18,AV18,AY18,BE18,BB18) | W18: -70 | X18: =AA18-W18 | Y18: ='0₦'!AE17*2 + 0 | AA18: =SUM(E18:O18)/21*75 + IF(AM18, -(MAX((U18-1800)/10, -40)), 0)+T18 + S18 + (P18-100)*0.5+AI18 +W18 | AI18: 0 | AJ18: 3 | AL18: mocha | AM18: 390 | AN18: 12 | AO18: salad lamb, chicken, hummus etc. | AP18: 800 | AQ18: 50 | AR18: mocha | AS18: 290 | AT18: 9 | AU18: mocha | AV18: 290 | AW18: 6 | AX18: kale + pistachios | AY18: 85 | AZ18: 7 | BM18: =SUM(BN18:BO27) | BN18: =COUNTIF('0₦'!L17:L23,"<>")*23 | BO18: 22 | BP18: • Got showers in this week, but I didn't enjoy them as much as I could have. • Forgetting floss was annoying. • Still lacking on pictures which is something that I should do, and I should pair that with the music.
B19: =B18+1 | C19: S | D19: =SUM(T19,AA19) | E19: 0 | F19: 0 | G19: 0 | H19: 2 | I19: 4 | J19: 1 | K19: 1 | L19: 0 | M19: 2 | N19: 1 | O19: 2 | P19: =SUM(AN19,AQ19,AT19,AZ19,BC19,BF19,AW19) | R19: 0 | T19: 20 | U19: =SUM(AM19,AP19,AS19,AV19,AY19,BE19,BB19) | W19: 70 | X19: =AA19-W19 | Y19: ='0₦'!AE18*2 + 20 | AA19: =SUM(E19:O19)/21*75 + IF(AM19, -(MAX((U19-1800)/10, -40)), 0)+T19 + S19 + (P19-100)*0.5+AI19 +W19 | AE19: 1 | AI19: 10 | AJ19: 1 | AL19: mocha | AM19: 340 | AN19: 12 | AO19: cheese + almonds | AP19: 210 | AQ19: 15 | AR19: 2 bao | AS19: 200 | AT19: 8 | AU19: noodles, shrimp x 2 + shrimp pcoket + greens | AV19: =200+200+50 | AW19: 25 | AX19: boba tea | AY19: 200 | AZ19: 6 | BA19: chicken + almonds + milk | BB19: =300+150 | BC19: =46+10
A20: =A13+0.1 | B20: =B19+1 | C20: S | D20: =SUM(T20,AA20) | E20: 0 | F20: 0 | G20: 1 | H20: 0 | I20: 4 | J20: 2 | K20: 1 | L20: 3 | M20: 2 | N20: 1 | O20: 2 | P20: 2 | R20: 0 | T20: 20 | U20: =SUM(AM20,AP20,AS20,AV20,AY20,BE20,BB20) | W20: 0 | X20: =AA20-W20 | Y20: ='0₦'!AE19*2 + 10 | AA20: =SUM(E20:O20)/21*75 + IF(AM20, -(MAX((U20-1800)/10, -40)), 0)+T20 + S20 + (P20-100)*0.5+AI20 +W20 | AI20: 10 | AJ20: 1 | AL20: mocha | AM20: 340 | AN20: 12 | AO20: 2 bao, spinach + spinach + chicken + yoghurt + flax + almonds + pistachios | AP20: =300+15+35+50+50 | AQ20: =5+5+5+10 | AR20: tea | AS20: 200 | AT20: 6 | AU20: 3 slice pizza carrots baba ganoush | AV20: =600+100 | AW20: 30 | AX20: tea | AY20: 100 | AZ20: 3
B21: =B20+1 | C21: M | D21: =SUM(T21,AA21) | E21: 0 | F21: 0 | G21: 1 | H21: 1 | I21: 1 | J21: 2 | K21: 1 | L21: 1 | M21: 0 | N21: 1 | O21: 2 | P21: =SUM(AN21,AQ21,AT21,AZ21,BC21,BF21,AW21) | R21: 10 | T21: 20 | U21: =SUM(AM21,AP21,AS21,AV21,AY21,BE21,BB21) | W21: 0 | X21: =AA21-W21 | Y21: ='0₦'!AE20*2 + 10 + 35 + 15 | AA21: =SUM(E21:O21)/21*75 + IF(AM21, -(MAX((U21-1800)/10, -40)), 0)+T21 + S21 + (P21-100)*0.5+AI21 +W21 | AI21: 10 | AJ21: 1 | AL21: mocha | AM21: 340 | AN21: 12 | AO21: 1 slice pizza | AP21: 200 | AQ21: 10 | AR21: larb gai | AS21: 200 | AT21: 25 | AU21: asha tea | AV21: 300 | AW21: 15 | AX21: chicken + cheese + potatoes + wine + cake | AY21: 800 | AZ21: 20
B22: =B21+1 | C22: T | D22: =SUM(T22,AA22) | E22: 0 | F22: 5 | G22: 0 | H22: 1 | I22: 4 | J22: 4 | K22: 3 | L22: 0 | M22: 0 | N22: 1 | O22: 2 | P22: =SUM(AN22,AQ22,AT22,AZ22,BC22,BF22,AW22) | R22: 0 | T22: 20 | U22: =SUM(AM22,AP22,AS22,AV22,AY22,BE22,BB22) | W22: -70 | X22: =AA22-W22 | Y22: ='0₦'!AE21*2 + 5 + 10 | AA22: =SUM(E22:O22)/21*75 + IF(AM22, -(MAX((U22-1800)/10, -40)), 0)+T22 + S22 + (P22-100)*0.5+AI22 +W22 | AI22: 10 | AJ22: 1 | AL22: mocha | AM22: 340 | AN22: 12 | AO22: flax + berries | AP22: 60 | AQ22: 2 | AR22: salad + flax + carrots + baba ganoush | AS22: =70+30+75+100 | AT22: =5 | AU22: tea | AV22: 200 | AW22: 5 | AX22: spinach | AY22: 35 | AZ22: 5 | BA22: chicken + yoghurt + flax | BB22: =330 | BC22: =15+30+2 | BD22: mocha + jerkey | BE22: =290+220 | BF22: =6+26
B23: =B22+1 | C23: W | D23: =SUM(T23,AA23) | E23: 1 | F23: 0 | G23: 2 | H23: 0 | I23: 1 | J23: 3 | K23: 0 | L23: 2 | M23: 0 | N23: 1 | O23: 2 | P23: =SUM(AN23,AQ23,AT23,AZ23,BC23,BF23,AW23) | R23: 0 | T23: 20 | U23: =SUM(AM23,AP23,AS23,AV23,AY23,BE23,BB23) | W23: 70 | X23: =AA23-W23 | Y23: ='0₦'!AE22*2 + 0 | AA23: =SUM(E23:O23)/21*75 + IF(AM23, -(MAX((U23-1800)/10, -40)), 0)+T23 + S23 + (P23-100)*0.5+AI23 +W23 | AI23: 10 | AJ23: 1 | AL23: mocha | AM23: 290 | AN23: 9 | AO23: spinach, potates, orange juice, bacon, sausage | AP23: =140+100+100+10+120+100 | AQ23: =5*2+3*4+2+1 | AR23: 2 tacos + tots | AS23: 500 | AT23: 25 | AU23: pizza + beer | AV23: 800 | AW23: 30
B24: =B23+1 | C24: Th | D24: =SUM(T24,AA24) | E24: 2 | F24: 0 | G24: 0 | H24: 4 | I24: 4 | J24: 4 | K24: 0 | L24: 0 | M24: 1 | N24: 0 | O24: 2 | P24: =SUM(AN24,AQ24,AT24,AZ24,BC24,BF24,AW24) | R24: 0 | T24: 20 | U24: =SUM(AM24,AP24,AS24,AV24,AY24,BE24,BB24) | V24: =AVERAGE(U24:U30) | W24: 35 | X24: =AA24-W24 | Y24: ='0₦'!AE23*2 + 0 | AA24: =SUM(E24:O24)/21*75 + IF(AM24, -(MAX((U24-1800)/10, -40)), 0)+T24 + S24 + (P24-100)*0.5+AI24 +W24 | AB24: =AVERAGE(AA24:AA30) | AC24: =AVERAGE(Y24:Y30) | AE24: 1 | AF24: =SUM(AE24:AE30) | AI24: 10 | AJ24: 1 | AL24: mocha | AM24: 390 | AN24: 12 | AO24: mocha | AP24: 290 | AQ24: 9 | AR24: cheese things | AS24: 200 | AT24: 18 | AU24: mocha | AV24: 290 | AW24: 9 | AX24: salad | AY24: 500 | AZ24: 40 | BA24: vietnamese bef | BB24: 300 | BC24: 30
B25: =B24+1 | C25: F | D25: =SUM(T25,AA25) | E25: 1 | F25: 2 | G25: 0 | H25: 2 | I25: 2 | J25: 2 | K25: 0 | L25: 0 | M25: 0 | N25: 1 | O25: 2 | P25: =SUM(AN25,AQ25,AT25,AZ25,BC25,BF25,AW25) | R25: 0 | T25: 20 | U25: =SUM(AM25,AP25,AS25,AV25,AY25,BE25,BB25) | W25: -70 | X25: =AA25-W25 | Y25: ='0₦'!AE24*2 + 0 | AA25: =SUM(E25:O25)/21*75 + IF(AM25, -(MAX((U25-1800)/10, -40)), 0)+T25 + S25 + (P25-100)*0.5+AI25 +W25 | AI25: 10 | AJ25: 1 | AL25: mocha | AM25: 390 | AN25: 12 | AO25: berries x 2 + fruit smoothie + potatoes + beans | AP25: =60+100+50+30 | AQ25: 8 | AR25: kebab + salad + tomateos + hummus | AS25: =300+100+30+80 | AT25: 35 | AU25: mocha | AV25: 290 | AW25: 9 | AX25: burgur + cheese | AY25: 700 | AZ25: 30 | BM25: =SUM(BN25:BO35) | BN25: =COUNTIF('0₦'!L25:L31,"<>")*23 | BO25: 0
B26: =B25+1 | C26: S | D26: =SUM(T26,AA26) | L26: 0 | P26: =SUM(AN26,AQ26,AT26,AZ26,BC26,BF26,AW26) | U26: =SUM(AM26,AP26,AS26,AV26,AY26,BE26,BB26) | X26: =AA26-W26 | Y26: ='0₦'!AE25*2 + 0 | AA26: =SUM(E26:O26)/21*75 + IF(AM26, -(MAX((U26-1800)/10, -40)), 0)+T26 + S26 + (P26-100)*0.5+AI26 +W26
A27: =A20+0.1 | B27: =B26+1 | C27: S | D27: =SUM(T27,AA27) | L27: 0 | P27: =SUM(AN27,AQ27,AT27,AZ27,BC27,BF27,AW27) | U27: =SUM(AM27,AP27,AS27,AV27,AY27,BE27,BB27) | X27: =AA27-W27 | Y27: ='0₦'!AE26*2 + 0 | AA27: =SUM(E27:O27)/21*75 + IF(AM27, -(MAX((U27-1800)/10, -40)), 0)+T27 + S27 + (P27-100)*0.5+AI27 +W27
B28: =B27+1 | C28: M | D28: =SUM(T28,AA28) | L28: 0 | P28: =SUM(AN28,AQ28,AT28,AZ28,BC28,BF28,AW28) | U28: =SUM(AM28,AP28,AS28,AV28,AY28,BE28,BB28) | X28: =AA28-W28 | Y28: ='0₦'!AE27*2 + 0 | AA28: =SUM(E28:O28)/21*75 + IF(AM28, -(MAX((U28-1800)/10, -40)), 0)+T28 + S28 + (P28-100)*0.5+AI28 +W28
B29: =B28+1 | C29: T | D29: =SUM(T29,AA29) | L29: 0 | P29: =SUM(AN29,AQ29,AT29,AZ29,BC29,BF29,AW29) | U29: =SUM(AM29,AP29,AS29,AV29,AY29,BE29,BB29) | X29: =AA29-W29 | Y29: ='0₦'!AE28*2 + 0 | AA29: =SUM(E29:O29)/21*75 + IF(AM29, -(MAX((U29-1800)/10, -40)), 0)+T29 + S29 + (P29-100)*0.5+AI29 +W29
B30: =B29+1 | C30: W | D30: =SUM(T30,AA30) | L30: 0 | P30: =SUM(AN30,AQ30,AT30,AZ30,BC30,BF30,AW30) | U30: =SUM(AM30,AP30,AS30,AV30,AY30,BE30,BB30) | X30: =AA30-W30 | Y30: ='0₦'!AE29*2 + 0 | AA30: =SUM(E30:O30)/21*75 + IF(AM30, -(MAX((U30-1800)/10, -40)), 0)+T30 + S30 + (P30-100)*0.5+AI30 +W30
B31: =B30+1 | C31: Th | D31: =SUM(T31,AA31) | L31: 0 | P31: =SUM(AN31,AQ31,AT31,AZ31,BC31,BF31,AW31) | U31: =SUM(AM31,AP31,AS31,AV31,AY31,BE31,BB31) | V31: =AVERAGE(U31:U37) | X31: =AA31-W31 | Y31: ='0₦'!AE30*2 + 0 | AA31: =SUM(E31:O31)/21*75 + IF(AM31, -(MAX((U31-1800)/10, -40)), 0)+T31 + S31 + (P31-100)*0.5+AI31 +W31 | AB31: =AVERAGE(AA31:AA37) | AC31: =AVERAGE(Y31:Y37) | AF31: =SUM(AE31:AE37)
B32: =B31+1 | C32: F | D32: =SUM(T32,AA32) | L32: 0 | P32: =SUM(AN32,AQ32,AT32,AZ32,BC32,BF32,AW32) | U32: =SUM(AM32,AP32,AS32,AV32,AY32,BE32,BB32) | X32: =AA32-W32 | Y32: ='0₦'!AE31*2 + 0 | AA32: =SUM(E32:O32)/21*75 + IF(AM32, -(MAX((U32-1800)/10, -40)), 0)+T32 + S32 + (P32-100)*0.5+AI32 +W32 | BM32: =SUM(BN32:BO42) | BN32: =COUNTIF('0₦'!L32:L38,"<>")*23 | BO32: 0
B33: =B32+1 | C33: S | D33: =SUM(T33,AA33) | L33: 0 | P33: =SUM(AN33,AQ33,AT33,AZ33,BC33,BF33,AW33) | U33: =SUM(AM33,AP33,AS33,AV33,AY33,BE33,BB33) | X33: =AA33-W33 | Y33: ='0₦'!AE32*2 + 0 | AA33: =SUM(E33:O33)/21*75 + IF(AM33, -(MAX((U33-1800)/10, -40)), 0)+T33 + S33 + (P33-100)*0.5+AI33 +W33
A34: =A6+1 | B34: =B33+1 | C34: S | D34: =SUM(T34,AA34) | U34: =SUM(AM34,AP34,AS34,AV34,AY34,BE34,BB34) | X34: =AA34-W34 | Y34: ='0₦'!AE33*2 + 0 | AA34: =SUM(E34:O34)/21*75 + IF(AM34, -(MAX((U34-1800)/10, -40)), 0)+T34 + S34 + (P34-100)*0.5+AI34 +W34
B35: =B34+1 | C35: M | D35: =SUM(T35,AA35) | U35: =SUM(AM35,AP35,AS35,AV35,AY35,BE35,BB35) | X35: =AA35-W35 | Y35: ='0₦'!AE34*2 + 0 | AA35: =SUM(E35:O35)/21*75 + IF(AM35, -(MAX((U35-1800)/10, -40)), 0)+T35 + S35 + (P35-100)*0.5+AI35 +W35
B36: =B35+1 | C36: T | D36: =SUM(T36,AA36) | U36: =SUM(AM36,AP36,AS36,AV36,AY36,BE36,BB36) | X36: =AA36-W36 | Y36: ='0₦'!AE35*2 + 0 | AA36: =SUM(E36:O36)/21*75 + IF(AM36, -(MAX((U36-1800)/10, -40)), 0)+T36 + S36 + (P36-100)*0.5+AI36 +W36
B37: =B36+1 | C37: W | D37: =SUM(T37,AA37) | U37: =SUM(AM37,AP37,AS37,AV37,AY37,BE37,BB37) | X37: =AA37-W37 | Y37: ='0₦'!AE36*2 + 0 | AA37: =SUM(E37:O37)/21*75 + IF(AM37, -(MAX((U37-1800)/10, -40)), 0)+T37 + S37 + (P37-100)*0.5+AI37 +W37
B38: =B37+1 | C38: Th | D38: =SUM(T38,AA38) | U38: =SUM(AM38,AP38,AS38,AV38,AY38,BE38,BB38) | V38: =AVERAGE(U38:U44) | X38: =AA38-W38 | Y38: ='0₦'!AE37*2 + 0 | AA38: =SUM(E38:O38)/21*75 + IF(AM38, -(MAX((U38-1800)/10, -40)), 0)+T38 + S38 + (P38-100)*0.5+AI38 +W38 | AB38: =AVERAGE(AA38:AA44) | AC38: =AVERAGE(Y38:Y44) | AF38: =SUM(AE38:AE44)
B39: =B38+1 | C39: F | D39: =SUM(T39,AA39) | U39: =SUM(AM39,AP39,AS39,AV39,AY39,BE39,BB39) | X39: =AA39-W39 | Y39: ='0₦'!AE38*2 + 0 | AA39: =SUM(E39:O39)/21*75 + IF(AM39, -(MAX((U39-1800)/10, -40)), 0)+T39 + S39 + (P39-100)*0.5+AI39 +W39 | BM39: =SUM(BN39:BO45) | BN39: =COUNTIF('0₦'!L39:L45,"<>")*23 | BO39: 0
B40: =B39+1 | C40: S | D40: =SUM(T40,AA40) | U40: =SUM(AM40,AP40,AS40,AV40,AY40,BE40,BB40) | X40: =AA40-W40 | Y40: ='0₦'!AE39*2 + 0 | AA40: =SUM(E40:O40)/21*75 + IF(AM40, -(MAX((U40-1800)/10, -40)), 0)+T40 + S40 + (P40-100)*0.5+AI40 +W40
A41: =A34+0.1 | B41: =B40+1 | C41: S | D41: =SUM(T41,AA41) | U41: =SUM(AM41,AP41,AS41,AV41,AY41,BE41,BB41) | X41: =AA41-W41 | Y41: ='0₦'!AE40*2 + 0 | AA41: =SUM(E41:O41)/21*75 + IF(AM41, -(MAX((U41-1800)/10, -40)), 0)+T41 + S41 + (P41-100)*0.5+AI41 +W41
B42: =B41+1 | C42: M | D42: =SUM(T42,AA42) | U42: =SUM(AM42,AP42,AS42,AV42,AY42,BE42,BB42) | X42: =AA42-W42 | Y42: ='0₦'!AE41*2 + 0 | AA42: =SUM(E42:O42)/21*75 + IF(AM42, -(MAX((U42-1800)/10, -40)), 0)+T42 + S42 + (P42-100)*0.5+AI42 +W42
B43: =B42+1 | C43: T | D43: =SUM(T43,AA43) | U43: =SUM(AM43,AP43,AS43,AV43,AY43,BE43,BB43) | X43: =AA43-W43 | Y43: ='0₦'!AE42*2 + 0 | AA43: =SUM(E43:O43)/21*75 + IF(AM43, -(MAX((U43-1800)/10, -40)), 0)+T43 + S43 + (P43-100)*0.5+AI43 +W43
B44: =B43+1 | C44: W | D44: =SUM(T44,AA44) | U44: =SUM(AM44,AP44,AS44,AV44,AY44,BE44,BB44) | X44: =AA44-W44 | Y44: ='0₦'!AE43*2 + 0 | AA44: =SUM(E44:O44)/21*75 + IF(AM44, -(MAX((U44-1800)/10, -40)), 0)+T44 + S44 + (P44-100)*0.5+AI44 +W44
B45: =B44+1 | C45: Th | D45: =SUM(T45,AA45) | U45: =SUM(AM45,AP45,AS45,AV45,AY45,BE45,BB45) | V45: =AVERAGE(U45:U51) | X45: =AA45-W45 | Y45: ='0₦'!AE44*2 + 0 | AA45: =SUM(E45:O45)/21*75 + IF(AM45, -(MAX((U45-1800)/10, -40)), 0)+T45 + S45 + (P45-100)*0.5+AI45 +W45 | AB45: =AVERAGE(AA45:AA51) | AC45: =AVERAGE(Y45:Y51) | AF45: =SUM(AE45:AE51)
B46: =B45+1 | C46: F | D46: =SUM(T46,AA46) | U46: =SUM(AM46,AP46,AS46,AV46,AY46,BE46,BB46) | X46: =AA46-W46 | Y46: ='0₦'!AE45*2 + 0 | AA46: =SUM(E46:O46)/21*75 + IF(AM46, -(MAX((U46-1800)/10, -40)), 0)+T46 + S46 + (P46-100)*0.5+AI46 +W46 | BM46: =SUM(BN46:BO52) | BN46: =COUNTIF('0₦'!L46:L52,"<>")*23 | BO46: 0
B47: =B46+1 | C47: S | D47: =SUM(T47,AA47) | U47: =SUM(AM47,AP47,AS47,AV47,AY47,BE47,BB47) | X47: =AA47-W47 | Y47: ='0₦'!AE46*2 + 0 | AA47: =SUM(E47:O47)/21*75 + IF(AM47, -(MAX((U47-1800)/10, -40)), 0)+T47 + S47 + (P47-100)*0.5+AI47 +W47
A48: =A41+0.1 | B48: =B47+1 | C48: S | D48: =SUM(T48,AA48) | U48: =SUM(AM48,AP48,AS48,AV48,AY48,BE48,BB48) | X48: =AA48-W48 | Y48: ='0₦'!AE47*2 + 0 | AA48: =SUM(E48:O48)/21*75 + IF(AM48, -(MAX((U48-1800)/10, -40)), 0)+T48 + S48 + (P48-100)*0.5+AI48 +W48
B49: =B48+1 | C49: M | D49: =SUM(T49,AA49) | U49: =SUM(AM49,AP49,AS49,AV49,AY49,BE49,BB49) | X49: =AA49-W49 | Y49: ='0₦'!AE48*2 + 0 | AA49: =SUM(E49:O49)/21*75 + IF(AM49, -(MAX((U49-1800)/10, -40)), 0)+T49 + S49 + (P49-100)*0.5+AI49 +W49
B50: =B49+1 | C50: T | D50: =SUM(T50,AA50) | U50: =SUM(AM50,AP50,AS50,AV50,AY50,BE50,BB50) | X50: =AA50-W50 | Y50: ='0₦'!AE49*2 + 0 | AA50: =SUM(E50:O50)/21*75 + IF(AM50, -(MAX((U50-1800)/10, -40)), 0)+T50 + S50 + (P50-100)*0.5+AI50 +W50
B51: =B50+1 | C51: W | D51: =SUM(T51,AA51) | U51: =SUM(AM51,AP51,AS51,AV51,AY51,BE51,BB51) | X51: =AA51-W51 | Y51: ='0₦'!AE50*2 + 0 | AA51: =SUM(E51:O51)/21*75 + IF(AM51, -(MAX((U51-1800)/10, -40)), 0)+T51 + S51 + (P51-100)*0.5+AI51 +W51
B52: =B51+1 | C52: Th | D52: =SUM(T52,AA52) | U52: =SUM(AM52,AP52,AS52,AV52,AY52,BE52,BB52) | V52: =AVERAGE(U52:U58) | X52: =AA52-W52 | Y52: ='0₦'!AE51*2 + 0 | AA52: =SUM(E52:O52)/21*75 + IF(AM52, -(MAX((U52-1800)/10, -40)), 0)+T52 + S52 + (P52-100)*0.5+AI52 +W52 | AB52: =AVERAGE(AA52:AA58) | AC52: =AVERAGE(Y52:Y58) | AF52: =SUM(AE52:AE58)
B53: =B52+1 | C53: F | D53: =SUM(T53,AA53) | U53: =SUM(AM53,AP53,AS53,AV53,AY53,BE53,BB53) | X53: =AA53-W53 | Y53: ='0₦'!AE52*2 + 0 | AA53: =SUM(E53:O53)/21*75 + IF(AM53, -(MAX((U53-1800)/10, -40)), 0)+T53 + S53 + (P53-100)*0.5+AI53 +W53 | BM53: =SUM(BN53:BO59) | BN53: =COUNTIF('0₦'!L53:L59,"<>")*23 | BO53: 0
B54: =B53+1 | C54: S | D54: =SUM(T54,AA54) | U54: =SUM(AM54,AP54,AS54,AV54,AY54,BE54,BB54) | X54: =AA54-W54 | Y54: ='0₦'!AE53*2 + 0 | AA54: =SUM(E54:O54)/21*75 + IF(AM54, -(MAX((U54-1800)/10, -40)), 0)+T54 + S54 + (P54-100)*0.5+AI54 +W54
A55: =A48+0.1 | B55: =B54+1 | C55: S | D55: =SUM(T55,AA55) | U55: =SUM(AM55,AP55,AS55,AV55,AY55,BE55,BB55) | X55: =AA55-W55 | Y55: ='0₦'!AE54*2 + 0 | AA55: =SUM(E55:O55)/21*75 + IF(AM55, -(MAX((U55-1800)/10, -40)), 0)+T55 + S55 + (P55-100)*0.5+AI55 +W55
B56: =B55+1 | C56: M | D56: =SUM(T56,AA56) | U56: =SUM(AM56,AP56,AS56,AV56,AY56,BE56,BB56) | X56: =AA56-W56 | Y56: ='0₦'!AE55*2 + 0 | AA56: =SUM(E56:O56)/21*75 + IF(AM56, -(MAX((U56-1800)/10, -40)), 0)+T56 + S56 + (P56-100)*0.5+AI56 +W56
B57: =B56+1 | C57: T | D57: =SUM(T57,AA57) | U57: =SUM(AM57,AP57,AS57,AV57,AY57,BE57,BB57) | X57: =AA57-W57 | Y57: ='0₦'!AE56*2 + 0 | AA57: =SUM(E57:O57)/21*75 + IF(AM57, -(MAX((U57-1800)/10, -40)), 0)+T57 + S57 + (P57-100)*0.5+AI57 +W57
B58: =B57+1 | C58: W | D58: =SUM(T58,AA58) | U58: =SUM(AM58,AP58,AS58,AV58,AY58,BE58,BB58) | X58: =AA58-W58 | Y58: ='0₦'!AE57*2 + 0 | AA58: =SUM(E58:O58)/21*75 + IF(AM58, -(MAX((U58-1800)/10, -40)), 0)+T58 + S58 + (P58-100)*0.5+AI58 +W58
B59: =B58+1 | C59: Th | D59: =SUM(T59,AA59) | U59: =SUM(AM59,AP59,AS59,AV59,AY59,BE59,BB59) | V59: =AVERAGE(U59:U65) | X59: =AA59-W59 | Y59: ='0₦'!AE58*2 + 0 | AA59: =SUM(E59:O59)/21*75 + IF(AM59, -(MAX((U59-1800)/10, -40)), 0)+T59 + S59 + (P59-100)*0.5+AI59 +W59 | AB59: =AVERAGE(AA59:AA65) | AC59: =AVERAGE(Y59:Y65) | AF59: =SUM(AE59:AE65)
B60: =B59+1 | C60: F | D60: =SUM(T60,AA60) | U60: =SUM(AM60,AP60,AS60,AV60,AY60,BE60,BB60) | X60: =AA60-W60 | Y60: ='0₦'!AE59*2 + 0 | AA60: =SUM(E60:O60)/21*75 + IF(AM60, -(MAX((U60-1800)/10, -40)), 0)+T60 + S60 + (P60-100)*0.5+AI60 +W60 | BM60: =SUM(BN60:BO66) | BN60: =COUNTIF('0₦'!L60:L66,"<>")*23 | BO60: 0
B61: =B60+1 | C61: S | D61: =SUM(T61,AA61) | U61: =SUM(AM61,AP61,AS61,AV61,AY61,BE61,BB61) | X61: =AA61-W61 | Y61: ='0₦'!AE60*2 + 0 | AA61: =SUM(E61:O61)/21*75 + IF(AM61, -(MAX((U61-1800)/10, -40)), 0)+T61 + S61 + (P61-100)*0.5+AI61 +W61
A62: =A34+1 | B62: =B61+1 | C62: S | D62: =SUM(T62,AA62) | U62: =SUM(AM62,AP62,AS62,AV62,AY62,BE62,BB62) | X62: =AA62-W62 | Y62: ='0₦'!AE61*2 + 0 | AA62: =SUM(E62:O62)/21*75 + IF(AM62, -(MAX((U62-1800)/10, -40)), 0)+T62 + S62 + (P62-100)*0.5+AI62 +W62
B63: =B62+1 | C63: M | D63: =SUM(T63,AA63) | U63: =SUM(AM63,AP63,AS63,AV63,AY63,BE63,BB63) | X63: =AA63-W63 | Y63: ='0₦'!AE62*2 + 0 | AA63: =SUM(E63:O63)/21*75 + IF(AM63, -(MAX((U63-1800)/10, -40)), 0)+T63 + S63 + (P63-100)*0.5+AI63 +W63
B64: =B63+1 | C64: T | D64: =SUM(T64,AA64) | U64: =SUM(AM64,AP64,AS64,AV64,AY64,BE64,BB64) | X64: =AA64-W64 | Y64: ='0₦'!AE63*2 + 0 | AA64: =SUM(E64:O64)/21*75 + IF(AM64, -(MAX((U64-1800)/10, -40)), 0)+T64 + S64 + (P64-100)*0.5+AI64 +W64
B65: =B64+1 | C65: W | D65: =SUM(T65,AA65) | U65: =SUM(AM65,AP65,AS65,AV65,AY65,BE65,BB65) | X65: =AA65-W65 | Y65: ='0₦'!AE64*2 + 0 | AA65: =SUM(E65:O65)/21*75 + IF(AM65, -(MAX((U65-1800)/10, -40)), 0)+T65 + S65 + (P65-100)*0.5+AI65 +W65
B66: =B65+1 | C66: Th | D66: =SUM(T66,AA66) | U66: =SUM(AM66,AP66,AS66,AV66,AY66,BE66,BB66) | V66: =AVERAGE(U66:U72) | X66: =AA66-W66 | Y66: ='0₦'!AE65*2 + 0 | AA66: =SUM(E66:O66)/21*75 + IF(AM66, -(MAX((U66-1800)/10, -40)), 0)+T66 + S66 + (P66-100)*0.5+AI66 +W66 | AB66: =AVERAGE(AA66:AA72) | AC66: =AVERAGE(Y66:Y72) | AF66: =SUM(AE66:AE72)
B67: =B66+1 | C67: F | D67: =SUM(T67,AA67) | U67: =SUM(AM67,AP67,AS67,AV67,AY67,BE67,BB67) | X67: =AA67-W67 | Y67: ='0₦'!AE66*2 + 0 | AA67: =SUM(E67:O67)/21*75 + IF(AM67, -(MAX((U67-1800)/10, -40)), 0)+T67 + S67 + (P67-100)*0.5+AI67 +W67 | BM67: =SUM(BN67:BO73) | BN67: =COUNTIF('0₦'!L67:L73,"<>")*23 | BO67: 0
B68: =B67+1 | C68: S | D68: =SUM(T68,AA68) | U68: =SUM(AM68,AP68,AS68,AV68,AY68,BE68,BB68) | X68: =AA68-W68 | Y68: ='0₦'!AE67*2 + 0 | AA68: =SUM(E68:O68)/21*75 + IF(AM68, -(MAX((U68-1800)/10, -40)), 0)+T68 + S68 + (P68-100)*0.5+AI68 +W68
A69: =A62+0.1 | B69: =B68+1 | C69: S | D69: =SUM(T69,AA69) | U69: =SUM(AM69,AP69,AS69,AV69,AY69,BE69,BB69) | X69: =AA69-W69 | Y69: ='0₦'!AE68*2 + 0 | AA69: =SUM(E69:O69)/21*75 + IF(AM69, -(MAX((U69-1800)/10, -40)), 0)+T69 + S69 + (P69-100)*0.5+AI69 +W69
B70: =B69+1 | C70: M | D70: =SUM(T70,AA70) | U70: =SUM(AM70,AP70,AS70,AV70,AY70,BE70,BB70) | X70: =AA70-W70 | Y70: ='0₦'!AE69*2 + 0 | AA70: =SUM(E70:O70)/21*75 + IF(AM70, -(MAX((U70-1800)/10, -40)), 0)+T70 + S70 + (P70-100)*0.5+AI70 +W70
B71: =B70+1 | C71: T | D71: =SUM(T71,AA71) | U71: =SUM(AM71,AP71,AS71,AV71,AY71,BE71,BB71) | X71: =AA71-W71 | Y71: ='0₦'!AE70*2 + 0 | AA71: =SUM(E71:O71)/21*75 + IF(AM71, -(MAX((U71-1800)/10, -40)), 0)+T71 + S71 + (P71-100)*0.5+AI71 +W71
B72: =B71+1 | C72: W | D72: =SUM(T72,AA72) | U72: =SUM(AM72,AP72,AS72,AV72,AY72,BE72,BB72) | X72: =AA72-W72 | Y72: ='0₦'!AE71*2 + 0 | AA72: =SUM(E72:O72)/21*75 + IF(AM72, -(MAX((U72-1800)/10, -40)), 0)+T72 + S72 + (P72-100)*0.5+AI72 +W72
B73: =B72+1 | C73: Th | D73: =SUM(T73,AA73) | U73: =SUM(AM73,AP73,AS73,AV73,AY73,BE73,BB73) | V73: =AVERAGE(U73:U79) | X73: =AA73-W73 | Y73: ='0₦'!AE72*2 + 0 | AA73: =SUM(E73:O73)/21*75 + IF(AM73, -(MAX((U73-1800)/10, -40)), 0)+T73 + S73 + (P73-100)*0.5+AI73 +W73 | AB73: =AVERAGE(AA73:AA79) | AC73: =AVERAGE(Y73:Y79) | AF73: =SUM(AE73:AE79)
B74: =B73+1 | C74: F | D74: =SUM(T74,AA74) | U74: =SUM(AM74,AP74,AS74,AV74,AY74,BE74,BB74) | X74: =AA74-W74 | Y74: ='0₦'!AE73*2 + 0 | AA74: =SUM(E74:O74)/21*75 + IF(AM74, -(MAX((U74-1800)/10, -40)), 0)+T74 + S74 + (P74-100)*0.5+AI74 +W74 | BM74: =SUM(BN74:BO80) | BN74: =COUNTIF('0₦'!L74:L80,"<>")*23 | BO74: 0
B75: =B74+1 | C75: S | D75: =SUM(T75,AA75) | U75: =SUM(AM75,AP75,AS75,AV75,AY75,BE75,BB75) | X75: =AA75-W75 | Y75: ='0₦'!AE74*2 + 0 | AA75: =SUM(E75:O75)/21*75 + IF(AM75, -(MAX((U75-1800)/10, -40)), 0)+T75 + S75 + (P75-100)*0.5+AI75 +W75
A76: =A69+0.1 | B76: =B75+1 | C76: S | D76: =SUM(T76,AA76) | U76: =SUM(AM76,AP76,AS76,AV76,AY76,BE76,BB76) | X76: =AA76-W76 | Y76: ='0₦'!AE75*2 + 0 | AA76: =SUM(E76:O76)/21*75 + IF(AM76, -(MAX((U76-1800)/10, -40)), 0)+T76 + S76 + (P76-100)*0.5+AI76 +W76
B77: =B76+1 | C77: M | D77: =SUM(T77,AA77) | U77: =SUM(AM77,AP77,AS77,AV77,AY77,BE77,BB77) | X77: =AA77-W77 | Y77: ='0₦'!AE76*2 + 0 | AA77: =SUM(E77:O77)/21*75 + IF(AM77, -(MAX((U77-1800)/10, -40)), 0)+T77 + S77 + (P77-100)*0.5+AI77 +W77
B78: =B77+1 | C78: T | D78: =SUM(T78,AA78) | U78: =SUM(AM78,AP78,AS78,AV78,AY78,BE78,BB78) | X78: =AA78-W78 | Y78: ='0₦'!AE77*2 + 0 | AA78: =SUM(E78:O78)/21*75 + IF(AM78, -(MAX((U78-1800)/10, -40)), 0)+T78 + S78 + (P78-100)*0.5+AI78 +W78
B79: =B78+1 | C79: W | D79: =SUM(T79,AA79) | U79: =SUM(AM79,AP79,AS79,AV79,AY79,BE79,BB79) | X79: =AA79-W79 | Y79: ='0₦'!AE78*2 + 0 | AA79: =SUM(E79:O79)/21*75 + IF(AM79, -(MAX((U79-1800)/10, -40)), 0)+T79 + S79 + (P79-100)*0.5+AI79 +W79
B80: =B79+1 | C80: Th | D80: =SUM(T80,AA80) | U80: =SUM(AM80,AP80,AS80,AV80,AY80,BE80,BB80) | V80: =AVERAGE(U80:U86) | X80: =AA80-W80 | Y80: ='0₦'!AE79*2 + 0 | AA80: =SUM(E80:O80)/21*75 + IF(AM80, -(MAX((U80-1800)/10, -40)), 0)+T80 + S80 + (P80-100)*0.5+AI80 +W80 | AB80: =AVERAGE(AA80:AA86) | AC80: =AVERAGE(Y80:Y86) | AF80: =SUM(AE80:AE86)
B81: =B80+1 | C81: F | D81: =SUM(T81,AA81) | U81: =SUM(AM81,AP81,AS81,AV81,AY81,BE81,BB81) | X81: =AA81-W81 | Y81: ='0₦'!AE80*2 + 0 | AA81: =SUM(E81:O81)/21*75 + IF(AM81, -(MAX((U81-1800)/10, -40)), 0)+T81 + S81 + (P81-100)*0.5+AI81 +W81 | BM81: =SUM(BN81:BO87) | BN81: =COUNTIF('0₦'!L81:L87,"<>")*23 | BO81: 0
B82: =B81+1 | C82: S | D82: =SUM(T82,AA82) | U82: =SUM(AM82,AP82,AS82,AV82,AY82,BE82,BB82) | X82: =AA82-W82 | Y82: ='0₦'!AE81*2 + 0 | AA82: =SUM(E82:O82)/21*75 + IF(AM82, -(MAX((U82-1800)/10, -40)), 0)+T82 + S82 + (P82-100)*0.5+AI82 +W82
A83: =A76+0.1 | B83: =B82+1 | C83: S | D83: =SUM(T83,AA83) | U83: =SUM(AM83,AP83,AS83,AV83,AY83,BE83,BB83) | X83: =AA83-W83 | Y83: ='0₦'!AE82*2 + 0 | AA83: =SUM(E83:O83)/21*75 + IF(AM83, -(MAX((U83-1800)/10, -40)), 0)+T83 + S83 + (P83-100)*0.5+AI83 +W83
B84: =B83+1 | C84: M | D84: =SUM(T84,AA84) | U84: =SUM(AM84,AP84,AS84,AV84,AY84,BE84,BB84) | X84: =AA84-W84 | Y84: ='0₦'!AE83*2 + 0 | AA84: =SUM(E84:O84)/21*75 + IF(AM84, -(MAX((U84-1800)/10, -40)), 0)+T84 + S84 + (P84-100)*0.5+AI84 +W84
B85: =B84+1 | C85: T | D85: =SUM(T85,AA85) | U85: =SUM(AM85,AP85,AS85,AV85,AY85,BE85,BB85) | X85: =AA85-W85 | Y85: ='0₦'!AE84*2 + 0 | AA85: =SUM(E85:O85)/21*75 + IF(AM85, -(MAX((U85-1800)/10, -40)), 0)+T85 + S85 + (P85-100)*0.5+AI85 +W85
B86: =B85+1 | C86: W | D86: =SUM(T86,AA86) | U86: =SUM(AM86,AP86,AS86,AV86,AY86,BE86,BB86) | X86: =AA86-W86 | Y86: ='0₦'!AE85*2 + 0 | AA86: =SUM(E86:O86)/21*75 + IF(AM86, -(MAX((U86-1800)/10, -40)), 0)+T86 + S86 + (P86-100)*0.5+AI86 +W86
B87: =B86+1 | C87: Th | D87: =SUM(T87,AA87) | U87: =SUM(AM87,AP87,AS87,AV87,AY87,BE87,BB87) | V87: =AVERAGE(U87:U93) | X87: =AA87-W87 | Y87: ='0₦'!AE86*2 + 0 | AA87: =SUM(E87:O87)/21*75 + IF(AM87, -(MAX((U87-1800)/10, -40)), 0)+T87 + S87 + (P87-100)*0.5+AI87 +W87 | AB87: =AVERAGE(AA87:AA93) | AC87: =AVERAGE(Y87:Y93) | AF87: =SUM(AE87:AE93)
B88: =B87+1 | C88: F | D88: =SUM(T88,AA88) | U88: =SUM(AM88,AP88,AS88,AV88,AY88,BE88,BB88) | X88: =AA88-W88 | Y88: ='0₦'!AE87*2 + 0 | AA88: =SUM(E88:O88)/21*75 + IF(AM88, -(MAX((U88-1800)/10, -40)), 0)+T88 + S88 + (P88-100)*0.5+AI88 +W88 | BM88: =SUM(BN88:BO94) | BN88: =COUNTIF('0₦'!L88:L94,"<>")*23 | BO88: 0
B89: =B88+1 | C89: S | D89: =SUM(T89,AA89) | U89: =SUM(AM89,AP89,AS89,AV89,AY89,BE89,BB89) | X89: =AA89-W89 | Y89: ='0₦'!AE88*2 + 0 | AA89: =SUM(E89:O89)/21*75 + IF(AM89, -(MAX((U89-1800)/10, -40)), 0)+T89 + S89 + (P89-100)*0.5+AI89 +W89
A90: =A83+0.1 | B90: =B89+1 | C90: S | D90: =SUM(T90,AA90) | U90: =SUM(AM90,AP90,AS90,AV90,AY90,BE90,BB90) | X90: =AA90-W90 | Y90: ='0₦'!AE89*2 + 0 | AA90: =SUM(E90:O90)/21*75 + IF(AM90, -(MAX((U90-1800)/10, -40)), 0)+T90 + S90 + (P90-100)*0.5+AI90 +W90
B91: =B90+1 | C91: M | D91: =SUM(T91,AA91) | U91: =SUM(AM91,AP91,AS91,AV91,AY91,BE91,BB91) | X91: =AA91-W91 | Y91: ='0₦'!AE90*2 + 0 | AA91: =SUM(E91:O91)/21*75 + IF(AM91, -(MAX((U91-1800)/10, -40)), 0)+T91 + S91 + (P91-100)*0.5+AI91 +W91
B92: =B91+1 | C92: T | D92: =SUM(T92,AA92) | U92: =SUM(AM92,AP92,AS92,AV92,AY92,BE92,BB92) | X92: =AA92-W92 | Y92: ='0₦'!AE91*2 + 0 | AA92: =SUM(E92:O92)/21*75 + IF(AM92, -(MAX((U92-1800)/10, -40)), 0)+T92 + S92 + (P92-100)*0.5+AI92 +W92
B93: =B92+1 | C93: W | D93: =SUM(T93,AA93) | U93: =SUM(AM93,AP93,AS93,AV93,AY93,BE93,BB93) | X93: =AA93-W93 | Y93: ='0₦'!AE92*2 + 0 | AA93: =SUM(E93:O93)/21*75 + IF(AM93, -(MAX((U93-1800)/10, -40)), 0)+T93 + S93 + (P93-100)*0.5+AI93 +W93
B94: =B93+1 | C94: Th | D94: =SUM(T94,AA94) | U94: =SUM(AM94,AP94,AS94,AV94,AY94,BE94,BB94) | V94: =AVERAGE(U94:U100) | X94: =AA94-W94 | Y94: ='0₦'!AE93*2 + 0 | AA94: =SUM(E94:O94)/21*75 + IF(AM94, -(MAX((U94-1800)/10, -40)), 0)+T94 + S94 + (P94-100)*0.5+AI94 +W94 | AB94: =AVERAGE(AA94:AA100) | AC94: =AVERAGE(Y94:Y100) | AF94: =SUM(AE94:AE100)
B95: =B94+1 | C95: F | D95: =SUM(T95,AA95) | U95: =SUM(AM95,AP95,AS95,AV95,AY95,BE95,BB95) | X95: =AA95-W95 | Y95: ='0₦'!AE94*2 + 0 | AA95: =SUM(E95:O95)/21*75 + IF(AM95, -(MAX((U95-1800)/10, -40)), 0)+T95 + S95 + (P95-100)*0.5+AI95 +W95 | BM95: =SUM(BN95:BO101) | BN95: =COUNTIF('0₦'!L95:L101,"<>")*23 | BO95: 0
B96: =B95+1 | C96: S | D96: =SUM(T96,AA96) | U96: =SUM(AM96,AP96,AS96,AV96,AY96,BE96,BB96) | X96: =AA96-W96 | Y96: ='0₦'!AE95*2 + 0 | AA96: =SUM(E96:O96)/21*75 + IF(AM96, -(MAX((U96-1800)/10, -40)), 0)+T96 + S96 + (P96-100)*0.5+AI96 +W96
A97: =A62+1 | B97: =B96+1 | C97: S | D97: =SUM(T97,AA97) | U97: =SUM(AM97,AP97,AS97,AV97,AY97,BE97,BB97) | X97: =AA97-W97 | Y97: ='0₦'!AE96*2 + 0 | AA97: =SUM(E97:O97)/21*75 + IF(AM97, -(MAX((U97-1800)/10, -40)), 0)+T97 + S97 + (P97-100)*0.5+AI97 +W97
B98: =B97+1 | C98: M | D98: =SUM(T98,AA98) | U98: =SUM(AM98,AP98,AS98,AV98,AY98,BE98,BB98) | X98: =AA98-W98 | Y98: ='0₦'!AE97*2 + 0 | AA98: =SUM(E98:O98)/21*75 + IF(AM98, -(MAX((U98-1800)/10, -40)), 0)+T98 + S98 + (P98-100)*0.5+AI98 +W98
B99: =B98+1 | C99: T | D99: =SUM(T99,AA99) | U99: =SUM(AM99,AP99,AS99,AV99,AY99,BE99,BB99) | X99: =AA99-W99 | Y99: ='0₦'!AE98*2 + 0 | AA99: =SUM(E99:O99)/21*75 + IF(AM99, -(MAX((U99-1800)/10, -40)), 0)+T99 + S99 + (P99-100)*0.5+AI99 +W99
B100: =B99+1 | C100: W | D100: =SUM(T100,AA100) | U100: =SUM(AM100,AP100,AS100,AV100,AY100,BE100,BB100) | X100: =AA100-W100 | Y100: ='0₦'!AE99*2 + 0 | AA100: =SUM(E100:O100)/21*75 + IF(AM100, -(MAX((U100-1800)/10, -40)), 0)+T100 + S100 + (P100-100)*0.5+AI100 +W100
B101: =B100+1 | C101: Th | D101: =SUM(T101,AA101) | U101: =SUM(AM101,AP101,AS101,AV101,AY101,BE101,BB101) | V101: =AVERAGE(U101:U107) | X101: =AA101-W101 | Y101: ='0₦'!AE100*2 + 0 | AA101: =SUM(E101:O101)/21*75 + IF(AM101, -(MAX((U101-1800)/10, -40)), 0)+T101 + S101 + (P101-100)*0.5+AI101 +W101 | AB101: =AVERAGE(AA101:AA107) | AC101: =AVERAGE(Y101:Y107) | AF101: =SUM(AE101:AE107)
...

Sheet m5x2
B1: LX | C1: IM | D1: LR | E1: MC | G1: LX | H1: IM | I1: LR | J1: MC | L1: IM|LX | M1: LR | N1: MC | O1: AW | P1: MG | S1: S | T1: M | U1: T | V1: W | W1: Th | X1: F | Y1: S | Z1: ∑ | AF1: f694 | AL1: m5x2 | AN1: Review of the last week | AP1: What does success look like next week?
B2: Updates (30分) | G2: 1|1 (1:1) | L2: Execution Tracking | AB2: IM | AC2: MC | AD2: LR | AE2: r202 | AF2: Notes | AG2: # Participate | AH2: Rating | AI2: Weekly Updates | AJ2: Thing | AL2: 651
A3: 1.1 | R3: 1.1 | Z3: =SUM(S3:Y3) | AM3: MA | AN3: Kept bringing open units down despite the off season. | AP3: 1. Progress with hiring 2. Continue to bring down applications 3. 2 KN 47 Leases signed.
A4: =A3+0.1 | R4: 1.2 | Z4: =SUM(S4:Y4) | AM4: MA | AN4: 1. One kn47 lease signed, behind target, though top of funnel looks healthy 2. We got to offer out stage for the leasing specialist, which I think is great. 3. Portfolio total is now at 151, but I think we should count all of March as well. | AP4: 1. Roadmaps are not awful. 2. We have realistic goals for Q1. 3. We're in a good position for tc68. 4. Progress on roles and responsibilities.
A5: =A4+0.1 | R5: 1.3 | Z5: =SUM(S5:Y5) | AM5: EE | AN5: 1. Roadmaps were pretty good, and while I haven't had all the followups done, at least they are happening. 2. We are on path for the 3. Hit all of the goals | AP5: 1. Roadmaps are locked with a reporting cadence that I can check on. 2. Continue to make progress with roles and responsibilities. (Jesus + Stefanie) 3. We are on track for occupancy progress at kn47
A6: =A5+0.1 | R6: 1.4 | Z6: =SUM(S6:Y6) | AL6: 631 | AM6: EE | AN6: 1. We have a soft commitment for $10m
A7: =A3+1 | R7: 2.1 | Z7: =SUM(S7:Y7)
A8: =A7+0.1 | R8: 2.2 | Z8: =SUM(S8:Y8)
A9: =A8+0.1 | R9: 2.3 | Z9: =SUM(S9:Y9)
A10: =A9+0.1 | R10: 2.4 | Z10: =SUM(S10:Y10)
A11: =A7+1 | R11: 3.1 | Z11: =SUM(S11:Y11)
A12: =A11+0.1 | R12: 3.2 | Z12: =SUM(S12:Y12)
A13: =A12+0.1 | R13: 3.3 | Z13: =SUM(S13:Y13)
A14: =A13+0.1 | R14: 3.4 | Z14: =SUM(S14:Y14)
A15: =A14+0.1 | R15: 3.5 | Z15: =SUM(S15:Y15) | AL15: 857
A16: 4.1 | R16: 4.1 | Z16: =SUM(S16:Y16)
A17: =A16+0.1 | R17: 4.2 | Z17: =SUM(S17:Y17)
A18: =A17+0.1 | R18: 4.3 | Z18: =SUM(S18:Y18)
A19: =A18+0.1 | R19: =R18+0.1 | Z19: =SUM(S19:Y19)
A20: =A16+1 | R20: =R16+1 | Z20: =SUM(S20:Y20)
A21: =A20+0.1 | R21: =R20+0.1 | Z21: =SUM(S21:Y21)
A22: =A21+0.1 | O22: 3 | R22: =R21+0.1 | Z22: =SUM(S22:Y22)
A23: =A22+0.1 | R23: =R22+0.1 | Z23: =SUM(S23:Y23)
A24: =A20+1 | R24: =R20+1 | Z24: =SUM(S24:Y24)
A25: =A24+0.1 | R25: =R24+0.1 | Z25: =SUM(S25:Y25)
A26: =A25+0.1 | R26: =R25+0.1 | Z26: =SUM(S26:Y26)
A27: =A26+0.1 | R27: =R26+0.1 | Z27: =SUM(S27:Y27)
A28: =A27+0.1 | R28: =R27+0.1 | Z28: =SUM(S28:Y28)
A29: =A16+3 | R29: =R16+3 | Z29: =SUM(S29:Y29)
A30: =A29+0.1 | R30: =R29+0.1 | Z30: =SUM(S30:Y30)
A31: =A30+0.1 | R31: =R30+0.1 | Z31: =SUM(S31:Y31)
A32: =A31+0.1 | R32: =R31+0.1 | Z32: =SUM(S32:Y32)
A33: =A29+1 | R33: =R29+1 | Z33: =SUM(S33:Y33)
A34: =A33+0.1 | R34: =R33+0.1 | Z34: =SUM(S34:Y34)
A35: =A34+0.1 | R35: =R34+0.1 | Z35: =SUM(S35:Y35)
A36: =A35+0.1 | R36: =R35+0.1 | Z36: =SUM(S36:Y36)
A37: =A33+1 | R37: =R33+1 | Z37: =SUM(S37:Y37)
A38: =A37+0.1 | R38: =R37+0.1 | Z38: =SUM(S38:Y38)
A39: =A38+0.1 | R39: =R38+0.1 | Z39: =SUM(S39:Y39)
A40: =A39+0.1 | R40: =R39+0.1 | Z40: =SUM(S40:Y40)
A41: =A40+0.1 | R41: =R40+0.1 | Z41: =SUM(S41:Y41)
A42: =A29+3 | R42: =R29+3 | Z42: =SUM(S42:Y42)
A43: =A42+0.1 | R43: =R42+0.1 | Z43: =SUM(S43:Y43) | AL43: 890
A44: =A43+0.1 | R44: =R43+0.1 | Z44: =SUM(S44:Y44) | AM44: MA
A45: =A44+0.1 | R45: =R44+0.1 | Z45: =SUM(S45:Y45)
A46: =A42+1 | R46: =R42+1 | Z46: =SUM(S46:Y46) | AL46: 910 | AM46: MA
A47: =A46+0.1 | R47: =R46+0.1 | Z47: =SUM(S47:Y47) | AM47: mm
A48: =A47+0.1 | R48: =R47+0.1 | Z48: =SUM(S48:Y48)
A49: =A48+0.1 | R49: =R48+0.1 | Z49: =SUM(S49:Y49) | AM49: OL
A50: =A46+1 | R50: =R46+1 | Z50: =SUM(S50:Y50) | AL50: 600 | AM50: MA
A51: =A50+0.1 | R51: =R50+0.1 | Z51: =SUM(S51:Y51) | AM51: OL
A52: =A51+0.1 | R52: =R51+0.1 | Z52: =SUM(S52:Y52) | AM52: MA
A53: =A52+0.1 | R53: =R52+0.1 | Z53: =SUM(S53:Y53) | AM53: MA
A54: =A53+0.1 | R54: =R53+0.1 | Z54: =SUM(S54:Y54)
A55: 12.6 | R55: =R54+0.1 | Z55: =SUM(S55:Y55)
AO58: ='1₹+1s'!I58
AO59: ='1₹+1s'!I59
AO60: ='1₹+1s'!I60
AO61: ='1₹+1s'!I61
AO62: ='1₹+1s'!I62
AO63: ='1₹+1s'!I63
AO64: ='1₹+1s'!I64
AO65: ='1₹+1s'!I65
AO66: ='1₹+1s'!I66
AO67: ='1₹+1s'!I67
AO68: ='1₹+1s'!I68
AO69: ='1₹+1s'!I69
... AO1048576: ='1₹+1s'!I1048576

Sheet i9
B1: i9 | F1: BA | G1: CB | H1: Jli | I1: ZB | J1: AW | K1: MG | L1: JLa | N1: BA | O1: CB | P1: Jli | Q1: Jla | S1: f692 | T1: JLa | U1: BA | V1: CB | W1: Jli | X1: Jla | Y1: PP | Z1: AW | AA1: MG | AD1: S | AE1: M | AF1: T | AG1: W | AH1: Th | AI1: F | AJ1: S | AK1: ∑
B2: OL | U2: Execution Tracking Followups
A3: 1.1 | B3: MA | C3: ='1₹+1s'!H2 | D3: • I let the presentation become more stressful than it should have been. • Finally cleared out comms, but with a delay. | E3: • All habits (and think about what other org habits I should have) • Get RoB that I believe out • Have a plan for hiring each | AC3: 1.1 | AD3: 5 | AE3: =35 | AF3: =15+30+15+5+15 | AG3: 5 | AH3: 5 | AI3: 5 | AJ3: 5 | AK3: =SUM(AD3:AJ3)
A4: =A3+0.1 | B4: MA | C4: ='1₹+1s'!H3 | D4: • I didn't quite get to all habits. But I did do a RoB, along with a good SLT presentation, which I feel OK about. • Others may have liked the offsite, and I think we are trying to build a culture so I get it. Felt like a drain on my time. • I'm marking work social time as social time. | E4: • All Habits (including weekly update) • Rhythm of business established | AC4: 1.2 | AD4: 5 | AE4: =5+SUM(#REF!,30) | AF4: =45+30+30 | AG4: 5 | AH4: 0 | AI4: 0 | AJ4: =SUM(#REF!,#REF!,#REF!,#REF!,H4,#REF!,6,5) | AK4: =SUM(AD4:AJ4)
A5: =A4+0.1 | B5: EE | C5: ='1₹+1s'!H4 | D5: • Not a great showing at the promotions meeting. • SLT went pretty well. • Mario is presenting more which is good. | E5: •Offsite goes well •Hove a vision for how offsites work in the future •Get initial ramp docs for Andy | AC5: 1.3 | AD5: 5 | AE5: 5 | AF5: =30+S4 | AG5: =90+5+30 | AH5: 5 | AI5: 5 | AJ5: 5 | AK5: =SUM(AD5:AJ5)
A6: =A5+0.1 | C6: ='1₹+1s'!H5 | AC6: 1.4 | AD6: 5 | AE6: 65 | AF6: 35 | AG6: =25+5+23 | AH6: =15+5 | AI6: =5+15 | AJ6: 5 | AK6: =SUM(AD6:AJ6)
A7: =A3+1 | C7: ='1₹+1s'!H6 | AC7: 2.1 | AD7: 5 | AE7: =30+15+5+SUM(#REF!) | AF7: =5+15+30+15 | AG7: =35+10 | AH7: 15 | AI7: 5 | AJ7: =5+30+SUM(#REF!,#REF!,#REF!) | AK7: =SUM(AD7:AJ7)
A8: =A7+0.1 | C8: ='1₹+1s'!H7 | AC8: 2.2 | AD8: =5+15 | AE8: =5+15+15 | AF8: =5+20+25+8+15+60 | AG8: 5 | AH8: =19+5 | AI8: =5+100+SUM(#REF!,#REF!,#REF!) | AJ8: 5 | AK8: =SUM(AD8:AJ8)
A9: =A8+0.1 | C9: ='1₹+1s'!H8 | AC9: 2.3 | AD9: 0 | AE9: 0 | AF9: 5 | AG9: 0 | AH9: 0 | AI9: 5 | AJ9: 0 | AK9: =SUM(AD9:AJ9)
A10: =A9+0.1 | C10: ='1₹+1s'!H9 | AC10: 2.4 | AD10: =5 | AE10: =#REF!+5+10+#REF!+#REF! | AF10: =5+15+30+20+40 | AG10: 5 | AH10: =5+23+#REF!+#REF!+#REF!+H10 | AI10: 5 | AJ10: 5 | AK10: =SUM(AD10:AJ10)
A11: =A7+1 | C11: ='1₹+1s'!H10 | AC11: 3.1 | AD11: =SUM(#REF!+#REF!,#REF!,#REF!,#REF!,S11) | AE11: 5 | AF11: 5 | AG11: 5 | AI11: 5 | AK11: =SUM(AD11:AJ11)
A12: =A11+0.1 | C12: ='1₹+1s'!H11 | AC12: 3.2 | AD12: =5+SUM(#REF!,#REF!,#REF!,#REF!) | AE12: 5 | AF12: 5 | AG12: 5 | AH12: 5 | AI12: 65 | AK12: =SUM(AD12:AJ12)
A13: =A12+0.1 | C13: ='1₹+1s'!H12 | AC13: 3.3 | AH13: 5 | AK13: =SUM(AD13:AJ13)
A14: =A13+0.1 | C14: ='1₹+1s'!H13 | AC14: 3.4 | AE14: 5 | AF14: =5+S14 | AG14: =5+37 | AI14: 5 | AJ14: 5 | AK14: =SUM(AD14:AJ14)
A15: =A14+0.1 | C15: ='1₹+1s'!H14 | AC15: 3.5 | AD15: 5 | AH15: =45+30+18+60 | AI15: 5 | AJ15: =5+SUM(#REF!,#REF!,#REF!) | AK15: =SUM(AD15:AJ15)
A16: 4.1 | C16: ='1₹+1s'!H15 | AC16: 4.1 | AD16: =#REF!+55 | AE16: =45+5 | AF16: =5+#REF!+15 | AG16: =53+5 | AH16: =5+5 | AI16: 5 | AJ16: =5+75+11 | AK16: =SUM(AD16:AJ16)
A17: =A16+0.1 | C17: ='1₹+1s'!H14 | AC17: 4.2 | AD17: 5 | AE17: 5 | AF17: 15 | AG17: =S17+5 | AH17: =65 | AK17: =SUM(AD17:AJ17)
A18: =A17+0.1 | C18: ='1₹+1s'!H15 | AC18: 4.3 | AD18: 5 | AE18: 20 | AH18: 5 | AI18: =#REF!+5 | AJ18: 5 | AK18: =SUM(AD18:AJ18)
A19: =A18+0.1 | C19: ='1₹+1s'!H16 | AC19: =AC18+0.1 | AD19: =85 | AE19: 5 | AF19: =28+20+5 | AG19: 5 | AH19: 5 | AI19: 5 | AJ19: 5 | AK19: =SUM(AD19:AJ19)
A20: =A16+1 | C20: ='1₹+1s'!H17 | AC20: =AC16+1 | AD20: =30 | AE20: 5 | AI20: 5 | AJ20: 5 | AK20: =SUM(AD20:AJ20)
A21: =A20+0.1 | C21: ='1₹+1s'!H18 | AC21: =AC20+0.1 | AD21: 5 | AE21: 5 | AF21: 5 | AG21: =65+30 | AH21: 5 | AK21: =SUM(AD21:AJ21)
A22: =A21+0.1 | C22: ='1₹+1s'!H19 | Z22: 3 | AC22: =AC21+0.1 | AE22: 5 | AH22: =45+5 | AI22: =65 | AK22: =SUM(AD22:AJ22)
A23: =A22+0.1 | C23: ='1₹+1s'!H20 | AC23: =AC22+0.1 | AK23: =SUM(AD23:AJ23)
A24: =A20+1 | C24: ='1₹+1s'!H21 | AC24: =AC20+1 | AE24: 5 | AF24: 5 | AG24: 5 | AI24: 5 | AJ24: =65 | AK24: =SUM(AD24:AJ24)
A25: =A24+0.1 | C25: ='1₹+1s'!H22 | AC25: =AC24+0.1 | AI25: 35 | AK25: =SUM(AD25:AJ25)
A26: =A25+0.1 | C26: ='1₹+1s'!H23 | AC26: =AC25+0.1 | AD26: =35+12 | AE26: 5 | AF26: 5 | AG26: 5 | AH26: 5 | AJ26: 5 | AK26: =SUM(AD26:AJ26)
A27: =A26+0.1 | C27: ='1₹+1s'!H24 | AC27: =AC26+0.1 | AH27: 5 | AI27: 5 | AK27: =SUM(AD27:AJ27)
A28: =A27+0.1 | C28: ='1₹+1s'!H25 | O28: 30 | S28: =75 | V28: 15 | AC28: =AC27+0.1 | AD28: 5 | AE28: 5 | AF28: =S28+O28+5+15 | AK28: =SUM(AD28:AJ28)
A29: =A16+3 | C29: ='1₹+1s'!H26 | S29: 60 | AC29: =AC16+3 | AD29: 5 | AE29: 5 | AF29: 5 | AG29: 5 | AH29: =S29+5 | AK29: =SUM(AD29:AJ29)
A30: =A29+0.1 | C30: ='1₹+1s'!H27 | S30: 30 | AC30: =AC29+0.1 | AG30: =65 | AH30: 65 | AI30: 30 | AJ30: =S30 | AK30: =SUM(AD30:AJ30)
A31: =A30+0.1 | C31: ='1₹+1s'!H28 | AC31: =AC30+0.1 | AD31: =120+29 + 10 + 30 + 13 + 5 | AF31: 30 | AG31: =40+30 + 5 + 20 | AK31: =SUM(AD31:AJ31)
A32: =A31+0.1 | C32: ='1₹+1s'!H29 | AC32: =AC31+0.1 | AD32: 0 | AE32: =5+40 + 35 | AI32: 35 | AJ32: =65 | AK32: =SUM(AD32:AJ32)
A33: =A29+1 | C33: ='1₹+1s'!H30 | AC33: =AC29+1 | AD33: 0 | AE33: =30+5 + 60 | AK33: =SUM(AD33:AJ33)
A34: =A33+0.1 | C34: ='1₹+1s'!H31 | O34: 30 | S34: =30+30 | W34: 30 | AC34: =AC33+0.1 | AD34: =25 | AE34: =O34+5 | AH34: =S34+5 | AI34: =W34+5 | AK34: =SUM(AD34:AJ34)
A35: =A34+0.1 | C35: ='1₹+1s'!H32 | S35: =53 | AC35: =AC34+0.1 | AD35: 0 | AE35: =53+5 | AF35: =45+5 | AG35: 0 | AH35: =65 | AI35: =45+30+30+30+5 | AJ35: 0 | AK35: =SUM(AD35:AJ35)
A36: =A35+0.1 | C36: ='1₹+1s'!H33 | S36: =65+30 + 15 | Y36: 20 | AC36: =AC35+0.1 | AE36: =65+5 + 30 + 20 | AG36: =15 | AI36: =60+45 | AK36: =SUM(AD36:AJ36)
A37: =A33+1 | C37: ='1₹+1s'!H34 | U37: 45 | AC37: =AC33+1 | AF37: 20 | AI37: =U37+5 | AK37: =SUM(AD37:AJ37)
A38: =A37+0.1 | C38: ='1₹+1s'!H35 | AC38: =AC37+0.1 | AK38: =SUM(AD38:AJ38)
A39: =A38+0.1 | C39: ='1₹+1s'!H36 | AC39: =AC38+0.1 | AK39: =SUM(AD39:AJ39)
A40: =A39+0.1 | C40: ='1₹+1s'!H37 | AC40: =AC39+0.1 | AF40: 20 | AK40: =SUM(AD40:AJ40)
A41: =A40+0.1 | C41: ='1₹+1s'!H38 | AC41: =AC40+0.1 | AK41: =SUM(AD41:AJ41)
A42: =A29+3 | C42: ='1₹+1s'!H39 | N42: 30 | AC42: =AC29+3 | AI42: 30 | AK42: =SUM(AD42:AJ42)
A43: =A42+0.1 | C43: ='1₹+1s'!H40 | AC43: =AC42+0.1 | AG43: =30+30 | AK43: =SUM(AD43:AJ43)
A44: =A43+0.1 | C44: ='1₹+1s'!H41 | AC44: =AC43+0.1 | AK44: =SUM(AD44:AJ44)
A45: =A44+0.1 | C45: ='1₹+1s'!H42 | AC45: =AC44+0.1 | AK45: =SUM(AD45:AJ45)
A46: =A42+1 | C46: ='1₹+1s'!H43 | AC46: =AC42+1 | AK46: =SUM(AD46:AJ46) | AM46: #VALUE!
A47: =A46+0.1 | C47: ='1₹+1s'!H44 | AC47: =AC46+0.1 | AK47: =SUM(AD47:AJ47) | AM47: #VALUE!
A48: =A47+0.1 | C48: ='1₹+1s'!H47 | AC48: =AC47+0.1 | AK48: =SUM(AD48:AJ48)
A49: =A48+0.1 | C49: ='1₹+1s'!H48 | AC49: =AC48+0.1 | AK49: =SUM(AD49:AJ49)
A50: =A46+1 | C50: ='1₹+1s'!H49 | AC50: =AC46+1 | AK50: =SUM(AD50:AJ50)
A51: =A50+0.1 | C51: ='1₹+1s'!H50 | AC51: =AC50+0.1 | AK51: =SUM(AD51:AJ51)
A52: =A51+0.1 | C52: ='1₹+1s'!H51 | AC52: =AC51+0.1 | AK52: =SUM(AD52:AJ52)
A53: =A52+0.1 | C53: ='1₹+1s'!H52 | AC53: =AC52+0.1 | AK53: =SUM(AD53:AJ53)
A54: =A53+0.1 | C54: ='1₹+1s'!H53 | AC54: =AC53+0.1 | AK54: =SUM(AD54:AJ54)
A55: 12.6 | C55: ='1₹+1s'!H54 | AC55: =AC54+0.1 | AK55: =SUM(AD55:AJ55)
C56: ='1₹+1s'!H55
C57: ='1₹+1s'!H56

Sheet 1₦+
B1: 5 | C1: 5^1 s | D1: 5^1 g | E1: i9 HPM | F1: 社 + hcbp | G1: 时→ f692 | H1: f693 | I1: i9/m7 | J1: 1 -2₲ | K1: VM|LI|MSGR | L1: -1₦ checkin | M1: f694 | N1: 1 xk88 | O1: 1 xk87 | P1: 周末 + aos | Q1: 5^1*2 c084 | R1: s897 | S1: 5^1 hcmc | T1: 5^1 hcbc | U1: long o314 | V1: hcbd: groceries | W1: 5^1 hcme | X1: 出 罗 日 | Y1: 5^1 hci | Z1: 长冥想 | AA1: 业写 | AB1: 一起饭 | AC1: nails | AD1: AoS | AE1: family | AF1: s897 | AG1: relax {60} | AH1: 轩轩丰富 | AI1: 琪琪丰富 | AJ1: i447 | AK1: 对身 | AL1: f695 | AM1: kids nature | AN1: ∑ | AO1: avg | AQ1: 5^1 ₦ Efficiency Clearance
B2: p(t) | C2: 20 | D2: 20 | E2: 60 | F2: 30 | G2: 10 | H2: 30 | I2: 10 | J2: 13 | K2: 10 | L2: 10 | M2: 5 | N2: 5 | O2: 8 | P2: 20 | Q2: 15 | R2: =meta!C73 | S2: 8 | T2: 5 | U2: 30 | V2: 15 | W2: 30 | X2: 10 | Y2: 15 | Z2: 60 | AA2: 60 | AB2: 90 | AC2: 3 | AD2: 15 | AE2: 120 | AF2: 120 | AG2: 60 | AH2: 120 | AI2: 120 | AJ2: 20 | AK2: 60 | AL2: 10 | AM2: 120 | AN2: =SUM(C2:AL2)
B3: e(分) | C3: 45 | D3: 5 | E3: 60 | F3: 40 | G3: 30 | H3: 30 | I3: 40 | J3: 20 | K3: 20 | L3: 15 | M3: 10 | N3: 15 | O3: 30 | P3: 20 | Q3: 15 | R3: 30 | S3: 15 | T3: 15 | U3: 15 | V3: 20 | W3: 25 | X3: 20 | Y3: 15 | Z3: 30 | AA3: 80 | AB3: 100 | AC3: 3 | AD3: 15 | AE3: 120 | AF3: 120 | AG3: 60 | AH3: 120 | AI3: 120 | AJ3: 25 | AK3: 30 | AL3: 25 | AM3: 120 | AN3: =SUM(C3:AM3)
A4: sf21 | B4: 1.1 | C4: 45 | D4: 20 | F4: 35 | G4: 20 | H4: 30 | I4: 60 | J4: 20 | K4: 25 | L4: 15 | M4: 21 | N4: 15 | O4: 30 | P4: 20 | Q4: 15 | R4: 25 | S4: 10 | T4: 15 | U4: 22 | V4: 20 | W4: 30 | X4: 20 | Y4: 15 | Z4: 15 | AA4: 80 | AB4: =40+30+30 + 30 | AC4: 3 | AD4: 15 | AE4: =20+20+20 | AF4: 120 | AG4: 60 | AH4: 120 | AI4: 120 | AJ4: 25 | AK4: 20 | AL4: 25 | AM4: 120 | AN4: =SUM(C4:AL4) | AO4: =SUM(AN4:AN7)/(AN$3*4) | AP4: =AVERAGE(AO4:AO16)
